Workbook

Sheet Local HTA submissions
A1: Number | B1: EMEA team | C1: HTA body | D1: Subcategory | E1: Therapy area | F1: Indication | G1: Year | H1: End Year | I1: Scope of IQVIA support | J1: Outcome | K1: Product/indication | AA1: {=_xlfn.UNIQUE(B:B)} -> EMEA team | AB1: {=_xlfn.UNIQUE(C:C)} -> HTA body | AC1: {=_xlfn.UNIQUE(D:D)} -> Subcategory | AD1: {=_xlfn.UNIQUE(E:E)} -> Therapy area | AE1: {=_xlfn.UNIQUE(F:F)} -> Indication | AF1: {=_xlfn.UNIQUE(G:G)} -> Year | AG1: {=_xlfn.UNIQUE(H:H)} -> End Year | AH1: {=_xlfn.UNIQUE(I:I)} -> Scope of IQVIA support | AI1: {=_xlfn.UNIQUE(J:J)} -> Outcome | AJ1: {=_xlfn.UNIQUE(K:K)} -> Product/indication
A2: 1 | B2: England | C2: NICE | D2: NICE Technology appraisals | E2: Oncology | F2: Non metastatic castration refractory prostate cancer (potential resubmission) | G2: 2021 | H2: =G2 -> 2021 | I2: CEM adaptation, BIM, STA write-up, post-submission support | J2: Ongoing | K2: Enzalutamide | AA2: England | AB2: NICE | AC2: NICE Technology appraisals | AD2: Oncology | AE2: Non metastatic castration refractory prostate cancer (potential resubmission) | AF2: 2021 | AG2: 2021 | AH2: CEM adaptation, BIM, STA write-up, post-submission support | AI2: Ongoing | AJ2: Enzalutamide
A3: 2 | B3: England | C3: NICE | D3: NICE Technology appraisals | E3: Oncology | F3: Metastatic hormone-sensitive prostate cancer | G3: 2019 | H3: 2021 | I3: CEM validation, BIM, STA write up, strategy validation with KOLs, post submission support, SLR + updates, NMA | J3: Recommended | K3: Enzalutamide | AA3: Scotland | AB3: SMC | AC3: NHSE - Specialised commissioning | AD3: Blood and immune system | AE3: Metastatic hormone-sensitive prostate cancer | AF3: 2019 | AG3: 2020 | AH3: CEM validation, BIM, STA write up, strategy validation with KOLs, post submission support, SLR + updates, NMA | AI3: Recommended | AJ3: Roxadustat
A4: 3 | B4: England | C4: NICE | D4: NICE Technology appraisals | E4: Blood and immune system | F4: Anaemia in CKD | G4: 2021 | H4: =G4 -> 2021 | I4: CEM adaptation, BIM, STA write-up, post-submission support | J4: Ongoing | K4: Roxadustat | AA4: Wales | AB4: AWMSG | AC4: N/A | AD4: Gastroenterology | AE4: Anaemia in CKD | AF4: 2020 | AG4: 2019 | AH4: Early scientific advice, CEM, BIM, SLR, ITC, STA write-up, post-submission support | AI4: Postponed | AJ4: Filgotinib
A5: 4 | B5: England | C5: NICE | D5: NICE Technology appraisals | E5: Gastroenterology | F5: Moderate-to-severe ulcerative colitis | G5: 2021 | H5: =G5 -> 2021 | I5: CEM adaptation, BIM, STA write-up, post-submission support | J5: Ongoing | K5: Filgotinib | AA5: Ireland | AB5: NCPE | AC5: Other | AD5: Cardiovascular diseases | AE5: Moderate-to-severe ulcerative colitis | AF5: 2018 | AG5: 2018 | AH5: STA write-up, post-submission support | AI5: Withdrawn | AJ5: Cabozantinib for HCC
A6: 5 | B6: England | C6: NICE | D6: NICE Technology appraisals | E6: Oncology | F6: Oncology - solid tumour | G6: 2021 | H6: =G6 -> 2021 | I6: Early scientific advice, CEM, BIM, SLR, ITC, STA write-up, post-submission support | J6: Ongoing | K6: Cabozantinib for HCC | AA6: Germany | AB6: G-BA | AC6: AIFA Technology appraisals | AD6: Respiratory | AE6: Oncology - solid tumour | AF6: 2017 | AG6: 2017 | AH6: CEM adaptation, STA write-up | AI6: Not recommended | AJ6: Libtayo® for NSCLC
A7: 6 | B7: England | C7: NICE | D7: NICE Technology appraisals | E7: Oncology | F7: Oncology - solid tumour | G7: 2021 | H7: =G7 -> 2021 | I7: STA write-up, post-submission support | J7: Ongoing | K7: Libtayo® for NSCLC | AA7: Spain | AB7: N/A | AC7: 0 | AD7: Muscoloskeletal | AE7: Heart failure | AF7: 2016 | AG7: 2016 | AH7: CEM adaptation, BIM adaptation, Section B3 development, SLR update | AI7: Pending | AJ7: Jardiance® for HFrEF
A8: 7 | B8: England | C8: NICE | D8: NICE Technology appraisals | E8: Cardiovascular diseases | F8: Heart failure | G8: 2021 | H8: =G8 -> 2021 | I8: CEM adaptation, STA write-up | J8: Ongoing | K8: Jardiance® for HFrEF | AA8: Italy | AB8: AIFA | AD8: Other/None | AE8: Cystic fibrosis | AF8: 2015 | AG8: 2015 | AH8: CEM, BIM, STA write up | AI8: Full assessment requested | AJ8: ELX/TEZ/IVA
A9: 8 | B9: England | C9: NICE | D9: NICE Technology appraisals | E9: Respiratory | F9: Cystic fibrosis | G9: 2020 | H9: =G9 -> 2020 | I9: CEM adaptation, BIM adaptation, Section B3 development, SLR update | J9: Postponed | K9: ELX/TEZ/IVA | AA9: France | AB9: CEESP | AD9: Metabolic/Endocrine Disorders | AE9: Moderate-to-severe rheumatoid arthritis | AF9: 2014 | AG9: 2014 | AH9: CEM, BIM, STA write up | AI9: Recommended (x2) | AJ9: 0
A10: 9 | B10: England | C10: NICE | D10: NICE Technology appraisals | E10: Muscoloskeletal | F10: Moderate-to-severe rheumatoid arthritis | G10: 2020 | H10: =G10 -> 2020 | I10: CEM adaptation, BIM, STA write-up, post-submission support | J10: Recommended | K10: Filgotinib | AA10: Portugal | AB10: CT | AD10: Dermatology | AE10: Genetic disease | AF10: 2013 | AG10: 2013 | AH10: CEM validation, BIM, STA write up, post submission support | AI10: Delayed | AJ10: Upadacitinib (recommended for severe RA)
A11: 10 | B11: England | C11: NICE | D11: NICE Technology appraisals | E11: Other/None | F11: Genetic disease | G11: 2020 | H11: =G11 -> 2020 | I11: CEM, BIM, STA write up | J11: Ongoing | AA11: Greece | AB11: INFARMED | AD11: Infectious diseases | AE11: Oncology - haemato-oncology | AF11: 2012 | AG11: 2012 | AH11: CEM, BIM, STA write-up | AI11: Procedure completed - resubmitted | AJ11: Larotrectinib (VItrakvi®)for NTRK fusion
A12: 11 | B12: England | C12: NICE | D12: NICE Technology appraisals | E12: Oncology | F12: Oncology - haemato-oncology | G12: 2020 | H12: =G12 -> 2020 | I12: CEM, BIM, STA write up | J12: Ongoing | AA12: Netherlands | AB12: Greek HTA Committee | AD12: Ophthalmology | AE12: Cardiovascular disease | AF12: 0 | AG12: 0 | AH12: CEM adaptation, STA write-up, post-submission support | AI12: Procedure completed - significant additional benefit | AJ12: Liraglutide for obesity
A13: 12 | B13: England | C13: NICE | D13: NICE Technology appraisals | E13: Cardiovascular diseases | F13: Cardiovascular disease | G13: 2020 | H13: =G13 -> 2020 | I13: CEM validation, BIM, STA write up, post submission support | J13: Ongoing | AA13: Czech Republic | AB13: Zorginstituut Nederland | AD13: Gynacology | AE13: Oncology – haemato-oncology | AG13: Ongoing | AH13: CEM, BIM, STA write-up | AI13: Procedure completed - indication of a low additional benefit | AJ13: Liposomal cytarabine–daunorubicin for untreated acute myeloid leukaemia
A14: 13 | B14: England | C14: NICE | D14: NICE Technology appraisals | E14: Oncology | F14: Oncology - haemato-oncology | G14: 2019 | H14: =G14 -> 2019 | I14: CEM, BIM, STA write-up | J14: Withdrawn | AA14: Slovakia | AB14: Zorgverzekeraars Nederland | AD14: Digestive system | AE14: Oncology – solid tumour | AH14: CEM, BIM, STA write-up, post-submission support | AI14: Not submitted | AJ14: Baricitinib (recommended for severe RA)
A15: 14 | B15: England | C15: NICE | D15: NICE Technology appraisals | E15: Muscoloskeletal | F15: Moderate-to-severe rheumatoid arthritis | G15: 2019 | H15: =G15 -> 2019 | I15: CEM adaptation, STA write-up, post-submission support | J15: Recommended | K15: Upadacitinib (recommended for severe RA) | AA15: 0 | AB15: SUKL | AD15: Central nervous system | AE15: Type 1 diabetes | AH15: CEM, BIM, post submission support | AI15: 0 | AJ15: Iluvien
A16: 15 | B16: England | C16: NICE | D16: NICE Technology appraisals | E16: Oncology | F16: Oncology – haemato-oncology | G16: 2019 | H16: =G16 -> 2019 | I16: CEM, BIM, STA write-up | J16: Ongoing | AB16: ŠUKL | AD16: Mental and behavioural disorders | AE16: Electrolyte imbalance | AH16: SLR, adaptation of CEM and BIM, STA write up | AI16: Procedure completed - no additional benefit | AJ16: Bronchitol
A17: 16 | B17: England | C17: NICE | D17: NICE Technology appraisals | E17: Oncology | F17: Oncology – solid tumour | G17: 2019 | H17: =G17 -> 2019 | I17: CEM, BIM, STA write-up, post-submission support | J17: Recommended | K17: Larotrectinib (VItrakvi®)for NTRK fusion | AB17: 0 | AD17: Rare Disease | AE17: Metabolic disease | AH17: CEM adaptation, STA write up, post-submission support | AI17: Procedure completed - evidence of substantial additional benefit. | AJ17: Larotrectinib (Vitrakvi®) for NTRK fusion cancer
A18: 17 | B18: England | C18: NICE | D18: NICE Technology appraisals | E18: Oncology | F18: Oncology – solid tumour | G18: 2019 | H18: =G18 -> 2019 | I18: CEM, BIM, STA write-up | J18: Recommended | AD18: Vaccines | AE18: Acute myeloid leukaemia | AH18: FTA write up, post-submission support | AI18: Procedure completed - Orphan - additional benefit | AJ18: Leuprorelin acetate (Prostap®) for pre- and perimenopausal women with advanced breast cancer suitable for hormonal manipulation.
A19: 18 | B19: England | C19: NICE | D19: NICE Technology appraisals | E19: Metabolic/Endocrine Disorders | F19: Type 1 diabetes | G19: 2019 | H19: =G19 -> 2019 | I19: CEM, BIM, post submission support | J19: Recommended | AD19: Urology | AE19: Moderate-to-severe plaque psoriasis | AH19: CEM, BIM, STA write up, strategy validation with KOLs, post submission support, SLR + updates, NMA | AI19: Procedure completed - non-quantifiable additional benefit | AJ19: Miconazole
A20: 19 | B20: England | C20: NICE | D20: NICE Technology appraisals | E20: Cardiovascular diseases | F20: Electrolyte imbalance | G20: 2019 | H20: =G20 -> 2019 | I20: SLR, adaptation of CEM and BIM, STA write up | J20: Recommended | AD20: Neurology | AE20: Prostate cancer (high-risk nmCRPC) | AH20: SLRs, CEM, BIM, STA write up, post-submission support | AI20: Procedure completed - indication of significant additional benefit | AJ20: Dalbavancin
A21: 20 | B21: England | C21: NICE | D21: NICE Technology appraisals | E21: Oncology | F21: Oncology – solid tumour | G21: 2019 | H21: =G21 -> 2019 | I21: CEM, BIM, STA write-up | J21: Not recommended | AD21: Rheumatology | AE21: Hepatitis C | AH21: CEM, BIM, post-submission support | AI21: Completed | AJ21: Fidaxomicin
A22: 21 | B22: England | C22: NICE | D22: NICE Technology appraisals | E22: Metabolic/Endocrine Disorders | F22: Metabolic disease | G22: 2019 | H22: =G22 -> 2019 | I22: CEM adaptation, STA write up, post-submission support | J22: Recommended | K22: Liraglutide for obesity | AD22: Cardiology | AE22: Autologous chrondrocyte implantation | AH22: CEM/BIM revision, updated submission under CDF framework | AI22: Procedure completed - Indication of significant additional benefit | AJ22: Xtandi
A23: 22 | B23: England | C23: NICE | D23: NICE Technology appraisals | E23: Oncology | F23: Acute myeloid leukaemia | G23: 2018 | H23: =G23 -> 2018 | I23: CEM adaptation, STA write up, post-submission support | J23: Recommended | K23: Liposomal cytarabine–daunorubicin for untreated acute myeloid leukaemia | AD23: Rare disease/ Ophthalmology | AE23: 3rd Line Metastatic/Unresectable Gastrointestinal Stromal Tumour | AH23: SLR, CEM, BIM, STA write up | AI23: X | AJ23: Risankizumab
A24: 23 | B24: England | C24: NICE | D24: NICE Technology appraisals | E24: Dermatology | F24: Moderate-to-severe plaque psoriasis | G24: 2018 | H24: =G24 -> 2018 | I24: FTA write up, post-submission support | J24: Ongoing | AD24: Rare disease/ Rheumatology | AE24: Metastatic hepatocellular carcinoma | AH24: Economic/QoL SLR, CEM, BIM, STA write up | AI24: Class C | AJ24: Evolocumab
A25: 24 | B25: England | C25: NICE | D25: NICE Technology appraisals | E25: Oncology | F25: Acute myeloid leukaemia | G25: 2018 | H25: =G25 -> 2018 | I25: CEM, BIM, STA write up | J25: Ongoing | AD25: Dermatology/ Rheumatology | AE25: Visual impairment due to macular oedema secondary to branch retinal vein occlusion | AH25: Updated survival data analysis, adaptation of CEM, BIM, STA write up | AI25: Reimbursed | AJ25: Blinatumomab
A26: 25 | B26: England | C26: NICE | D26: NICE Technology appraisals | E26: Oncology | F26: Prostate cancer (high-risk nmCRPC) | G26: 2018 | H26: =G26 -> 2018 | I26: CEM, BIM, STA write up, strategy validation with KOLs, post submission support, SLR + updates, NMA | J26: Not recommended | K26: Enzalutamide | AD26: Hematology | AE26: Advanced hepatocellular carcinoma | AH26: SLR, CEM, BIM, STA write up, represented company at NICE | AI26: Re-negotiated | AJ26: Apixaban
A27: 26 | B27: England | C27: NICE | D27: NICE Technology appraisals | E27: Infectious diseases | F27: Hepatitis C | G27: 2017 | H27: =G27 -> 2017 | I27: CEM adaptation, STA write up, post-submission support | J27: Recommended | AD27: Medical device | AE27: Prostate cancer | AH27: CEM, MTA write up | AI27: Reimbursed & Innovative | AJ27: Anamorelin
A28: 27 | B28: England | C28: NICE | D28: NICE Technology appraisals | E28: Muscoloskeletal | F28: Autologous chrondrocyte implantation | G28: 2017 | H28: =G28 -> 2017 | I28: SLRs, CEM, BIM, STA write up, post-submission support | J28: Recommended | AD28: Surgical operation | AE28: Treatment of adults with castration-resistant prostate cancer, symptomatic bone metastases and no known visceral metastases. | AH28: CEM | AI28: EMA withdrawn | AJ28: Anamorelin
A29: 28 | B29: England | C29: NICE | D29: NICE Technology appraisals | E29: Oncology | F29: 3rd Line Metastatic/Unresectable Gastrointestinal Stromal Tumour | G29: 2017 | H29: =G29 -> 2017 | I29: CEM, BIM, STA write up | J29: Recommended | AD29: Psychiatry | AE29: Dupuytren's contracture | AH29: NMA, CEM, STA write up | AI29: Under AIFA evaluation | AJ29: Perampanel
A30: 29 | B30: England | C30: NICE | D30: NICE Technology appraisals | E30: Muscoloskeletal | F30: Moderate-to-severe rheumatoid arthritis | G30: 2017 | H30: =G30 -> 2017 | I30: CEM, BIM, post-submission support | J30: Recommended | K30: Baricitinib (recommended for severe RA) | AD30: Haemato-oncology | AE30: Type 2 diabetes | AH30: CEM, BIM, STA write up, strategy validation with KOLs, post submission support, OS adjustment | AI30: Completed (reimbursed) | AJ30: Empagliflozin/Metformin
A31: 30 | B31: England | C31: NICE | D31: NICE Technology appraisals | E31: Oncology | F31: Metastatic hepatocellular carcinoma | G31: 2016 | H31: =G31 -> 2016 | I31: CEM/BIM revision, updated submission under CDF framework | J31: Pending | AD31: 0 | AE31: Visual impairment due to diabetic macular oedema | AH31: CEM, BIM, STA write up, post submission support | AI31: Completed (under evaluation) | AJ31: Empagliflozin/Linagliptin
A32: 31 | B32: England | C32: NICE | D32: NICE Technology appraisals | E32: Ophthalmology | F32: Visual impairment due to macular oedema secondary to branch retinal vein occlusion | G32: 2016 | H32: =G32 -> 2016 | I32: SLR, CEM, BIM, STA write up | J32: Recommended | AE32: Visual impairment caused by macular oedema secondary to central retinal vein occlusion | AH32: CEM, BIM, STA write up, strategy validation with KOLs, post submission support, SLR, NMA | AI32: Completed (HTA positive assessment) | AJ32: Empagliflozin
A33: 32 | B33: England | C33: NICE | D33: NICE Technology appraisals | E33: Oncology | F33: Advanced hepatocellular carcinoma | G33: 2016 | H33: =G33 -> 2016 | I33: CEM, BIM, STA write up | J33: Recommended | AE33: Prostate cancer (chemo-naive mCRPC) | AH33: CSP dossier | AI33: Completed (succesful negotiation) | AJ33: Plitidepsin
A34: 33 | B34: England | C34: NICE | D34: NICE Technology appraisals | E34: Dermatology | F34: Moderate-to-severe plaque psoriasis | G34: 2015 | H34: =G34 -> 2015 | I34: Economic/QoL SLR, CEM, BIM, STA write up | J34: Recommended | AE34: Rivaroxaban for the treatment of deep vein thrombosis and prevention of recurrent deep vein thrombosis and pulmonary embolism | AH34: CEM adaptation, BIM, NPAF write up, NPAF strategy validation, post submission support | AI34: Completed (not submitted yet) | AJ34: Eribulin
A35: 34 | B35: England | C35: NICE | D35: NICE Technology appraisals | E35: Oncology | F35: Prostate cancer | G35: 2015 | H35: =G35 -> 2015 | I35: Updated survival data analysis, adaptation of CEM, BIM, STA write up | J35: Recommended | AE35: Wet age-related macular degeneration | AH35: SMC submission | AI35: Positive reimbursement advice | AJ35: Blinatumomab
A36: 35 | B36: England | C36: NICE | D36: NICE Technology appraisals | E36: Oncology | F36: Treatment of adults with castration-resistant prostate cancer, symptomatic bone metastases and no known visceral metastases. | G36: 2015 | H36: =G36 -> 2015 | I36: SLR, CEM, BIM, STA write up, represented company at NICE | J36: Recommended | AE36: Diabetic macular edema | AH36: CEM adaptation, NPAF write-up, post-subimssion support | AI36: XXX | AJ36: Velmanase alfa
A37: 36 | B37: England | C37: NICE | D37: NICE Technology appraisals | E37: Muscoloskeletal | F37: Dupuytren's contracture | G37: 2015 | H37: =G37 -> 2015 | I37: CEM, MTA write up | J37: Recommended | AE37: Prostate cancer (post-chemo mCRPC) | AH37: CEM development, SLR, NPAF write-up | AI37: Reimbursed after price negotiation | AJ37: Lenvatinib
A38: 37 | B38: England | C38: NICE | D38: NICE Technology appraisals | E38: Metabolic/Endocrine Disorders | F38: Type 2 diabetes | G38: 2015 | H38: =G38 -> 2015 | I38: CEM | J38: Recommended | AE38: Rivaroxaban for treating pulmonary embolism and preventing recurrent venous thromboembolism | AH38: CEM QC, SMC submission | AI38: Price negotiation recommended | AJ38: Guselkumab
A39: 38 | B39: England | C39: NICE | D39: NICE Technology appraisals | E39: Ophthalmology | F39: Visual impairment due to diabetic macular oedema | G39: 2014 | H39: =G39 -> 2014 | I39: NMA, CEM, STA write up | J39: Recommended | AE39: Rivaroxaban for the prevention of stroke and systemic embolism in people with atrial fibrillation | AH39: SLR, model updated, SMC submission | AJ39: Sirukumab
A40: 39 | B40: England | C40: NICE | D40: NICE Technology appraisals | E40: Ophthalmology | F40: Visual impairment caused by macular oedema secondary to central retinal vein occlusion | G40: 2014 | H40: =G40 -> 2014 | I40: SLR, CEM, BIM, STA write up | J40: Recommended | AE40: In combination with oral anti-diabetic therapy for the treatment of type 2 diabetes | AH40: SMC submission and post-admission support | AJ40: Brodalumab
A41: 40 | B41: England | C41: NICE | D41: NICE Technology appraisals | E41: Oncology | F41: Prostate cancer (chemo-naive mCRPC) | G41: 2014 | H41: =G41 -> 2014 | I41: CEM, BIM, STA write up, strategy validation with KOLs, post submission support, OS adjustment | J41: Recommended | K41: Enzalutamide | AE41: Hypercholesterolemia | AH41: CEM, SMC submission | AJ41: Nonacog beta pegol
A42: 41 | B42: England | C42: NICE | D42: NICE Technology appraisals | E42: Cardiovascular diseases | F42: Rivaroxaban for the treatment of deep vein thrombosis and prevention of recurrent deep vein thrombosis and pulmonary embolism | G42: 2013 | H42: =G42 -> 2013 | I42: SLR, CEM, BIM, STA write up, represented company at NICE | J42: Recommended | AE42: Type 2 diabetes | AH42: CEM and BIM QC, SMC submission | AJ42: Melatonin
A43: 42 | B43: England | C43: NICE | D43: NICE Technology appraisals | E43: Ophthalmology | F43: Wet age-related macular degeneration | G43: 2013 | H43: =G43 -> 2013 | I43: CEM, BIM, STA write up | J43: Recommended | AE43: Acute myeloid leukemia | AH43: CEM, NMA, SLR, SMC submission | AJ43: Cabozantinib
A44: 43 | B44: England | C44: NICE | D44: NICE Technology appraisals | E44: Metabolic/Endocrine Disorders | F44: Type 2 diabetes | G44: 2013 | H44: =G44 -> 2013 | I44: CEM | J44: Recommended | AE44: Plaque psoriasis | AH44: NPAF write up, postsubmission support | AJ44: Picato
A45: 44 | B45: England | C45: NICE | D45: NICE Technology appraisals | E45: Ophthalmology | F45: Diabetic macular edema | G45: 2013 | H45: =G45 -> 2013 | I45: CEM, BIM, STA write up, post submission support | J45: Recommended | K45: Iluvien | AE45: Hyperkalemia | AH45: CEM adaptation, BIM, NPAF write up, NPAF strategy validation, post submission support, SLR, NMA | AJ45: Ribociclib
A46: 45 | B46: England | C46: NICE | D46: NICE Technology appraisals | E46: Oncology | F46: Prostate cancer (post-chemo mCRPC) | G46: 2013 | H46: =G46 -> 2013 | I46: CEM, BIM, STA write up, strategy validation with KOLs, post submission support, SLR, NMA | J46: Recommended | K46: Enzalutamide | AE46: Contraception | AH46: CEM adaptation, BIM, Section 6 | AJ46: Naldemedin
A47: 46 | B47: England | C47: NICE | D47: NICE Technology appraisals | E47: Cardiovascular diseases | F47: Rivaroxaban for treating pulmonary embolism and preventing recurrent venous thromboembolism | G47: 2012 | H47: =G47 -> 2012 | I47: SLR, CEM, BIM, STA write up | J47: Recommended | AE47: Hepatocellular carcinoma | AH47: AWMSG submission | AJ47: Naldemedine
A48: 47 | B48: England | C48: NICE | D48: NICE Technology appraisals | E48: Cardiovascular diseases | F48: Rivaroxaban for the prevention of stroke and systemic embolism in people with atrial fibrillation | G48: 2012 | H48: =G48 -> 2012 | I48: SLR, CEM, BIM, STA write up, represented company at NICE | J48: Recommended | AE48: 3rd line metastatic GIST | AH48: Form A, Form B | AJ48: Multiple
A49: 48 | B49: England | C49: NICE | D49: NICE Technology appraisals | E49: Metabolic/Endocrine Disorders | F49: In combination with oral anti-diabetic therapy for the treatment of type 2 diabetes | G49: 2012 | H49: =G49 -> 2012 | I49: CEM, BIM, STA write up | J49: Recommended | AE49: Branch retinal vein occlusion | AH49: CEM, dossier post-submission support | AJ49: Carfilzomib
A50: 49 | B50: England | C50: NICE | D50: NICE Technology appraisals | E50: Metabolic/Endocrine Disorders | F50: Cystic fibrosis | G50: 2012 | H50: =G50 -> 2012 | I50: CEM, BIM, STA write up, post submission support | J50: Recommended | K50: Bronchitol | AE50: Oropharyngeal candidiasis (OPC) in immunocompromised patients | AH50: BIM, AWMSG dossier (Form B) | AJ50: Ide-Cel
A51: 51 | B51: England | C51: NICE | D51: NHSE - Specialised commissioning | E51: Metabolic/Endocrine Disorders | F51: Hypercholesterolemia | G51: 2017 | H51: =G51 -> 2017 | I51: CSP dossier | J51: Recommended | AE51: Acute bacterial skin and skin structure infections (ABSSSI) | AH51: CEM adaptation, BIM, Form B write up, AWMSG strategy validation, post submission support | AJ51: Liso-Cel
A52: 52 | B52: Scotland | C52: SMC | D52: N/A | E52: Oncology | F52: Metastatic hormone-sensitive prostate cancer | G52: 2021 | H52: =G52 -> 2021 | I52: CEM adaptation, BIM, NPAF write up, NPAF strategy validation, post submission support | J52: Ongoing | K52: Enzalutamide | AE52: Clostridium difficile infections | AH52: Rapid review, CEM adaptation, BIM, STA write-up, post-submission support | AJ52: Everolimus-Lenvatinib
A53: 53 | B53: Scotland | C53: SMC | D53: N/A | E53: Blood and immune system | F53: Anaemia in CKD | G53: 2021 | H53: =G53 -> 2021 | I53: CEM adaptation, BIM, STA write-up, post-submission support | J53: Ongoing | K53: Roxadustat | AE53: Haematology | AH53: Rapid review | AJ53: Cometriq
A54: 54 | B54: Scotland | C54: SMC | D54: N/A | E54: Gastroenterology | F54: Moderate-to-severe ulcerative colitis | G54: 2021 | H54: =G54 -> 2021 | I54: SMC submission | J54: Ongoing | K54: Filgotinib | AE54: Hepatic veno-occlusive disease | AH54: CEM adaptation, BIM, Rapid Review Form write up, Scoping Meeting, Full dossier, post submission support | AJ54: Palovaroten
A55: 55 | B55: Scotland | C55: SMC | D55: N/A | E55: Muscoloskeletal | F55: Moderate-to-severe rheumatoid arthritis | G55: 2021 | H55: =G55 -> 2021 | I55: SMC submission | J55: Ongoing | K55: Filgotinib | AE55: Non metastatic castration refractory prostate cancer | AH55: Full economic assessment | AJ55: Gazyvaro
A56: 56 | B56: Scotland | C56: SMC | D56: N/A | E56: Oncology | F56: Oncology - solid tumour | G56: 2021 | H56: =G56 -> 2021 | I56: CEM adaptation, NPAF write-up, post-subimssion support | J56: Ongoing | K56: Larotrectinib (Vitrakvi®) for NTRK fusion cancer | AE56: Rheumatoid arthritis | AH56: Economic assessment | AJ56: Isatuximab
A57: 57 | B57: Scotland | C57: SMC | D57: N/A | E57: Oncology | F57: Oncology - solid tumour | G57: 2020 | H57: =G57 -> 2020 | I57: CEM development, SLR, NPAF write-up | J57: Recommended | K57: Leuprorelin acetate (Prostap®) for pre- and perimenopausal women with advanced breast cancer suitable for hormonal manipulation. | AE57: Parkinson’s disease | AH57: NMA & economics sections only | AJ57: Cefiderocol
A58: 58 | B58: Scotland | C58: SMC | D58: N/A | E58: Muscoloskeletal | F58: Moderate-to-severe rheumatoid arthritis | G58: 2020 | H58: =G58 -> 2020 | I58: SMC submission | J58: Recommended | K58: Upadacitinib (recommended for severe RA) | AE58: Hepatitis C (2 indications) | AH58: Rapid review & economic assessment | AJ58: Ibalizumab
A59: 59 | B59: Scotland | C59: SMC | D59: N/A | E59: Metabolic/Endocrine Disorders | F59: Type 2 diabetes | G59: 2019 | H59: =G59 -> 2019 | I59: SMC submission | J59: Ongoing | AE59: Diabetes/endocrine disorders | AH59: Rapid review & full economic assessment | AJ59: Symkevi
A60: 60 | B60: Scotland | C60: SMC | D60: N/A | E60: Oncology | F60: Acute myeloid leukemia | G60: 2019 | H60: =G60 -> 2019 | I60: SMC submission | J60: Ongoing | AE60: Infections | AH60: Derivation of the appropriate comparator therapy for early G-BA consultation; Study design consultation | AJ60: Icosapent ethyl
A61: 61 | B61: Scotland | C61: SMC | D61: N/A | E61: Dermatology | F61: Plaque psoriasis | G61: 2019 | H61: =G61 -> 2019 | I61: SMC submission | J61: Ongoing | AE61: Ocular health | AH61: Full AMNOG dossier | AJ61: Sotorasib
A62: 62 | B62: Scotland | C62: SMC | D62: N/A | E62: Metabolic/Endocrine Disorders | F62: Hyperkalemia | G62: 2018 | H62: =G62 -> 2018 | I62: SMC submission | J62: Ongoing | AE62: Cancer (2 indications) | AH62: Development of pricing and reimbursement strategy Health Technology Assessment (HTA) dossier Netherlands | AJ62: AMG 330
A63: 63 | B63: Scotland | C63: SMC | D63: N/A | E63: Oncology | F63: Prostate cancer (high-risk nmCRPC) | G63: 2018 | H63: =G63 -> 2018 | I63: CEM adaptation, BIM, NPAF write up, NPAF strategy validation, post submission support | J63: Not recommended | K63: Enzalutamide | AE63: Pulmonary hypertension | AH63: Health economic evaluation Evaluation of avoidable treatment costs of cardiovascular events. | AJ63: CAR T
A64: 64 | B64: Scotland | C64: SMC | D64: N/A | E64: Gynacology | F64: Contraception | G64: 2017 | H64: =G64 -> 2017 | I64: CEM QC, SMC submission | J64: Recommended | AE64: LDL cholesterol reducer | AH64: AMNOG Dossier resubmission | AJ64: Lenvima plus Everolimus
A65: 65 | B65: Scotland | C65: SMC | D65: N/A | E65: Oncology | F65: Hepatocellular carcinoma | G65: 2016 | H65: =G65 -> 2016 | I65: SLR, model updated, SMC submission | J65: Recommended | AE65: Acute B-cell lymphoblastic leukemia | AH65: Parts of AMNOG dossier | AJ65: Lenvatinib plus Pembrolizumab
A66: 66 | B66: Scotland | C66: SMC | D66: N/A | E66: Oncology | F66: 3rd line metastatic GIST | G66: 2015 | H66: =G66 -> 2015 | I66: SMC submission and post-admission support | J66: Recommended | AE66: Treatment and prophylaxis of venous thrombosis and pulmonary embolism | AH66: 0 | AJ66: Lumoxiti
A67: 67 | B67: Scotland | C67: SMC | D67: N/A | E67: Oncology | F67: Prostate cancer | G67: 2015 | H67: =G67 -> 2015 | I67: CEM, SMC submission | J67: Recommended | AE67: Non-Small Cell Lung Cancer | AH67: Strategic consulting | AJ67: Cabozantinib-Nivolumab
A68: 68 | B68: Scotland | C68: SMC | D68: N/A | E68: Metabolic/Endocrine Disorders | F68: Type 2 diabetes | G68: 2015 | H68: =G68 -> 2015 | I68: CEM, SMC submission | J68: Recommended | AE68: Epilepsy | AH68: Early G-BA advice | AJ68: Depression
A69: 69 | B69: Scotland | C69: SMC | D69: N/A | E69: Metabolic/Endocrine Disorders | F69: Type 2 diabetes | G69: 2015 | H69: =G69 -> 2015 | I69: CEM | J69: Recommended | AE69: Type-2-Diabetes | AH69: Systematic Literature- and study registry search and Delphi Panel | AJ69: Ponesimod
A70: 70 | B70: Scotland | C70: SMC | D70: N/A | E70: Gynacology | F70: Contraception | G70: 2015 | H70: =G70 -> 2015 | I70: CEM and BIM QC, SMC submission | J70: Recommended | AE70: Multiple myoloma | AH70: G-BA advice | AJ70: Tralokinumab
A71: 71 | B71: Scotland | C71: SMC | D71: N/A | E71: Ophthalmology | F71: Branch retinal vein occlusion | G71: 2015 | H71: =G71 -> 2015 | I71: CEM, NMA, SLR, SMC submission | J71: Recommended | AE71: Breast cancer | AH71: Derivation of the appropriate comparator therapy for early G-BA consultation | AJ71: Cladribin
A72: 72 | B72: Scotland | C72: SMC | D72: N/A | E72: Oncology | F72: Prostate cancer (chemo-naive mCRPC) | G72: 2015 | H72: =G72 -> 2015 | I72: CEM adaptation, BIM, NPAF write up, NPAF strategy validation, post submission support | J72: Recommended | K72: Enzalutamide | AE72: Alpha-Mannosidose | AH72: Network meta-analysis (NMA) of seven active ingredients Analysis of weak points of the NMA Publication of the results Statement on IQWiG's NMA | AJ72: Luxturna
A73: 73 | B73: Scotland | C73: SMC | D73: N/A | E73: Infectious diseases | F73: Oropharyngeal candidiasis (OPC) in immunocompromised patients | G73: 2015 | H73: =G73 -> 2015 | I73: NPAF write up, postsubmission support | J73: Not recommended | K73: Miconazole | AE73: Hemophilia B | AH73: Horizon scanning Best-practice-derived recommendations | AJ73: Elranatamab
A74: 74 | B74: Scotland | C74: SMC | D74: N/A | E74: Infectious diseases | F74: Acute bacterial skin and skin structure infections (ABSSSI) | G74: 2015 | H74: =G74 -> 2015 | I74: CEM adaptation, BIM, NPAF write up, NPAF strategy validation, post submission support, SLR, NMA | J74: Recommended | K74: Dalbavancin | AE74: non-metastatic castration-resistant prostate cancer | AH74: Comprehensive overview of HTA processes Identification of hurdles and success factors Best-practice-derived recommendations | AJ74: Cemiplimab
A75: 75 | B75: Scotland | C75: SMC | D75: N/A | E75: Oncology | F75: Prostate cancer (post-chemo mCRPC) | G75: 2013 | H75: =G75 -> 2013 | I75: CEM adaptation, BIM, NPAF write up, NPAF strategy validation, post submission support | J75: Recommended | K75: Enzalutamide | AE75: Sleep disorders | AH75: Pricing and reimbursment | AJ75: Olipudase Alfa
A76: 76 | B76: Scotland | C76: SMC | D76: N/A | E76: Metabolic/Endocrine Disorders | F76: Cystic fibrosis | G76: 2012 | H76: =G76 -> 2012 | I76: CEM adaptation, BIM, NPAF write up, NPAF strategy validation, post submission support | J76: Recommended | K76: Bronchitol | AE76: Non-hyperkeratotic, non-hypertrophic actinic keratoses | AH76: BIM | AJ76: Levofloxacin
A77: 77 | B77: Scotland | C77: SMC | D77: N/A | E77: Infectious diseases | F77: Clostridium difficile infections | G77: 2012 | H77: =G77 -> 2012 | I77: CEM adaptation, BIM, NPAF write up, NPAF strategy validation, post submission support, SLR, NMA | J77: Recommended | K77: Fidaxomicin | AE77: ALL and DLBCL | AH77: DV | AJ77: Levantinib plus pembrolizumab
A78: 78 | B78: Scotland | C78: SMC | D78: N/A | E78: Respiratory | F78: Cystic fibrosis | G78: 2020 | H78: =G78 -> 2020 | I78: CEM adaptation, BIM, Section 6 | J78: Postponed | K78: ELX/TEZ/IVA | AE78: Opioid-induced constipation | AH78: DV, BIM | AJ78: Cabozantinib in Combination with Atezolizumab
A79: 79 | B79: Wales | C79: AWMSG | D79: N/A | E79: Metabolic/Endocrine Disorders | F79: Type 2 diabetes | G79: 2019 | H79: =G79 -> 2019 | I79: AWMSG submission | J79: Ongoing | AE79: VWF | AH79: Burden of disease economic model | AJ79: MK-7110
A80: 80 | B80: Wales | C80: AWMSG | D80: N/A | E80: Oncology | F80: Haematology | G80: 2018 | H80: =G80 -> 2018 | I80: Form A, Form B | J80: Recommended | AE80: Other | AH80: DV, BIM, CEM | AJ80: Molnupiravir
A81: 81 | B81: Wales | C81: AWMSG | D81: N/A | E81: Gynacology | F81: Contraception | G81: 2018 | H81: =G81 -> 2018 | I81: CEM, dossier post-submission support | J81: Recommended | AE81: Acute Lymphoblastic Leukemia | AH81: CEM, BIM | AJ81: Zepatier
A82: 82 | B82: Wales | C82: AWMSG | D82: N/A | E82: Metabolic/Endocrine Disorders | F82: Type 2 diabetes | G82: 2016 | H82: =G82 -> 2016 | I82: BIM, AWMSG dossier (Form B) | J82: Recommended | AE82: Relapsed and refractory multiple myeloma | AH82: VD | AJ82: Rovi
A83: 83 | B83: Wales | C83: AWMSG | D83: N/A | E83: Infectious diseases | F83: Clostridium difficile infections | G83: 2015 | H83: =G83 -> 2015 | I83: CEM adaptation, BIM, Form B write up, AWMSG strategy validation, post submission support | J83: Recommended | AE83: CAR-T cell therapy | AH83: Pricing stategy and position dosier | AJ83: Ibalizumab
A84: 84 | B84: Wales | C84: AWMSG | D84: N/A | E84: Cardiovascular diseases | F84: Hepatic veno-occlusive disease | G84: 2013 | H84: =G84 -> 2013 | I84: BIM, AWMSG dossier (Form B) | J84: Recommended | AE84: Renal cell carcinoma (2L) | AH84: Economic model | AJ84: Symkevi®
A85: 85 | B85: Ireland | C85: NCPE | D85: N/A | E85: Oncology | F85: Non metastatic castration refractory prostate cancer | G85: 2021 | H85: =G85 -> 2021 | I85: CEM adaptation, BIM, STA write-up, post-submission support | J85: Ongoing | K85: Xtandi | AE85: Medullary thyroid carcinoma | AH85: Core Diabetes Model | AJ85: Tysabri®
A86: 86 | B86: Ireland | C86: NCPE | D86: N/A | E86: Oncology | F86: Metastatic hormone-sensitive prostate cancer | G86: 2021 | H86: =G86 -> 2021 | I86: Rapid review, CEM adaptation, BIM, STA write-up, post-submission support | J86: Ongoing | K86: Xtandi | AE86: Fibrodysplasia ossificans progressiva | AH86: P&R Dossier Development | AJ86: Natpar
A87: 87 | B87: Ireland | C87: NCPE | D87: N/A | E87: Blood and immune system | F87: Anaemia in CKD | G87: 2021 | H87: =G87 -> 2021 | I87: CEM adaptation, BIM, STA write-up, post-submission support | J87: Ongoing | K87: Roxadustat | AE87: Follicular lymphoma (1L) | AH87: P&R Dossier Development Pharmacoeconomics Models Adaptation | AJ87: Enhertu®
A88: 88 | B88: Ireland | C88: NCPE | D88: N/A | E88: Digestive system | F88: Moderate-to-severe ulcerative colitis | G88: 2021 | H88: =G88 -> 2021 | I88: Rapid review | J88: Pending | K88: Filgotinib | AE88: Chronic lymphocytic leukemia | AH88: P&R Dossier Development Support with AIFA negotiation | AJ88: PLASMA EXCHANGE WITH ALBUMIN
A89: 89 | B89: Ireland | C89: NCPE | D89: N/A | E89: Muscoloskeletal | F89: Rheumatoid arthritis | G89: 2020 | H89: =G89 -> 2020 | I89: Rapid review | J89: Recommended | K89: Filgotinib | AE89: Refractory follicular lymphoma | AH89: P&R Dossier Development Pharmacoeconomics Models Adaptation Innovativeness request | AJ89: Budget impact of NACOs reimbursment in DVT and EP
A90: 90 | B90: Ireland | C90: NCPE | D90: N/A | E90: Muscoloskeletal | F90: Rheumatoid arthritis | G90: 2019 | H90: =G90 -> 2019 | I90: Rapid review | J90: Ongoing | AE90: Multiple myeloma (3L) | AH90: Pharmacoeconomics Models Adaptation | AJ90: Risperidone ISM®
A91: 91 | B91: Ireland | C91: NCPE | D91: N/A | E91: Dermatology | F91: Plaque psoriasis | G91: 2019 | H91: =G91 -> 2019 | I91: Rapid review | J91: Full assessment requested | K91: Risankizumab | AE91: Antibiotics | AH91: Pharmacoeconomics Models Adaptation Innovativeness request | AJ91: Remodulin®
A92: 92 | B92: Ireland | C92: NCPE | D92: N/A | E92: Oncology | F92: Prostate cancer (high-risk nmCRPC) | G92: 2019 | H92: =G92 -> 2019 | I92: CEM adaptation, BIM, Rapid Review Form write up, Scoping Meeting, Full dossier, post submission support | J92: Ongoing | K92: Enzalutamide | AE92: HIV | AH92: P&R Dossier Development Pharmacoeconomics Models Adaptation Innovativeness request Support with AIFA negotiation | AJ92: Somazina®
A93: 93 | B93: Ireland | C93: NCPE | D93: N/A | E93: Dermatology | F93: Plaque psoriasis | G93: 2020 | H93: =G93 -> 2020 | I93: Full economic assessment | J93: Ongoing | AE93: Risk of cardiovascular events among adults with elevated triglyceride levels | AH93: P&R Dossier development + CEM & BIM Adaptation | AJ93: Venclyxto®
A94: 94 | B94: Ireland | C94: NCPE | D94: N/A | E94: Central nervous system | F94: Parkinson’s disease | G94: 2018 | H94: =G94 -> 2018 | I94: Full economic assessment | J94: Pending | AE94: Renal cell carcinoma (1L) | AH94: Literature review + Expert panel + CEM & BIM adaptation + HTA application form | AJ94: Nilemdo®
A95: 95 | B95: Ireland | C95: NCPE | D95: N/A | E95: Infectious diseases | F95: Hepatitis C (2 indications) | G95: 2018 | H95: =G95 -> 2018 | I95: Rapid review | J95: Recommended (x2) | AE95: Endometrial carcinoma | AH95: Literature review + Expert panel + BIM development + HTA application form | AJ95: Adcetris®
A96: 96 | B96: Ireland | C96: NCPE | D96: N/A | E96: Metabolic/Endocrine Disorders | F96: Diabetes/endocrine disorders | G96: 2017 | H96: =G96 -> 2017 | I96: Economic assessment | J96: Pending | AE96: Hairy cell leucemia | AH96: Literature review + CEM & BIM adaptation + HTA application form | AJ96: Kengrexal®
A97: 97 | B97: Ireland | C97: NCPE | D97: N/A | E97: Infectious diseases | F97: Infections | G97: 2017 | H97: =G97 -> 2017 | I97: Rapid review | J97: Recommended | AE97: Renal cell carcinoma (1L) | AH97: Literature review + Expert panel + CEM & BIM adaptation + Objection Handler adaptation + Mock negotiation + HTA application form | AJ97: Dupilumab
A98: 98 | B98: Ireland | C98: NCPE | D98: N/A | E98: Ophthalmology | F98: Ocular health | G98: 2016 | H98: =G98 -> 2016 | I98: NMA & economics sections only | J98: Pending | AE98: Psoriatic arthritis | AH98: Literature review + Expert panel + CEM, CMM & BIM adaptation + Objection Handler adaptation + Mock negotiation + HTA application form | AJ98: Braftovi® & Mektovi®
A99: 99 | B99: Ireland | C99: NCPE | D99: N/A | E99: Ophthalmology | F99: Ocular health | G99: 2015 | H99: =G99 -> 2015 | I99: Rapid review | J99: Recommended | AE99: Depression | AH99: Literature review + CEM & BIM adaptation + Objection Handler adaptation + Mock negotiation + HTA application form | AJ99: Ninlaro®
A100: 100 | B100: Ireland | C100: NCPE | D100: N/A | E100: Metabolic/Endocrine Disorders | F100: Diabetes/endocrine disorders | G100: 2016 | H100: =G100 -> 2016 | I100: Rapid review & economic assessment | J100: Delayed | AE100: Mulitiple sclerosis | AH100: Literature review + CEM, CMM & BIM adaptation + HTA application form | AJ100: Upadacitinib (Rinvoq®)
...

Sheet HTA scientific advice
A1: HTA body | B1: Regulatory body, if included | C1: Therapy area | D1: Indication | E1: Year | F1: Product | J1: {=_xlfn.UNIQUE(A:A)} -> HTA body | K1: {=_xlfn.UNIQUE(B:B)} -> Regulatory body, if included | L1: {=_xlfn.UNIQUE(C:C)} -> Therapy area | M1: {=_xlfn.UNIQUE(D:D)} -> Indication | N1: {=_xlfn.UNIQUE(E:E)} -> Year | O1: {=_xlfn.UNIQUE(F:F)} -> Product
A2: CADTH | B2: N/A | C2: Dermatology | D2: Atopic dermatitis | E2: 2018 | F2: nemolizumab | J2: CADTH | K2: N/A | L2: Dermatology | M2: Atopic dermatitis | N2: 2018 | O2: nemolizumab
A3: G-BA | B3: N/A | C3: Dermatology | D3: Atopic dermatitis | E3: 2018 | F3: nemolizumab | J3: G-BA | K3: EMA’s adaptive pathway process | L3: Haemato-oncology | M3: Atopic dermatitis | N3: 2021 | O3: Elrinatamab
A4: HAS | B4: N/A | C4: Dermatology | D4: Atopic dermatitis | E4: 2018 | F4: nemolizumab | J4: HAS | K4: 0 | L4: Nephrology | M4: Multiple Myeloma | N4: 2020 | O4: Axicabtagene ciloleucel (Yescarta®)
A5: NICE | B5: N/A | C5: Dermatology | D5: Atopic dermatitis | E5: 2018 | F5: nemolizumab | J5: NICE | L5: Oncology | M5: Relapsed or refractory diffuse large B cell lymphoma (DLBCL) and primary mediastinal large B cell lymphoma (PMBCL), after two or more lines of systemic therapy | N5: 2017 | O5: VIS649
A6: G-BA | B6: N/A | C6: Haemato-oncology | D6: Multiple Myeloma | E6: 2021 | F6: Elrinatamab | J6: ZIN | L6: Various | M6: Primary IgA Nephropathy | N6: 2019 | O6: IMAB362 as add on to mFOLFOX6 in 1L of CLDN18.2 positive
A7: HAS | B7: N/A | C7: Haemato-oncology | D7: Multiple Myeloma | E7: 2021 | F7: Elrinatamab | J7: EUnetHTA | L7: 0 | M7: HER2 negative metastatic gastric and gastroesophageal junction adenocarcinoma | N7: 2016 | O7: MEN1116
A8: NICE | B8: N/A | C8: Haemato-oncology | D8: Multiple Myeloma | E8: 2021 | F8: Elrinatamab | J8: Parallel EMA / HTA | M8: Breast Cancer | N8: 0 | O8: Enfortumab vedotin
A9: ZIN | B9: N/A | C9: Haemato-oncology | D9: Relapsed or refractory diffuse large B cell lymphoma (DLBCL) and primary mediastinal large B cell lymphoma (PMBCL), after two or more lines of systemic therapy | E9: 2020 | F9: Axicabtagene ciloleucel (Yescarta®) | J9: 0 | M9: First-line treatment of locally advanced or metastatic urothelial carcinoma | O9: PLacental eXpanded (PLX) cells
A10: HAS | B10: N/A | C10: Nephrology | D10: Primary IgA Nephropathy | E10: 2021 | F10: VIS649 | M10: Somatic cell therapy | O10: 0
A11: EUnetHTA | B11: N/A | C11: Oncology | D11: HER2 negative metastatic gastric and gastroesophageal junction adenocarcinoma | E11: 2017 | F11: IMAB362 as add on to mFOLFOX6 in 1L of CLDN18.2 positive | M11: 0 | O11: Elrinatanab
A12: G-BA | B12: N/A | C12: Oncology | D12: Breast Cancer | E12: 2021 | F12: MEN1116
A13: NICE | B13: N/A | C13: Oncology | D13: Breast Cancer | E13: 2021 | F13: MEN1116
A14: NICE | B14: N/A | C14: Oncology | D14: First-line treatment of locally advanced or metastatic urothelial carcinoma | E14: 2019 | F14: Enfortumab vedotin
A15: Parallel EMA / HTA | B15: EMA’s adaptive pathway process | C15: Various | D15: Somatic cell therapy | E15: 2016 | F15: PLacental eXpanded (PLX) cells
A542: NICE | C542: Oncology | D542: Multiple Myeloma | E542: 2021 | F542: Elrinatanab
A543: NICE | C543: Oncology | D543: Breast cancer | E543: 2021 | F543: MEN1116
A544: HAS | C544: Oncology | D544: Breast cancer | E544: 2021 | F544: MEN1116

Sheet GVDs
A1: Therapy area | B1: Indication | C1: Year | D1: Product | J1: {=_xlfn.UNIQUE(A:A)} -> Therapy area | K1: {=_xlfn.UNIQUE(B:B)} -> Indication | L1: {=_xlfn.UNIQUE(C:C)} -> Year | M1: {=_xlfn.UNIQUE(D:D)} -> Product
A2: Haematology | B2: Anticoagulant product in venous thromboembolism | C2: 2015 | J2: Haematology | K2: Anticoagulant product in venous thromboembolism | L2: 2015 | M2: 0
A3: Haemato-oncology | B3: Mantle Cell Lymphoma product | C3: 2015 | J3: Haemato-oncology | K3: Mantle Cell Lymphoma product | L3: 2016 | M3: Binimetinib + encorafenib
A4: Metabolic/Endocrine Disorders | B4: Acromegaly product | C4: 2015 | J4: Metabolic/Endocrine Disorders | K4: Acromegaly product | L4: 2017 | M4: Veyvondi
A5: Cardiorenal/Metabolic | B5: Hyperkalemia product | C5: 2016 | J5: Cardiorenal/Metabolic | K5: Hyperkalemia product | L5: 2018 | M5: nAB
A6: Metabolic/Endocrine Disorders | B6: DPP-4 / SGLT-2 combination product in T2DM (update) | C6: 2016 | J6: Oncology | K6: DPP-4 / SGLT-2 combination product in T2DM (update) | L6: 2019 | M6: Opdivo + Cabozantinib
A7: Oncology | B7: Melanoma | C7: 2017 | D7: Binimetinib + encorafenib | J7: Respiratory | K7: Melanoma | L7: 2020
A8: Oncology | B8: Metastatic colorectal cancer product | C8: 2017 | J8: Central nervous system | K8: Metastatic colorectal cancer product | L8: 2021
A9: Respiratory | B9: Asthma product | C9: 2017 | J9: Infectious diseases | K9: Asthma product | L9: 0
A10: Respiratory | B10: Chronic Obstructive Pulmonary Disease product | C10: 2017 | J10: Mental illness | K10: Chronic Obstructive Pulmonary Disease product
A11: Central nervous system | B11: Diabetic peripheral neuropathy/post-herpetic neuralgia product | C11: 2018 | J11: 0 | K11: Diabetic peripheral neuropathy/post-herpetic neuralgia product
A12: Infectious diseases | B12: Pseudomonas aeruginosa anti-infective product | C12: 2018 | K12: Pseudomonas aeruginosa anti-infective product
A13: Mental illness | B13: Digital treatment program for depression | C13: 2018 | K13: Digital treatment program for depression
A14: Metabolic/Endocrine Disorders | B14: GLP-1 agonist product in T2DM | C14: 2018 | K14: GLP-1 agonist product in T2DM
A15: Oncology | B15: Cutaneous melanoma product | C15: 2018 | K15: Cutaneous melanoma product
A16: Oncology | B16: Non-small cell lung cancer IO product | C16: 2018 | K16: Non-small cell lung cancer IO product
A17: Central nervous system | B17: Epilepsy product (update) | C17: 2019 | K17: Epilepsy product (update)
A18: Infectious diseases | B18: HIV product | C18: 2019 | K18: HIV product
A19: Oncology | B19: Hepatocellular cell carcinoma/renal cell carcinoma product | C19: 2019 | K19: Hepatocellular cell carcinoma/renal cell carcinoma product
A20: Haemato-oncology | B20: Non Hodgkin Lymphoma | C20: 2020 | K20: Non Hodgkin Lymphoma
A21: Haemato-oncology | B21: Relapsed/refractory AML product | C21: 2020 | K21: Relapsed/refractory AML product
A22: Oncology | B22: Unresectable malignant pleural mesothelioma | C22: 2020 | K22: Unresectable malignant pleural mesothelioma
A23: Haematology | B23: von Willebrand disease (an inherited bleeding disorder) | C23: 2021 | D23: Veyvondi | K23: von Willebrand disease (an inherited bleeding disorder)
A24: Infectious diseases | B24: COVID-19 infection | C24: 2021 | D24: nAB | K24: COVID-19 infection
A25: Oncology | B25: Advanced renal cell carcinoma | C25: 2021 | D25: Opdivo + Cabozantinib | K25: Advanced renal cell carcinoma
K26: 0

Sheet Local HTA Pivot Table
A2: Count of HTA body | B2: Column Labels
A3: Row Labels | B3: AIFA | C3: AWMSG | D3: G-BA | E3: Greek HTA Committee | F3: INFARMED | G3: N/A | H3: NCPE | I3: NICE | J3: SMC | K3: SUKL | L3: ŠUKL | M3: Zorginstituut Nederland | N3: Zorgverzekeraars Nederland | O3: Grand Total
A4: 2012 | I4: 4 | J4: 2 | O4: 6
A5: 2013 | C5: 1 | H5: 3 | I5: 5 | J5: 1 | O5: 10
A6: 2014 | H6: 2 | I6: 3 | O6: 5
A7: 2015 | C7: 1 | D7: 7 | G7: 5 | H7: 2 | I7: 5 | J7: 9 | O7: 29
A8: 2016 | C8: 1 | D8: 9 | G8: 8 | H8: 2 | I8: 3 | J8: 1 | O8: 24
A9: 2017 | D9: 11 | G9: 6 | H9: 2 | I9: 5 | J9: 1 | O9: 25
A10: 2018 | B10: 6 | C10: 2 | D10: 12 | E10: 3 | G10: 7 | H10: 2 | I10: 4 | J10: 2 | K10: 1 | L10: 1 | M10: 1 | O10: 41
A11: 2019 | B11: 6 | C11: 1 | D11: 14 | E11: 6 | F11: 1 | G11: 7 | H11: 3 | I11: 10 | J11: 3 | M11: 4 | N11: 1 | O11: 56
A12: 2020 | B12: 17 | D12: 25 | E12: 9 | F12: 2 | G12: 5 | H12: 2 | I12: 5 | J12: 3 | M12: 3 | N12: 1 | O12: 72
A13: 2021 | B13: 17 | D13: 7 | E13: 2 | F13: 3 | G13: 2 | H13: 4 | I13: 6 | J13: 5 | M13: 5 | O13: 51
A14: Grand Total | B14: 46 | C14: 6 | D14: 85 | E14: 20 | F14: 6 | G14: 40 | H14: 22 | I14: 50 | J14: 27 | K14: 1 | L14: 1 | M14: 13 | N14: 2 | O14: 319

Sheet HTA scientific advice Pivot
A2: Count of Year | B2: Column Labels
A3: Row Labels | B3: 2016 | C3: 2017 | D3: 2018 | E3: 2019 | F3: 2020 | G3: 2021 | H3: Grand Total
A4: Dermatology | D4: 4 | H4: 4
A5: Haemato-oncology | F5: 1 | G5: 3 | H5: 4
A6: Nephrology | G6: 1 | H6: 1
A7: Oncology | C7: 1 | E7: 1 | G7: 2 | H7: 4
A8: Misc | B8: 1 | H8: 1
A9: Grand Total | B9: 1 | C9: 1 | D9: 4 | E9: 1 | F9: 1 | G9: 6 | H9: 14

Sheet GVDs Pivot Table
A3: Count of Indication | B3: Column Labels
A4: Row Labels | B4: 2015 | C4: 2016 | D4: 2017 | E4: 2018 | F4: 2019 | G4: 2020 | H4: 2021 | I4: Grand Total
A5: Acromegaly product | B5: 1 | I5: 1
A6: Advanced renal cell carcinoma | H6: 1 | I6: 1
A7: Anticoagulant product in venous thromboembolism | B7: 1 | I7: 1
A8: Asthma product | D8: 1 | I8: 1
A9: Chronic Obstructive Pulmonary Disease product | D9: 1 | I9: 1
A10: COVID-19 infection | H10: 1 | I10: 1
A11: Cutaneous melanoma product | E11: 1 | I11: 1
A12: Diabetic peripheral neuropathy/post-herpetic neuralgia product | E12: 1 | I12: 1
A13: Digital treatment program for depression | E13: 1 | I13: 1
A14: DPP-4 / SGLT-2 combination product in T2DM (update) | C14: 1 | I14: 1
A15: Epilepsy product (update) | F15: 1 | I15: 1
A16: GLP-1 agonist product in T2DM | E16: 1 | I16: 1
A17: Hepatocellular cell carcinoma/renal cell carcinoma product | F17: 1 | I17: 1
A18: HIV product | F18: 1 | I18: 1
A19: Hyperkalemia product | C19: 1 | I19: 1
A20: Mantle Cell Lymphoma product | B20: 1 | I20: 1
A21: Melanoma | D21: 1 | I21: 1
A22: Metastatic colorectal cancer product | D22: 1 | I22: 1
A23: Non Hodgkin Lymphoma | G23: 1 | I23: 1
A24: Non-small cell lung cancer IO product | E24: 1 | I24: 1
A25: Pseudomonas aeruginosa anti-infective product | E25: 1 | I25: 1
A26: Relapsed/refractory AML product | G26: 1 | I26: 1
A27: Unresectable malignant pleural mesothelioma | G27: 1 | I27: 1
A28: von Willebrand disease (an inherited bleeding disorder) | H28: 1 | I28: 1
A29: Grand Total | B29: 3 | C29: 2 | D29: 4 | E29: 6 | F29: 3 | G29: 3 | H29: 3 | I29: 24

Sheet By year
A3: Local HTA submissions
A4: HTA submissions by Year & HTA body
A5: Year | B5: NICE | C5: SMC | D5: AWMSG | E5: NCPE | F5: G-BA | G5: AIFA | H5: AEMPS | I5: CEESP | J5: CT | K5: Total
A6: ='Local HTA submissions'!AG12 -> 0 | B6: =COUNTIFS('Local HTA submissions'!$H:$H,'By year'!$A6,'Local HTA submissions'!$C:$C,'By year'!B$5) -> 0 | C6: =COUNTIFS('Local HTA submissions'!$H:$H,'By year'!$A6,'Local HTA submissions'!$C:$C,'By year'!C$5) -> 0 | D6: =COUNTIFS('Local HTA submissions'!$H:$H,'By year'!$A6,'Local HTA submissions'!$C:$C,'By year'!D$5) -> 0 | E6: =COUNTIFS('Local HTA submissions'!$H:$H,'By year'!$A6,'Local HTA submissions'!$C:$C,'By year'!E$5) -> 0 | F6: =COUNTIFS('Local HTA submissions'!$H:$H,'By year'!$A6,'Local HTA submissions'!$C:$C,'By year'!F$5) -> 0 | G6: =COUNTIFS('Local HTA submissions'!$H:$H,'By year'!$A6,'Local HTA submissions'!$C:$C,'By year'!G$5) -> 0 | H6: =COUNTIFS('Local HTA submissions'!$H:$H,'By year'!$A6,'Local HTA submissions'!$C:$C,'By year'!H$5) -> 0 | I6: =COUNTIFS('Local HTA submissions'!$H:$H,'By year'!$A6,'Local HTA submissions'!$C:$C,'By year'!I$5) -> 0 | J6: =COUNTIFS('Local HTA submissions'!$H:$H,'By year'!$A6,'Local HTA submissions'!$C:$C,'By year'!J$5) -> 0 | K6: =SUM(B6:J6) -> 0
A7: ='Local HTA submissions'!AG11 -> 2012 | B7: =COUNTIFS('Local HTA submissions'!$H:$H,'By year'!$A7,'Local HTA submissions'!$C:$C,'By year'!B$5) -> 4 | C7: =COUNTIFS('Local HTA submissions'!$H:$H,'By year'!$A7,'Local HTA submissions'!$C:$C,'By year'!C$5) -> 2 | D7: =COUNTIFS('Local HTA submissions'!$H:$H,'By year'!$A7,'Local HTA submissions'!$C:$C,'By year'!D$5) -> 0 | E7: =COUNTIFS('Local HTA submissions'!$H:$H,'By year'!$A7,'Local HTA submissions'!$C:$C,'By year'!E$5) -> 0 | F7: =COUNTIFS('Local HTA submissions'!$H:$H,'By year'!$A7,'Local HTA submissions'!$C:$C,'By year'!F$5) -> 0 | G7: =COUNTIFS('Local HTA submissions'!$H:$H,'By year'!$A7,'Local HTA submissions'!$C:$C,'By year'!G$5) -> 0 | H7: =COUNTIFS('Local HTA submissions'!$H:$H,'By year'!$A7,'Local HTA submissions'!$C:$C,'By year'!H$5) -> 0 | I7: =COUNTIFS('Local HTA submissions'!$H:$H,'By year'!$A7,'Local HTA submissions'!$C:$C,'By year'!I$5) -> 0 | J7: =COUNTIFS('Local HTA submissions'!$H:$H,'By year'!$A7,'Local HTA submissions'!$C:$C,'By year'!J$5) -> 0 | K7: =SUM(B7:J7) -> 6
A8: ='Local HTA submissions'!AG10 -> 2013 | B8: =COUNTIFS('Local HTA submissions'!$H:$H,'By year'!$A8,'Local HTA submissions'!$C:$C,'By year'!B$5) -> 5 | C8: =COUNTIFS('Local HTA submissions'!$H:$H,'By year'!$A8,'Local HTA submissions'!$C:$C,'By year'!C$5) -> 1 | D8: =COUNTIFS('Local HTA submissions'!$H:$H,'By year'!$A8,'Local HTA submissions'!$C:$C,'By year'!D$5) -> 1 | E8: =COUNTIFS('Local HTA submissions'!$H:$H,'By year'!$A8,'Local HTA submissions'!$C:$C,'By year'!E$5) -> 3 | F8: =COUNTIFS('Local HTA submissions'!$H:$H,'By year'!$A8,'Local HTA submissions'!$C:$C,'By year'!F$5) -> 0 | G8: =COUNTIFS('Local HTA submissions'!$H:$H,'By year'!$A8,'Local HTA submissions'!$C:$C,'By year'!G$5) -> 0 | H8: =COUNTIFS('Local HTA submissions'!$H:$H,'By year'!$A8,'Local HTA submissions'!$C:$C,'By year'!H$5) -> 0 | I8: =COUNTIFS('Local HTA submissions'!$H:$H,'By year'!$A8,'Local HTA submissions'!$C:$C,'By year'!I$5) -> 0 | J8: =COUNTIFS('Local HTA submissions'!$H:$H,'By year'!$A8,'Local HTA submissions'!$C:$C,'By year'!J$5) -> 0 | K8: =SUM(B8:J8) -> 10
A9: ='Local HTA submissions'!AG9 -> 2014 | B9: =COUNTIFS('Local HTA submissions'!$H:$H,'By year'!$A9,'Local HTA submissions'!$C:$C,'By year'!B$5) -> 3 | C9: =COUNTIFS('Local HTA submissions'!$H:$H,'By year'!$A9,'Local HTA submissions'!$C:$C,'By year'!C$5) -> 0 | D9: =COUNTIFS('Local HTA submissions'!$H:$H,'By year'!$A9,'Local HTA submissions'!$C:$C,'By year'!D$5) -> 0 | E9: =COUNTIFS('Local HTA submissions'!$H:$H,'By year'!$A9,'Local HTA submissions'!$C:$C,'By year'!E$5) -> 2 | F9: =COUNTIFS('Local HTA submissions'!$H:$H,'By year'!$A9,'Local HTA submissions'!$C:$C,'By year'!F$5) -> 0 | G9: =COUNTIFS('Local HTA submissions'!$H:$H,'By year'!$A9,'Local HTA submissions'!$C:$C,'By year'!G$5) -> 0 | H9: =COUNTIFS('Local HTA submissions'!$H:$H,'By year'!$A9,'Local HTA submissions'!$C:$C,'By year'!H$5) -> 0 | I9: =COUNTIFS('Local HTA submissions'!$H:$H,'By year'!$A9,'Local HTA submissions'!$C:$C,'By year'!I$5) -> 0 | J9: =COUNTIFS('Local HTA submissions'!$H:$H,'By year'!$A9,'Local HTA submissions'!$C:$C,'By year'!J$5) -> 0 | K9: =SUM(B9:J9) -> 5
A10: ='Local HTA submissions'!AG8 -> 2015 | B10: =COUNTIFS('Local HTA submissions'!$H:$H,'By year'!$A10,'Local HTA submissions'!$C:$C,'By year'!B$5) -> 5 | C10: =COUNTIFS('Local HTA submissions'!$H:$H,'By year'!$A10,'Local HTA submissions'!$C:$C,'By year'!C$5) -> 9 | D10: =COUNTIFS('Local HTA submissions'!$H:$H,'By year'!$A10,'Local HTA submissions'!$C:$C,'By year'!D$5) -> 1 | E10: =COUNTIFS('Local HTA submissions'!$H:$H,'By year'!$A10,'Local HTA submissions'!$C:$C,'By year'!E$5) -> 2 | F10: =COUNTIFS('Local HTA submissions'!$H:$H,'By year'!$A10,'Local HTA submissions'!$C:$C,'By year'!F$5) -> 7 | G10: =COUNTIFS('Local HTA submissions'!$H:$H,'By year'!$A10,'Local HTA submissions'!$C:$C,'By year'!G$5) -> 0 | H10: =COUNTIFS('Local HTA submissions'!$H:$H,'By year'!$A10,'Local HTA submissions'!$C:$C,'By year'!H$5) -> 0 | I10: 5 | J10: 36 | K10: =SUM(B10:J10) -> 65
A11: ='Local HTA submissions'!AG7 -> 2016 | B11: =COUNTIFS('Local HTA submissions'!$H:$H,'By year'!$A11,'Local HTA submissions'!$C:$C,'By year'!B$5) -> 3 | C11: =COUNTIFS('Local HTA submissions'!$H:$H,'By year'!$A11,'Local HTA submissions'!$C:$C,'By year'!C$5) -> 1 | D11: =COUNTIFS('Local HTA submissions'!$H:$H,'By year'!$A11,'Local HTA submissions'!$C:$C,'By year'!D$5) -> 1 | E11: =COUNTIFS('Local HTA submissions'!$H:$H,'By year'!$A11,'Local HTA submissions'!$C:$C,'By year'!E$5) -> 2 | F11: =COUNTIFS('Local HTA submissions'!$H:$H,'By year'!$A11,'Local HTA submissions'!$C:$C,'By year'!F$5) -> 9 | G11: =COUNTIFS('Local HTA submissions'!$H:$H,'By year'!$A11,'Local HTA submissions'!$C:$C,'By year'!G$5) -> 0 | H11: =COUNTIFS('Local HTA submissions'!$H:$H,'By year'!$A11,'Local HTA submissions'!$C:$C,'By year'!H$5) -> 0 | I11: 9 | J11: 31 | K11: =SUM(B11:J11) -> 56
A12: ='Local HTA submissions'!AG6 -> 2017 | B12: =COUNTIFS('Local HTA submissions'!$H:$H,'By year'!$A12,'Local HTA submissions'!$C:$C,'By year'!B$5) -> 5 | C12: =COUNTIFS('Local HTA submissions'!$H:$H,'By year'!$A12,'Local HTA submissions'!$C:$C,'By year'!C$5) -> 1 | D12: =COUNTIFS('Local HTA submissions'!$H:$H,'By year'!$A12,'Local HTA submissions'!$C:$C,'By year'!D$5) -> 0 | E12: =COUNTIFS('Local HTA submissions'!$H:$H,'By year'!$A12,'Local HTA submissions'!$C:$C,'By year'!E$5) -> 2 | F12: =COUNTIFS('Local HTA submissions'!$H:$H,'By year'!$A12,'Local HTA submissions'!$C:$C,'By year'!F$5) -> 11 | G12: =COUNTIFS('Local HTA submissions'!$H:$H,'By year'!$A12,'Local HTA submissions'!$C:$C,'By year'!G$5) -> 0 | H12: =COUNTIFS('Local HTA submissions'!$H:$H,'By year'!$A12,'Local HTA submissions'!$C:$C,'By year'!H$5) -> 0 | I12: 6 | J12: 22 | K12: =SUM(B12:J12) -> 47
A13: ='Local HTA submissions'!AG5 -> 2018 | B13: =COUNTIFS('Local HTA submissions'!$H:$H,'By year'!$A13,'Local HTA submissions'!$C:$C,'By year'!B$5) -> 4 | C13: =COUNTIFS('Local HTA submissions'!$H:$H,'By year'!$A13,'Local HTA submissions'!$C:$C,'By year'!C$5) -> 2 | D13: =COUNTIFS('Local HTA submissions'!$H:$H,'By year'!$A13,'Local HTA submissions'!$C:$C,'By year'!D$5) -> 2 | E13: =COUNTIFS('Local HTA submissions'!$H:$H,'By year'!$A13,'Local HTA submissions'!$C:$C,'By year'!E$5) -> 2 | F13: =COUNTIFS('Local HTA submissions'!$H:$H,'By year'!$A13,'Local HTA submissions'!$C:$C,'By year'!F$5) -> 12 | G13: =COUNTIFS('Local HTA submissions'!$H:$H,'By year'!$A13,'Local HTA submissions'!$C:$C,'By year'!G$5) -> 6 | H13: =COUNTIFS('Local HTA submissions'!$H:$H,'By year'!$A13,'Local HTA submissions'!$C:$C,'By year'!H$5) -> 0 | I13: 7 | J13: 24 | K13: =SUM(B13:J13) -> 59
A14: ='Local HTA submissions'!AG4 -> 2019 | B14: =COUNTIFS('Local HTA submissions'!$H:$H,'By year'!$A14,'Local HTA submissions'!$C:$C,'By year'!B$5) -> 9 | C14: =COUNTIFS('Local HTA submissions'!$H:$H,'By year'!$A14,'Local HTA submissions'!$C:$C,'By year'!C$5) -> 3 | D14: =COUNTIFS('Local HTA submissions'!$H:$H,'By year'!$A14,'Local HTA submissions'!$C:$C,'By year'!D$5) -> 1 | E14: =COUNTIFS('Local HTA submissions'!$H:$H,'By year'!$A14,'Local HTA submissions'!$C:$C,'By year'!E$5) -> 3 | F14: =COUNTIFS('Local HTA submissions'!$H:$H,'By year'!$A14,'Local HTA submissions'!$C:$C,'By year'!F$5) -> 14 | G14: =COUNTIFS('Local HTA submissions'!$H:$H,'By year'!$A14,'Local HTA submissions'!$C:$C,'By year'!G$5) -> 6 | H14: =COUNTIFS('Local HTA submissions'!$H:$H,'By year'!$A14,'Local HTA submissions'!$C:$C,'By year'!H$5) -> 0 | I14: 19 | J14: 22 | K14: =SUM(B14:J14) -> 77
A15: ='Local HTA submissions'!AG3 -> 2020 | B15: =COUNTIFS('Local HTA submissions'!$H:$H,'By year'!$A15,'Local HTA submissions'!$C:$C,'By year'!B$5) -> 5 | C15: =COUNTIFS('Local HTA submissions'!$H:$H,'By year'!$A15,'Local HTA submissions'!$C:$C,'By year'!C$5) -> 3 | D15: =COUNTIFS('Local HTA submissions'!$H:$H,'By year'!$A15,'Local HTA submissions'!$C:$C,'By year'!D$5) -> 0 | E15: =COUNTIFS('Local HTA submissions'!$H:$H,'By year'!$A15,'Local HTA submissions'!$C:$C,'By year'!E$5) -> 2 | F15: =COUNTIFS('Local HTA submissions'!$H:$H,'By year'!$A15,'Local HTA submissions'!$C:$C,'By year'!F$5) -> 25 | G15: =COUNTIFS('Local HTA submissions'!$H:$H,'By year'!$A15,'Local HTA submissions'!$C:$C,'By year'!G$5) -> 17 | H15: =COUNTIFS('Local HTA submissions'!$H:$H,'By year'!$A15,'Local HTA submissions'!$C:$C,'By year'!H$5) -> 0 | I15: 19 | J15: 22 | K15: =SUM(B15:J15) -> 93
A16: ='Local HTA submissions'!AG2 -> 2021 | B16: =COUNTIFS('Local HTA submissions'!$H:$H,'By year'!$A16,'Local HTA submissions'!$C:$C,'By year'!B$5) -> 7 | C16: =COUNTIFS('Local HTA submissions'!$H:$H,'By year'!$A16,'Local HTA submissions'!$C:$C,'By year'!C$5) -> 5 | D16: =COUNTIFS('Local HTA submissions'!$H:$H,'By year'!$A16,'Local HTA submissions'!$C:$C,'By year'!D$5) -> 0 | E16: =COUNTIFS('Local HTA submissions'!$H:$H,'By year'!$A16,'Local HTA submissions'!$C:$C,'By year'!E$5) -> 4 | F16: =COUNTIFS('Local HTA submissions'!$H:$H,'By year'!$A16,'Local HTA submissions'!$C:$C,'By year'!F$5) -> 7 | G16: =COUNTIFS('Local HTA submissions'!$H:$H,'By year'!$A16,'Local HTA submissions'!$C:$C,'By year'!G$5) -> 17 | H16: =COUNTIFS('Local HTA submissions'!$H:$H,'By year'!$A16,'Local HTA submissions'!$C:$C,'By year'!H$5) -> 0 | I16: 4 | J16: 4 | K16: =SUM(B16:J16) -> 48
A17: ='Local HTA submissions'!AG13 -> Ongoing | B17: =COUNTIFS('Local HTA submissions'!$H:$H,'By year'!$A17,'Local HTA submissions'!$C:$C,'By year'!B$5) -> 0 | C17: =COUNTIFS('Local HTA submissions'!$H:$H,'By year'!$A17,'Local HTA submissions'!$C:$C,'By year'!C$5) -> 0 | D17: =COUNTIFS('Local HTA submissions'!$H:$H,'By year'!$A17,'Local HTA submissions'!$C:$C,'By year'!D$5) -> 0 | E17: =COUNTIFS('Local HTA submissions'!$H:$H,'By year'!$A17,'Local HTA submissions'!$C:$C,'By year'!E$5) -> 0 | F17: =COUNTIFS('Local HTA submissions'!$H:$H,'By year'!$A17,'Local HTA submissions'!$C:$C,'By year'!F$5) -> 0 | G17: =COUNTIFS('Local HTA submissions'!$H:$H,'By year'!$A17,'Local HTA submissions'!$C:$C,'By year'!G$5) -> 0 | H17: =COUNTIFS('Local HTA submissions'!$H:$H,'By year'!$A17,'Local HTA submissions'!$C:$C,'By year'!H$5) -> 0 | I17: 4 | J17: 4 | K17: =SUM(B17:J17) -> 8
A18: Total | B18: =SUM(B6:B17) -> 50 | C18: =SUM(C6:C17) -> 27 | D18: =SUM(D6:D17) -> 6 | E18: =SUM(E6:E17) -> 22 | F18: =SUM(F6:F17) -> 85 | G18: =SUM(G6:G17) -> 46 | H18: =SUM(H6:H17) -> 0 | I18: =SUM(I6:I17) -> 73 | J18: =SUM(J6:J17) -> 165 | K18: =SUM(B18:J18) -> 474
A46: HTA submissions by Year & Country
A47: Country | B47: 2012 | C47: 2013 | D47: 2014 | E47: 2015 | F47: 2016 | G47: 2017 | H47: 2018 | I47: 2019 | J47: 2020 | K47: 2021 | L47: Total
A48: ='Local HTA submissions'!AA2 -> England | B48: =COUNTIFS('Local HTA submissions'!$B:$B,'By year'!$A48,'Local HTA submissions'!$H:$H,'By year'!B$47) -> 4 | C48: =COUNTIFS('Local HTA submissions'!$B:$B,'By year'!$A48,'Local HTA submissions'!$H:$H,'By year'!C$47) -> 5 | D48: =COUNTIFS('Local HTA submissions'!$B:$B,'By year'!$A48,'Local HTA submissions'!$H:$H,'By year'!D$47) -> 3 | E48: =COUNTIFS('Local HTA submissions'!$B:$B,'By year'!$A48,'Local HTA submissions'!$H:$H,'By year'!E$47) -> 5 | F48: =COUNTIFS('Local HTA submissions'!$B:$B,'By year'!$A48,'Local HTA submissions'!$H:$H,'By year'!F$47) -> 3 | G48: =COUNTIFS('Local HTA submissions'!$B:$B,'By year'!$A48,'Local HTA submissions'!$H:$H,'By year'!G$47) -> 5 | H48: =COUNTIFS('Local HTA submissions'!$B:$B,'By year'!$A48,'Local HTA submissions'!$H:$H,'By year'!H$47) -> 4 | I48: =COUNTIFS('Local HTA submissions'!$B:$B,'By year'!$A48,'Local HTA submissions'!$H:$H,'By year'!I$47) -> 9 | ... K48: =COUNTIFS('Local HTA submissions'!$B:$B,'By year'!$A48,'Local HTA submissions'!$H:$H,'By year'!K$47) -> 7 | L48: =SUM(B48:K48) -> 50
A49: ='Local HTA submissions'!AA3 -> Scotland | B49: =COUNTIFS('Local HTA submissions'!$B:$B,'By year'!$A49,'Local HTA submissions'!$H:$H,'By year'!B$47) -> 2 | C49: =COUNTIFS('Local HTA submissions'!$B:$B,'By year'!$A49,'Local HTA submissions'!$H:$H,'By year'!C$47) -> 1 | D49: =COUNTIFS('Local HTA submissions'!$B:$B,'By year'!$A49,'Local HTA submissions'!$H:$H,'By year'!D$47) -> 0 | E49: =COUNTIFS('Local HTA submissions'!$B:$B,'By year'!$A49,'Local HTA submissions'!$H:$H,'By year'!E$47) -> 9 | F49: =COUNTIFS('Local HTA submissions'!$B:$B,'By year'!$A49,'Local HTA submissions'!$H:$H,'By year'!F$47) -> 1 | G49: =COUNTIFS('Local HTA submissions'!$B:$B,'By year'!$A49,'Local HTA submissions'!$H:$H,'By year'!G$47) -> 1 | H49: =COUNTIFS('Local HTA submissions'!$B:$B,'By year'!$A49,'Local HTA submissions'!$H:$H,'By year'!H$47) -> 2 | I49: =COUNTIFS('Local HTA submissions'!$B:$B,'By year'!$A49,'Local HTA submissions'!$H:$H,'By year'!I$47) -> 3 | ... K49: =COUNTIFS('Local HTA submissions'!$B:$B,'By year'!$A49,'Local HTA submissions'!$H:$H,'By year'!K$47) -> 5 | L49: =SUM(B49:K49) -> 27
A50: ='Local HTA submissions'!AA4 -> Wales | B50: =COUNTIFS('Local HTA submissions'!$B:$B,'By year'!$A50,'Local HTA submissions'!$H:$H,'By year'!B$47) -> 0 | C50: =COUNTIFS('Local HTA submissions'!$B:$B,'By year'!$A50,'Local HTA submissions'!$H:$H,'By year'!C$47) -> 1 | D50: =COUNTIFS('Local HTA submissions'!$B:$B,'By year'!$A50,'Local HTA submissions'!$H:$H,'By year'!D$47) -> 0 | E50: =COUNTIFS('Local HTA submissions'!$B:$B,'By year'!$A50,'Local HTA submissions'!$H:$H,'By year'!E$47) -> 1 | F50: =COUNTIFS('Local HTA submissions'!$B:$B,'By year'!$A50,'Local HTA submissions'!$H:$H,'By year'!F$47) -> 1 | G50: =COUNTIFS('Local HTA submissions'!$B:$B,'By year'!$A50,'Local HTA submissions'!$H:$H,'By year'!G$47) -> 0 | H50: =COUNTIFS('Local HTA submissions'!$B:$B,'By year'!$A50,'Local HTA submissions'!$H:$H,'By year'!H$47) -> 2 | I50: =COUNTIFS('Local HTA submissions'!$B:$B,'By year'!$A50,'Local HTA submissions'!$H:$H,'By year'!I$47) -> 1 | ... K50: =COUNTIFS('Local HTA submissions'!$B:$B,'By year'!$A50,'Local HTA submissions'!$H:$H,'By year'!K$47) -> 0 | L50: =SUM(B50:K50) -> 6
A51: ='Local HTA submissions'!AA5 -> Ireland | B51: =COUNTIFS('Local HTA submissions'!$B:$B,'By year'!$A51,'Local HTA submissions'!$H:$H,'By year'!B$47) -> 0 | C51: =COUNTIFS('Local HTA submissions'!$B:$B,'By year'!$A51,'Local HTA submissions'!$H:$H,'By year'!C$47) -> 3 | D51: =COUNTIFS('Local HTA submissions'!$B:$B,'By year'!$A51,'Local HTA submissions'!$H:$H,'By year'!D$47) -> 2 | E51: =COUNTIFS('Local HTA submissions'!$B:$B,'By year'!$A51,'Local HTA submissions'!$H:$H,'By year'!E$47) -> 2 | F51: =COUNTIFS('Local HTA submissions'!$B:$B,'By year'!$A51,'Local HTA submissions'!$H:$H,'By year'!F$47) -> 2 | G51: =COUNTIFS('Local HTA submissions'!$B:$B,'By year'!$A51,'Local HTA submissions'!$H:$H,'By year'!G$47) -> 2 | H51: =COUNTIFS('Local HTA submissions'!$B:$B,'By year'!$A51,'Local HTA submissions'!$H:$H,'By year'!H$47) -> 2 | I51: =COUNTIFS('Local HTA submissions'!$B:$B,'By year'!$A51,'Local HTA submissions'!$H:$H,'By year'!I$47) -> 3 | ... K51: =COUNTIFS('Local HTA submissions'!$B:$B,'By year'!$A51,'Local HTA submissions'!$H:$H,'By year'!K$47) -> 4 | L51: =SUM(B51:K51) -> 22
A52: ='Local HTA submissions'!AA6 -> Germany | B52: =COUNTIFS('Local HTA submissions'!$B:$B,'By year'!$A52,'Local HTA submissions'!$H:$H,'By year'!B$47) -> 0 | C52: =COUNTIFS('Local HTA submissions'!$B:$B,'By year'!$A52,'Local HTA submissions'!$H:$H,'By year'!C$47) -> 0 | D52: =COUNTIFS('Local HTA submissions'!$B:$B,'By year'!$A52,'Local HTA submissions'!$H:$H,'By year'!D$47) -> 0 | E52: =COUNTIFS('Local HTA submissions'!$B:$B,'By year'!$A52,'Local HTA submissions'!$H:$H,'By year'!E$47) -> 7 | F52: =COUNTIFS('Local HTA submissions'!$B:$B,'By year'!$A52,'Local HTA submissions'!$H:$H,'By year'!F$47) -> 9 | G52: =COUNTIFS('Local HTA submissions'!$B:$B,'By year'!$A52,'Local HTA submissions'!$H:$H,'By year'!G$47) -> 11 | H52: =COUNTIFS('Local HTA submissions'!$B:$B,'By year'!$A52,'Local HTA submissions'!$H:$H,'By year'!H$47) -> 12 | I52: =COUNTIFS('Local HTA submissions'!$B:$B,'By year'!$A52,'Local HTA submissions'!$H:$H,'By year'!I$47) -> 14 | ... K52: =COUNTIFS('Local HTA submissions'!$B:$B,'By year'!$A52,'Local HTA submissions'!$H:$H,'By year'!K$47) -> 7 | L52: =SUM(B52:K52) -> 85
A53: ='Local HTA submissions'!AA7 -> Spain | B53: =COUNTIFS('Local HTA submissions'!$B:$B,'By year'!$A53,'Local HTA submissions'!$H:$H,'By year'!B$47) -> 0 | C53: =COUNTIFS('Local HTA submissions'!$B:$B,'By year'!$A53,'Local HTA submissions'!$H:$H,'By year'!C$47) -> 0 | D53: =COUNTIFS('Local HTA submissions'!$B:$B,'By year'!$A53,'Local HTA submissions'!$H:$H,'By year'!D$47) -> 0 | E53: =COUNTIFS('Local HTA submissions'!$B:$B,'By year'!$A53,'Local HTA submissions'!$H:$H,'By year'!E$47) -> 5 | F53: =COUNTIFS('Local HTA submissions'!$B:$B,'By year'!$A53,'Local HTA submissions'!$H:$H,'By year'!F$47) -> 8 | G53: =COUNTIFS('Local HTA submissions'!$B:$B,'By year'!$A53,'Local HTA submissions'!$H:$H,'By year'!G$47) -> 6 | H53: =COUNTIFS('Local HTA submissions'!$B:$B,'By year'!$A53,'Local HTA submissions'!$H:$H,'By year'!H$47) -> 7 | I53: =COUNTIFS('Local HTA submissions'!$B:$B,'By year'!$A53,'Local HTA submissions'!$H:$H,'By year'!I$47) -> 7 | ... K53: =COUNTIFS('Local HTA submissions'!$B:$B,'By year'!$A53,'Local HTA submissions'!$H:$H,'By year'!K$47) -> 2 | L53: =SUM(B53:K53) -> 40
A54: ='Local HTA submissions'!AA8 -> Italy | B54: =COUNTIFS('Local HTA submissions'!$B:$B,'By year'!$A54,'Local HTA submissions'!$H:$H,'By year'!B$47) -> 0 | C54: =COUNTIFS('Local HTA submissions'!$B:$B,'By year'!$A54,'Local HTA submissions'!$H:$H,'By year'!C$47) -> 0 | D54: =COUNTIFS('Local HTA submissions'!$B:$B,'By year'!$A54,'Local HTA submissions'!$H:$H,'By year'!D$47) -> 0 | E54: =COUNTIFS('Local HTA submissions'!$B:$B,'By year'!$A54,'Local HTA submissions'!$H:$H,'By year'!E$47) -> 0 | F54: =COUNTIFS('Local HTA submissions'!$B:$B,'By year'!$A54,'Local HTA submissions'!$H:$H,'By year'!F$47) -> 0 | G54: =COUNTIFS('Local HTA submissions'!$B:$B,'By year'!$A54,'Local HTA submissions'!$H:$H,'By year'!G$47) -> 0 | H54: =COUNTIFS('Local HTA submissions'!$B:$B,'By year'!$A54,'Local HTA submissions'!$H:$H,'By year'!H$47) -> 6 | I54: =COUNTIFS('Local HTA submissions'!$B:$B,'By year'!$A54,'Local HTA submissions'!$H:$H,'By year'!I$47) -> 6 | ... K54: =COUNTIFS('Local HTA submissions'!$B:$B,'By year'!$A54,'Local HTA submissions'!$H:$H,'By year'!K$47) -> 17 | L54: =SUM(B54:K54) -> 46
A55: ='Local HTA submissions'!AA9 -> France | B55: =COUNTIFS('Local HTA submissions'!$B:$B,'By year'!$A55,'Local HTA submissions'!$H:$H,'By year'!B$47) -> 0 | C55: =COUNTIFS('Local HTA submissions'!$B:$B,'By year'!$A55,'Local HTA submissions'!$H:$H,'By year'!C$47) -> 0 | D55: =COUNTIFS('Local HTA submissions'!$B:$B,'By year'!$A55,'Local HTA submissions'!$H:$H,'By year'!D$47) -> 0 | E55: 41 | F55: 40 | G55: 28 | H55: 31 | I55: 41 | J55: 41 | K55: 8 | L55: =SUM(B55:K55) -> 230
A56: ='Local HTA submissions'!AA10 -> Portugal | B56: =COUNTIFS('Local HTA submissions'!$B:$B,'By year'!$A56,'Local HTA submissions'!$H:$H,'By year'!B$47) -> 0 | C56: =COUNTIFS('Local HTA submissions'!$B:$B,'By year'!$A56,'Local HTA submissions'!$H:$H,'By year'!C$47) -> 0 | D56: =COUNTIFS('Local HTA submissions'!$B:$B,'By year'!$A56,'Local HTA submissions'!$H:$H,'By year'!D$47) -> 0 | E56: =COUNTIFS('Local HTA submissions'!$B:$B,'By year'!$A56,'Local HTA submissions'!$H:$H,'By year'!E$47) -> 0 | F56: =COUNTIFS('Local HTA submissions'!$B:$B,'By year'!$A56,'Local HTA submissions'!$H:$H,'By year'!F$47) -> 0 | G56: =COUNTIFS('Local HTA submissions'!$B:$B,'By year'!$A56,'Local HTA submissions'!$H:$H,'By year'!G$47) -> 0 | H56: =COUNTIFS('Local HTA submissions'!$B:$B,'By year'!$A56,'Local HTA submissions'!$H:$H,'By year'!H$47) -> 0 | I56: =COUNTIFS('Local HTA submissions'!$B:$B,'By year'!$A56,'Local HTA submissions'!$H:$H,'By year'!I$47) -> 0 | ... K56: =COUNTIFS('Local HTA submissions'!$B:$B,'By year'!$A56,'Local HTA submissions'!$H:$H,'By year'!K$47) -> 4 | L56: =SUM(B56:K56) -> 6
A57: ='Local HTA submissions'!AA11 -> Greece | B57: =COUNTIFS('Local HTA submissions'!$B:$B,'By year'!$A57,'Local HTA submissions'!$H:$H,'By year'!B$47) -> 0 | C57: =COUNTIFS('Local HTA submissions'!$B:$B,'By year'!$A57,'Local HTA submissions'!$H:$H,'By year'!C$47) -> 0 | D57: =COUNTIFS('Local HTA submissions'!$B:$B,'By year'!$A57,'Local HTA submissions'!$H:$H,'By year'!D$47) -> 0 | E57: =COUNTIFS('Local HTA submissions'!$B:$B,'By year'!$A57,'Local HTA submissions'!$H:$H,'By year'!E$47) -> 0 | F57: =COUNTIFS('Local HTA submissions'!$B:$B,'By year'!$A57,'Local HTA submissions'!$H:$H,'By year'!F$47) -> 0 | G57: =COUNTIFS('Local HTA submissions'!$B:$B,'By year'!$A57,'Local HTA submissions'!$H:$H,'By year'!G$47) -> 0 | H57: =COUNTIFS('Local HTA submissions'!$B:$B,'By year'!$A57,'Local HTA submissions'!$H:$H,'By year'!H$47) -> 1 | I57: =COUNTIFS('Local HTA submissions'!$B:$B,'By year'!$A57,'Local HTA submissions'!$H:$H,'By year'!I$47) -> 4 | ... K57: =COUNTIFS('Local HTA submissions'!$B:$B,'By year'!$A57,'Local HTA submissions'!$H:$H,'By year'!K$47) -> 6 | L57: =SUM(B57:K57) -> 20
A58: ='Local HTA submissions'!AA12 -> Netherlands | B58: =COUNTIFS('Local HTA submissions'!$B:$B,'By year'!$A58,'Local HTA submissions'!$H:$H,'By year'!B$47) -> 0 | C58: =COUNTIFS('Local HTA submissions'!$B:$B,'By year'!$A58,'Local HTA submissions'!$H:$H,'By year'!C$47) -> 0 | D58: =COUNTIFS('Local HTA submissions'!$B:$B,'By year'!$A58,'Local HTA submissions'!$H:$H,'By year'!D$47) -> 0 | E58: =COUNTIFS('Local HTA submissions'!$B:$B,'By year'!$A58,'Local HTA submissions'!$H:$H,'By year'!E$47) -> 0 | F58: =COUNTIFS('Local HTA submissions'!$B:$B,'By year'!$A58,'Local HTA submissions'!$H:$H,'By year'!F$47) -> 0 | G58: =COUNTIFS('Local HTA submissions'!$B:$B,'By year'!$A58,'Local HTA submissions'!$H:$H,'By year'!G$47) -> 0 | H58: =COUNTIFS('Local HTA submissions'!$B:$B,'By year'!$A58,'Local HTA submissions'!$H:$H,'By year'!H$47) -> 0 | I58: =COUNTIFS('Local HTA submissions'!$B:$B,'By year'!$A58,'Local HTA submissions'!$H:$H,'By year'!I$47) -> 2 | ... K58: =COUNTIFS('Local HTA submissions'!$B:$B,'By year'!$A58,'Local HTA submissions'!$H:$H,'By year'!K$47) -> 3 | L58: =SUM(B58:K58) -> 10
A59: ='Local HTA submissions'!AA13 -> Czech Republic | B59: =COUNTIFS('Local HTA submissions'!$B:$B,'By year'!$A59,'Local HTA submissions'!$H:$H,'By year'!B$47) -> 0 | C59: =COUNTIFS('Local HTA submissions'!$B:$B,'By year'!$A59,'Local HTA submissions'!$H:$H,'By year'!C$47) -> 0 | D59: =COUNTIFS('Local HTA submissions'!$B:$B,'By year'!$A59,'Local HTA submissions'!$H:$H,'By year'!D$47) -> 0 | E59: =COUNTIFS('Local HTA submissions'!$B:$B,'By year'!$A59,'Local HTA submissions'!$H:$H,'By year'!E$47) -> 0 | F59: =COUNTIFS('Local HTA submissions'!$B:$B,'By year'!$A59,'Local HTA submissions'!$H:$H,'By year'!F$47) -> 0 | G59: =COUNTIFS('Local HTA submissions'!$B:$B,'By year'!$A59,'Local HTA submissions'!$H:$H,'By year'!G$47) -> 0 | H59: =COUNTIFS('Local HTA submissions'!$B:$B,'By year'!$A59,'Local HTA submissions'!$H:$H,'By year'!H$47) -> 1 | I59: =COUNTIFS('Local HTA submissions'!$B:$B,'By year'!$A59,'Local HTA submissions'!$H:$H,'By year'!I$47) -> 0 | ... K59: =COUNTIFS('Local HTA submissions'!$B:$B,'By year'!$A59,'Local HTA submissions'!$H:$H,'By year'!K$47) -> 0 | L59: =SUM(B59:K59) -> 1
A60: ='Local HTA submissions'!AA14 -> Slovakia | B60: =COUNTIFS('Local HTA submissions'!$B:$B,'By year'!$A60,'Local HTA submissions'!$H:$H,'By year'!B$47) -> 0 | C60: =COUNTIFS('Local HTA submissions'!$B:$B,'By year'!$A60,'Local HTA submissions'!$H:$H,'By year'!C$47) -> 0 | D60: =COUNTIFS('Local HTA submissions'!$B:$B,'By year'!$A60,'Local HTA submissions'!$H:$H,'By year'!D$47) -> 0 | E60: =COUNTIFS('Local HTA submissions'!$B:$B,'By year'!$A60,'Local HTA submissions'!$H:$H,'By year'!E$47) -> 0 | F60: =COUNTIFS('Local HTA submissions'!$B:$B,'By year'!$A60,'Local HTA submissions'!$H:$H,'By year'!F$47) -> 0 | G60: =COUNTIFS('Local HTA submissions'!$B:$B,'By year'!$A60,'Local HTA submissions'!$H:$H,'By year'!G$47) -> 0 | H60: =COUNTIFS('Local HTA submissions'!$B:$B,'By year'!$A60,'Local HTA submissions'!$H:$H,'By year'!H$47) -> 1 | I60: =COUNTIFS('Local HTA submissions'!$B:$B,'By year'!$A60,'Local HTA submissions'!$H:$H,'By year'!I$47) -> 0 | ... K60: =COUNTIFS('Local HTA submissions'!$B:$B,'By year'!$A60,'Local HTA submissions'!$H:$H,'By year'!K$47) -> 0 | L60: =SUM(B60:K60) -> 1
A61: ='Local HTA submissions'!AA15 -> 0 | B61: =COUNTIFS('Local HTA submissions'!$B:$B,'By year'!$A61,'Local HTA submissions'!$H:$H,'By year'!B$47) -> 0 | C61: =COUNTIFS('Local HTA submissions'!$B:$B,'By year'!$A61,'Local HTA submissions'!$H:$H,'By year'!C$47) -> 0 | D61: =COUNTIFS('Local HTA submissions'!$B:$B,'By year'!$A61,'Local HTA submissions'!$H:$H,'By year'!D$47) -> 0 | E61: =COUNTIFS('Local HTA submissions'!$B:$B,'By year'!$A61,'Local HTA submissions'!$H:$H,'By year'!E$47) -> 0 | F61: =COUNTIFS('Local HTA submissions'!$B:$B,'By year'!$A61,'Local HTA submissions'!$H:$H,'By year'!F$47) -> 0 | G61: =COUNTIFS('Local HTA submissions'!$B:$B,'By year'!$A61,'Local HTA submissions'!$H:$H,'By year'!G$47) -> 0 | H61: =COUNTIFS('Local HTA submissions'!$B:$B,'By year'!$A61,'Local HTA submissions'!$H:$H,'By year'!H$47) -> 0 | I61: =COUNTIFS('Local HTA submissions'!$B:$B,'By year'!$A61,'Local HTA submissions'!$H:$H,'By year'!I$47) -> 0 | ... K61: =COUNTIFS('Local HTA submissions'!$B:$B,'By year'!$A61,'Local HTA submissions'!$H:$H,'By year'!K$47) -> 0 | L61: =SUM(B61:K61) -> 0
A62: ='Local HTA submissions'!AA16 -> 0 | B62: =COUNTIFS('Local HTA submissions'!$B:$B,'By year'!$A62,'Local HTA submissions'!$H:$H,'By year'!B$47) -> 0 | C62: =COUNTIFS('Local HTA submissions'!$B:$B,'By year'!$A62,'Local HTA submissions'!$H:$H,'By year'!C$47) -> 0 | D62: =COUNTIFS('Local HTA submissions'!$B:$B,'By year'!$A62,'Local HTA submissions'!$H:$H,'By year'!D$47) -> 0 | E62: =COUNTIFS('Local HTA submissions'!$B:$B,'By year'!$A62,'Local HTA submissions'!$H:$H,'By year'!E$47) -> 0 | F62: =COUNTIFS('Local HTA submissions'!$B:$B,'By year'!$A62,'Local HTA submissions'!$H:$H,'By year'!F$47) -> 0 | G62: =COUNTIFS('Local HTA submissions'!$B:$B,'By year'!$A62,'Local HTA submissions'!$H:$H,'By year'!G$47) -> 0 | H62: =COUNTIFS('Local HTA submissions'!$B:$B,'By year'!$A62,'Local HTA submissions'!$H:$H,'By year'!H$47) -> 0 | I62: =COUNTIFS('Local HTA submissions'!$B:$B,'By year'!$A62,'Local HTA submissions'!$H:$H,'By year'!I$47) -> 0 | ... K62: =COUNTIFS('Local HTA submissions'!$B:$B,'By year'!$A62,'Local HTA submissions'!$H:$H,'By year'!K$47) -> 0 | L62: =SUM(B62:K62) -> 0
A63: ='Local HTA submissions'!AA17 -> 0 | B63: =COUNTIFS('Local HTA submissions'!$B:$B,'By year'!$A63,'Local HTA submissions'!$H:$H,'By year'!B$47) -> 0 | C63: =COUNTIFS('Local HTA submissions'!$B:$B,'By year'!$A63,'Local HTA submissions'!$H:$H,'By year'!C$47) -> 0 | D63: =COUNTIFS('Local HTA submissions'!$B:$B,'By year'!$A63,'Local HTA submissions'!$H:$H,'By year'!D$47) -> 0 | E63: =COUNTIFS('Local HTA submissions'!$B:$B,'By year'!$A63,'Local HTA submissions'!$H:$H,'By year'!E$47) -> 0 | F63: =COUNTIFS('Local HTA submissions'!$B:$B,'By year'!$A63,'Local HTA submissions'!$H:$H,'By year'!F$47) -> 0 | G63: =COUNTIFS('Local HTA submissions'!$B:$B,'By year'!$A63,'Local HTA submissions'!$H:$H,'By year'!G$47) -> 0 | H63: =COUNTIFS('Local HTA submissions'!$B:$B,'By year'!$A63,'Local HTA submissions'!$H:$H,'By year'!H$47) -> 0 | I63: =COUNTIFS('Local HTA submissions'!$B:$B,'By year'!$A63,'Local HTA submissions'!$H:$H,'By year'!I$47) -> 0 | ... K63: =COUNTIFS('Local HTA submissions'!$B:$B,'By year'!$A63,'Local HTA submissions'!$H:$H,'By year'!K$47) -> 0 | L63: =SUM(B63:K63) -> 0
A64: ='Local HTA submissions'!AA18 -> 0 | B64: =COUNTIFS('Local HTA submissions'!$B:$B,'By year'!$A64,'Local HTA submissions'!$H:$H,'By year'!B$47) -> 0 | C64: =COUNTIFS('Local HTA submissions'!$B:$B,'By year'!$A64,'Local HTA submissions'!$H:$H,'By year'!C$47) -> 0 | D64: =COUNTIFS('Local HTA submissions'!$B:$B,'By year'!$A64,'Local HTA submissions'!$H:$H,'By year'!D$47) -> 0 | E64: =COUNTIFS('Local HTA submissions'!$B:$B,'By year'!$A64,'Local HTA submissions'!$H:$H,'By year'!E$47) -> 0 | F64: =COUNTIFS('Local HTA submissions'!$B:$B,'By year'!$A64,'Local HTA submissions'!$H:$H,'By year'!F$47) -> 0 | G64: =COUNTIFS('Local HTA submissions'!$B:$B,'By year'!$A64,'Local HTA submissions'!$H:$H,'By year'!G$47) -> 0 | H64: =COUNTIFS('Local HTA submissions'!$B:$B,'By year'!$A64,'Local HTA submissions'!$H:$H,'By year'!H$47) -> 0 | I64: =COUNTIFS('Local HTA submissions'!$B:$B,'By year'!$A64,'Local HTA submissions'!$H:$H,'By year'!I$47) -> 0 | ... K64: =COUNTIFS('Local HTA submissions'!$B:$B,'By year'!$A64,'Local HTA submissions'!$H:$H,'By year'!K$47) -> 0 | L64: =SUM(B64:K64) -> 0
A65: ='Local HTA submissions'!AA19 -> 0 | B65: =COUNTIFS('Local HTA submissions'!$B:$B,'By year'!$A65,'Local HTA submissions'!$H:$H,'By year'!B$47) -> 0 | C65: =COUNTIFS('Local HTA submissions'!$B:$B,'By year'!$A65,'Local HTA submissions'!$H:$H,'By year'!C$47) -> 0 | D65: =COUNTIFS('Local HTA submissions'!$B:$B,'By year'!$A65,'Local HTA submissions'!$H:$H,'By year'!D$47) -> 0 | E65: =COUNTIFS('Local HTA submissions'!$B:$B,'By year'!$A65,'Local HTA submissions'!$H:$H,'By year'!E$47) -> 0 | F65: =COUNTIFS('Local HTA submissions'!$B:$B,'By year'!$A65,'Local HTA submissions'!$H:$H,'By year'!F$47) -> 0 | G65: =COUNTIFS('Local HTA submissions'!$B:$B,'By year'!$A65,'Local HTA submissions'!$H:$H,'By year'!G$47) -> 0 | H65: =COUNTIFS('Local HTA submissions'!$B:$B,'By year'!$A65,'Local HTA submissions'!$H:$H,'By year'!H$47) -> 0 | I65: =COUNTIFS('Local HTA submissions'!$B:$B,'By year'!$A65,'Local HTA submissions'!$H:$H,'By year'!I$47) -> 0 | ... K65: =COUNTIFS('Local HTA submissions'!$B:$B,'By year'!$A65,'Local HTA submissions'!$H:$H,'By year'!K$47) -> 0 | L65: =SUM(B65:K65) -> 0
A66: All countries | B66: =COUNTIFS('Local HTA submissions'!$B:$B,'By year'!$A66,'Local HTA submissions'!$H:$H,'By year'!B$47) -> 0 | C66: =SUBTOTAL(109,C48:C65) -> 10 | D66: =SUBTOTAL(109,D48:D65) -> 5 | E66: =SUBTOTAL(109,E48:E65) -> 70 | F66: =SUBTOTAL(109,F48:F65) -> 64 | G66: =SUBTOTAL(109,G48:G65) -> 53 | H66: =SUBTOTAL(109,H48:H65) -> 69 | I66: =SUBTOTAL(109,I48:I65) -> 90 | J66: =SUBTOTAL(109,J48:J65) -> 114 | K66: =SUBTOTAL(109,K48:K65) -> 63 | L66: =SUM(B66:K66) -> 538
A89: HTA scientific advice
A91: HTA scientific advices by Year & HTA body
A92: Year | B92: CADTH | C92: EUnetHTA | D92: G-BA | E92: HAS | F92: NICE | G92: Parallel EMA / HTA | H92: ZIN | I92: Total
A93: ='HTA scientific advice'!N8 -> 0 | B93: =COUNTIFS(Table1[Year],'By year'!$A93,Table1[HTA body],'By year'!B$92) -> 0 | C93: =COUNTIFS(Table1[Year],'By year'!$A93,Table1[HTA body],'By year'!C$92) -> 0 | D93: =COUNTIFS(Table1[Year],'By year'!$A93,Table1[HTA body],'By year'!D$92) -> 0 | E93: =COUNTIFS(Table1[Year],'By year'!$A93,Table1[HTA body],'By year'!E$92) -> 0 | F93: =COUNTIFS(Table1[Year],'By year'!$A93,Table1[HTA body],'By year'!F$92) -> 0 | G93: =COUNTIFS(Table1[Year],'By year'!$A93,Table1[HTA body],'By year'!G$92) -> 0 | H93: =COUNTIFS(Table1[Year],'By year'!$A93,Table1[HTA body],'By year'!H$92) -> 0 | I93: =SUM(B93:H93) -> 0
A94: ='HTA scientific advice'!N9 -> 0 | B94: =COUNTIFS(Table1[Year],'By year'!$A94,Table1[HTA body],'By year'!B$92) -> 0 | C94: =COUNTIFS(Table1[Year],'By year'!$A94,Table1[HTA body],'By year'!C$92) -> 0 | D94: =COUNTIFS(Table1[Year],'By year'!$A94,Table1[HTA body],'By year'!D$92) -> 0 | E94: =COUNTIFS(Table1[Year],'By year'!$A94,Table1[HTA body],'By year'!E$92) -> 0 | F94: =COUNTIFS(Table1[Year],'By year'!$A94,Table1[HTA body],'By year'!F$92) -> 0 | G94: =COUNTIFS(Table1[Year],'By year'!$A94,Table1[HTA body],'By year'!G$92) -> 0 | H94: =COUNTIFS(Table1[Year],'By year'!$A94,Table1[HTA body],'By year'!H$92) -> 0 | I94: =SUM(B94:H94) -> 0
A95: ='HTA scientific advice'!N10 -> 0 | B95: =COUNTIFS(Table1[Year],'By year'!$A95,Table1[HTA body],'By year'!B$92) -> 0 | C95: =COUNTIFS(Table1[Year],'By year'!$A95,Table1[HTA body],'By year'!C$92) -> 0 | D95: =COUNTIFS(Table1[Year],'By year'!$A95,Table1[HTA body],'By year'!D$92) -> 0 | E95: =COUNTIFS(Table1[Year],'By year'!$A95,Table1[HTA body],'By year'!E$92) -> 0 | F95: =COUNTIFS(Table1[Year],'By year'!$A95,Table1[HTA body],'By year'!F$92) -> 0 | G95: =COUNTIFS(Table1[Year],'By year'!$A95,Table1[HTA body],'By year'!G$92) -> 0 | H95: =COUNTIFS(Table1[Year],'By year'!$A95,Table1[HTA body],'By year'!H$92) -> 0 | I95: =SUM(B95:H95) -> 0
A96: ='HTA scientific advice'!N11 -> 0 | B96: =COUNTIFS(Table1[Year],'By year'!$A96,Table1[HTA body],'By year'!B$92) -> 0 | C96: =COUNTIFS(Table1[Year],'By year'!$A96,Table1[HTA body],'By year'!C$92) -> 0 | D96: =COUNTIFS(Table1[Year],'By year'!$A96,Table1[HTA body],'By year'!D$92) -> 0 | E96: =COUNTIFS(Table1[Year],'By year'!$A96,Table1[HTA body],'By year'!E$92) -> 0 | F96: =COUNTIFS(Table1[Year],'By year'!$A96,Table1[HTA body],'By year'!F$92) -> 0 | G96: =COUNTIFS(Table1[Year],'By year'!$A96,Table1[HTA body],'By year'!G$92) -> 0 | H96: =COUNTIFS(Table1[Year],'By year'!$A96,Table1[HTA body],'By year'!H$92) -> 0 | I96: =SUM(B96:H96) -> 0
A97: ='HTA scientific advice'!N12 -> 0 | B97: =COUNTIFS(Table1[Year],'By year'!$A97,Table1[HTA body],'By year'!B$92) -> 0 | C97: =COUNTIFS(Table1[Year],'By year'!$A97,Table1[HTA body],'By year'!C$92) -> 0 | D97: =COUNTIFS(Table1[Year],'By year'!$A97,Table1[HTA body],'By year'!D$92) -> 0 | E97: =COUNTIFS(Table1[Year],'By year'!$A97,Table1[HTA body],'By year'!E$92) -> 0 | F97: =COUNTIFS(Table1[Year],'By year'!$A97,Table1[HTA body],'By year'!F$92) -> 0 | G97: =COUNTIFS(Table1[Year],'By year'!$A97,Table1[HTA body],'By year'!G$92) -> 0 | H97: =COUNTIFS(Table1[Year],'By year'!$A97,Table1[HTA body],'By year'!H$92) -> 0 | I97: =SUM(B97:H97) -> 0
A98: ='HTA scientific advice'!N13 -> 0 | B98: =COUNTIFS(Table1[Year],'By year'!$A98,Table1[HTA body],'By year'!B$92) -> 0 | C98: =COUNTIFS(Table1[Year],'By year'!$A98,Table1[HTA body],'By year'!C$92) -> 0 | D98: =COUNTIFS(Table1[Year],'By year'!$A98,Table1[HTA body],'By year'!D$92) -> 0 | E98: =COUNTIFS(Table1[Year],'By year'!$A98,Table1[HTA body],'By year'!E$92) -> 0 | F98: =COUNTIFS(Table1[Year],'By year'!$A98,Table1[HTA body],'By year'!F$92) -> 0 | G98: =COUNTIFS(Table1[Year],'By year'!$A98,Table1[HTA body],'By year'!G$92) -> 0 | H98: =COUNTIFS(Table1[Year],'By year'!$A98,Table1[HTA body],'By year'!H$92) -> 0 | I98: =SUM(B98:H98) -> 0
A99: ='HTA scientific advice'!N14 -> 0 | B99: =COUNTIFS(Table1[Year],'By year'!$A99,Table1[HTA body],'By year'!B$92) -> 0 | C99: =COUNTIFS(Table1[Year],'By year'!$A99,Table1[HTA body],'By year'!C$92) -> 0 | D99: =COUNTIFS(Table1[Year],'By year'!$A99,Table1[HTA body],'By year'!D$92) -> 0 | E99: =COUNTIFS(Table1[Year],'By year'!$A99,Table1[HTA body],'By year'!E$92) -> 0 | F99: =COUNTIFS(Table1[Year],'By year'!$A99,Table1[HTA body],'By year'!F$92) -> 0 | G99: =COUNTIFS(Table1[Year],'By year'!$A99,Table1[HTA body],'By year'!G$92) -> 0 | H99: =COUNTIFS(Table1[Year],'By year'!$A99,Table1[HTA body],'By year'!H$92) -> 0 | I99: =SUM(B99:H99) -> 0
A100: ='HTA scientific advice'!N15 -> 0 | B100: =COUNTIFS(Table1[Year],'By year'!$A100,Table1[HTA body],'By year'!B$92) -> 0 | C100: =COUNTIFS(Table1[Year],'By year'!$A100,Table1[HTA body],'By year'!C$92) -> 0 | D100: =COUNTIFS(Table1[Year],'By year'!$A100,Table1[HTA body],'By year'!D$92) -> 0 | E100: =COUNTIFS(Table1[Year],'By year'!$A100,Table1[HTA body],'By year'!E$92) -> 0 | F100: =COUNTIFS(Table1[Year],'By year'!$A100,Table1[HTA body],'By year'!F$92) -> 0 | G100: =COUNTIFS(Table1[Year],'By year'!$A100,Table1[HTA body],'By year'!G$92) -> 0 | H100: =COUNTIFS(Table1[Year],'By year'!$A100,Table1[HTA body],'By year'!H$92) -> 0 | I100: =SUM(B100:H100) -> 0
A101: ='HTA scientific advice'!N7 -> 2016 | B101: =COUNTIFS(Table1[Year],'By year'!$A101,Table1[HTA body],'By year'!B$92) -> 0 | C101: =COUNTIFS(Table1[Year],'By year'!$A101,Table1[HTA body],'By year'!C$92) -> 0 | D101: =COUNTIFS(Table1[Year],'By year'!$A101,Table1[HTA body],'By year'!D$92) -> 0 | E101: =COUNTIFS(Table1[Year],'By year'!$A101,Table1[HTA body],'By year'!E$92) -> 0 | F101: =COUNTIFS(Table1[Year],'By year'!$A101,Table1[HTA body],'By year'!F$92) -> 0 | G101: =COUNTIFS(Table1[Year],'By year'!$A101,Table1[HTA body],'By year'!G$92) -> 1 | H101: =COUNTIFS(Table1[Year],'By year'!$A101,Table1[HTA body],'By year'!H$92) -> 0 | I101: =SUM(B101:H101) -> 1
A102: ='HTA scientific advice'!N5 -> 2017 | B102: =COUNTIFS(Table1[Year],'By year'!$A102,Table1[HTA body],'By year'!B$92) -> 0 | C102: =COUNTIFS(Table1[Year],'By year'!$A102,Table1[HTA body],'By year'!C$92) -> 1 | D102: =COUNTIFS(Table1[Year],'By year'!$A102,Table1[HTA body],'By year'!D$92) -> 0 | E102: =COUNTIFS(Table1[Year],'By year'!$A102,Table1[HTA body],'By year'!E$92) -> 0 | F102: =COUNTIFS(Table1[Year],'By year'!$A102,Table1[HTA body],'By year'!F$92) -> 0 | G102: =COUNTIFS(Table1[Year],'By year'!$A102,Table1[HTA body],'By year'!G$92) -> 0 | H102: =COUNTIFS(Table1[Year],'By year'!$A102,Table1[HTA body],'By year'!H$92) -> 0 | I102: =SUM(B102:H102) -> 1
A103: ='HTA scientific advice'!N2 -> 2018 | B103: =COUNTIFS(Table1[Year],'By year'!$A103,Table1[HTA body],'By year'!B$92) -> 1 | C103: =COUNTIFS(Table1[Year],'By year'!$A103,Table1[HTA body],'By year'!C$92) -> 0 | D103: =COUNTIFS(Table1[Year],'By year'!$A103,Table1[HTA body],'By year'!D$92) -> 1 | E103: =COUNTIFS(Table1[Year],'By year'!$A103,Table1[HTA body],'By year'!E$92) -> 1 | F103: =COUNTIFS(Table1[Year],'By year'!$A103,Table1[HTA body],'By year'!F$92) -> 1 | G103: =COUNTIFS(Table1[Year],'By year'!$A103,Table1[HTA body],'By year'!G$92) -> 0 | H103: =COUNTIFS(Table1[Year],'By year'!$A103,Table1[HTA body],'By year'!H$92) -> 0 | I103: =SUM(B103:H103) -> 4
A104: ='HTA scientific advice'!N6 -> 2019 | B104: =COUNTIFS(Table1[Year],'By year'!$A104,Table1[HTA body],'By year'!B$92) -> 0 | C104: =COUNTIFS(Table1[Year],'By year'!$A104,Table1[HTA body],'By year'!C$92) -> 0 | D104: =COUNTIFS(Table1[Year],'By year'!$A104,Table1[HTA body],'By year'!D$92) -> 0 | E104: =COUNTIFS(Table1[Year],'By year'!$A104,Table1[HTA body],'By year'!E$92) -> 0 | F104: =COUNTIFS(Table1[Year],'By year'!$A104,Table1[HTA body],'By year'!F$92) -> 1 | G104: =COUNTIFS(Table1[Year],'By year'!$A104,Table1[HTA body],'By year'!G$92) -> 0 | H104: =COUNTIFS(Table1[Year],'By year'!$A104,Table1[HTA body],'By year'!H$92) -> 0 | I104: =SUM(B104:H104) -> 1
A105: ='HTA scientific advice'!N4 -> 2020 | B105: =COUNTIFS(Table1[Year],'By year'!$A105,Table1[HTA body],'By year'!B$92) -> 0 | C105: =COUNTIFS(Table1[Year],'By year'!$A105,Table1[HTA body],'By year'!C$92) -> 0 | D105: =COUNTIFS(Table1[Year],'By year'!$A105,Table1[HTA body],'By year'!D$92) -> 0 | E105: =COUNTIFS(Table1[Year],'By year'!$A105,Table1[HTA body],'By year'!E$92) -> 0 | F105: =COUNTIFS(Table1[Year],'By year'!$A105,Table1[HTA body],'By year'!F$92) -> 0 | G105: =COUNTIFS(Table1[Year],'By year'!$A105,Table1[HTA body],'By year'!G$92) -> 0 | H105: =COUNTIFS(Table1[Year],'By year'!$A105,Table1[HTA body],'By year'!H$92) -> 1 | I105: =SUM(B105:H105) -> 1
A106: ='HTA scientific advice'!N3 -> 2021 | B106: =COUNTIFS(Table1[Year],'By year'!$A106,Table1[HTA body],'By year'!B$92) -> 0 | C106: =COUNTIFS(Table1[Year],'By year'!$A106,Table1[HTA body],'By year'!C$92) -> 0 | D106: =COUNTIFS(Table1[Year],'By year'!$A106,Table1[HTA body],'By year'!D$92) -> 2 | E106: =COUNTIFS(Table1[Year],'By year'!$A106,Table1[HTA body],'By year'!E$92) -> 2 | F106: =COUNTIFS(Table1[Year],'By year'!$A106,Table1[HTA body],'By year'!F$92) -> 2 | G106: =COUNTIFS(Table1[Year],'By year'!$A106,Table1[HTA body],'By year'!G$92) -> 0 | H106: =COUNTIFS(Table1[Year],'By year'!$A106,Table1[HTA body],'By year'!H$92) -> 0 | I106: =SUM(B106:H106) -> 6
A107: Total | B107: =SUBTOTAL(109,Table6[CADTH]) -> 1 | C107: =SUBTOTAL(109,Table6[EUnetHTA]) -> 1 | D107: =SUBTOTAL(109,Table6[G-BA]) -> 3 | E107: =SUBTOTAL(109,Table6[HAS]) -> 3 | F107: =SUBTOTAL(109,Table6[NICE]) -> 4 | G107: =SUBTOTAL(109,Table6[Parallel EMA / HTA]) -> 1 | H107: =SUBTOTAL(109,Table6[ZIN]) -> 1 | I107: =SUBTOTAL(109,Table6[Total]) -> 14
A132: GVDs
A134: GVDs by Year & Indication
A135: Indication | B135: 2015 | C135: 2016 | D135: 2017 | E135: 2018 | F135: 2019 | G135: 2020 | H135: 2021 | I135: Total
A136: =GVDs!K26 -> 0 | B136: =COUNTIFS(Table2[Indication],'By year'!$A136,Table2[Year],'By year'!B$135) -> 0 | C136: =COUNTIFS(Table2[Indication],'By year'!$A136,Table2[Year],'By year'!C$135) -> 0 | D136: =COUNTIFS(Table2[Indication],'By year'!$A136,Table2[Year],'By year'!D$135) -> 0 | E136: =COUNTIFS(Table2[Indication],'By year'!$A136,Table2[Year],'By year'!E$135) -> 0 | F136: =COUNTIFS(Table2[Indication],'By year'!$A136,Table2[Year],'By year'!F$135) -> 0 | G136: =COUNTIFS(Table2[Indication],'By year'!$A136,Table2[Year],'By year'!G$135) -> 0 | H136: =COUNTIFS(Table2[Indication],'By year'!$A136,Table2[Year],'By year'!H$135) -> 0 | I136: =SUM(B136:H136) -> 0
A137: =GVDs!K27 -> 0 | B137: =COUNTIFS(Table2[Indication],'By year'!$A137,Table2[Year],'By year'!B$135) -> 0 | C137: =COUNTIFS(Table2[Indication],'By year'!$A137,Table2[Year],'By year'!C$135) -> 0 | D137: =COUNTIFS(Table2[Indication],'By year'!$A137,Table2[Year],'By year'!D$135) -> 0 | E137: =COUNTIFS(Table2[Indication],'By year'!$A137,Table2[Year],'By year'!E$135) -> 0 | F137: =COUNTIFS(Table2[Indication],'By year'!$A137,Table2[Year],'By year'!F$135) -> 0 | G137: =COUNTIFS(Table2[Indication],'By year'!$A137,Table2[Year],'By year'!G$135) -> 0 | H137: =COUNTIFS(Table2[Indication],'By year'!$A137,Table2[Year],'By year'!H$135) -> 0 | I137: =SUM(B137:H137) -> 0
A138: =GVDs!K28 -> 0 | B138: =COUNTIFS(Table2[Indication],'By year'!$A138,Table2[Year],'By year'!B$135) -> 0 | C138: =COUNTIFS(Table2[Indication],'By year'!$A138,Table2[Year],'By year'!C$135) -> 0 | D138: =COUNTIFS(Table2[Indication],'By year'!$A138,Table2[Year],'By year'!D$135) -> 0 | E138: =COUNTIFS(Table2[Indication],'By year'!$A138,Table2[Year],'By year'!E$135) -> 0 | F138: =COUNTIFS(Table2[Indication],'By year'!$A138,Table2[Year],'By year'!F$135) -> 0 | G138: =COUNTIFS(Table2[Indication],'By year'!$A138,Table2[Year],'By year'!G$135) -> 0 | H138: =COUNTIFS(Table2[Indication],'By year'!$A138,Table2[Year],'By year'!H$135) -> 0 | I138: =SUM(B138:H138) -> 0
A139: =GVDs!K29 -> 0 | B139: =COUNTIFS(Table2[Indication],'By year'!$A139,Table2[Year],'By year'!B$135) -> 0 | C139: =COUNTIFS(Table2[Indication],'By year'!$A139,Table2[Year],'By year'!C$135) -> 0 | D139: =COUNTIFS(Table2[Indication],'By year'!$A139,Table2[Year],'By year'!D$135) -> 0 | E139: =COUNTIFS(Table2[Indication],'By year'!$A139,Table2[Year],'By year'!E$135) -> 0 | F139: =COUNTIFS(Table2[Indication],'By year'!$A139,Table2[Year],'By year'!F$135) -> 0 | G139: =COUNTIFS(Table2[Indication],'By year'!$A139,Table2[Year],'By year'!G$135) -> 0 | H139: =COUNTIFS(Table2[Indication],'By year'!$A139,Table2[Year],'By year'!H$135) -> 0 | I139: =SUM(B139:H139) -> 0
A140: =GVDs!K30 -> 0 | B140: =COUNTIFS(Table2[Indication],'By year'!$A140,Table2[Year],'By year'!B$135) -> 0 | C140: =COUNTIFS(Table2[Indication],'By year'!$A140,Table2[Year],'By year'!C$135) -> 0 | D140: =COUNTIFS(Table2[Indication],'By year'!$A140,Table2[Year],'By year'!D$135) -> 0 | E140: =COUNTIFS(Table2[Indication],'By year'!$A140,Table2[Year],'By year'!E$135) -> 0 | F140: =COUNTIFS(Table2[Indication],'By year'!$A140,Table2[Year],'By year'!F$135) -> 0 | G140: =COUNTIFS(Table2[Indication],'By year'!$A140,Table2[Year],'By year'!G$135) -> 0 | H140: =COUNTIFS(Table2[Indication],'By year'!$A140,Table2[Year],'By year'!H$135) -> 0 | I140: =SUM(B140:H140) -> 0
A141: =GVDs!K31 -> 0 | B141: =COUNTIFS(Table2[Indication],'By year'!$A141,Table2[Year],'By year'!B$135) -> 0 | C141: =COUNTIFS(Table2[Indication],'By year'!$A141,Table2[Year],'By year'!C$135) -> 0 | D141: =COUNTIFS(Table2[Indication],'By year'!$A141,Table2[Year],'By year'!D$135) -> 0 | E141: =COUNTIFS(Table2[Indication],'By year'!$A141,Table2[Year],'By year'!E$135) -> 0 | F141: =COUNTIFS(Table2[Indication],'By year'!$A141,Table2[Year],'By year'!F$135) -> 0 | G141: =COUNTIFS(Table2[Indication],'By year'!$A141,Table2[Year],'By year'!G$135) -> 0 | H141: =COUNTIFS(Table2[Indication],'By year'!$A141,Table2[Year],'By year'!H$135) -> 0 | I141: =SUM(B141:H141) -> 0
A142: =GVDs!K32 -> 0 | B142: =COUNTIFS(Table2[Indication],'By year'!$A142,Table2[Year],'By year'!B$135) -> 0 | C142: =COUNTIFS(Table2[Indication],'By year'!$A142,Table2[Year],'By year'!C$135) -> 0 | D142: =COUNTIFS(Table2[Indication],'By year'!$A142,Table2[Year],'By year'!D$135) -> 0 | E142: =COUNTIFS(Table2[Indication],'By year'!$A142,Table2[Year],'By year'!E$135) -> 0 | F142: =COUNTIFS(Table2[Indication],'By year'!$A142,Table2[Year],'By year'!F$135) -> 0 | G142: =COUNTIFS(Table2[Indication],'By year'!$A142,Table2[Year],'By year'!G$135) -> 0 | H142: =COUNTIFS(Table2[Indication],'By year'!$A142,Table2[Year],'By year'!H$135) -> 0 | I142: =SUM(B142:H142) -> 0
A143: =GVDs!K33 -> 0 | B143: =COUNTIFS(Table2[Indication],'By year'!$A143,Table2[Year],'By year'!B$135) -> 0 | C143: =COUNTIFS(Table2[Indication],'By year'!$A143,Table2[Year],'By year'!C$135) -> 0 | D143: =COUNTIFS(Table2[Indication],'By year'!$A143,Table2[Year],'By year'!D$135) -> 0 | E143: =COUNTIFS(Table2[Indication],'By year'!$A143,Table2[Year],'By year'!E$135) -> 0 | F143: =COUNTIFS(Table2[Indication],'By year'!$A143,Table2[Year],'By year'!F$135) -> 0 | G143: =COUNTIFS(Table2[Indication],'By year'!$A143,Table2[Year],'By year'!G$135) -> 0 | H143: =COUNTIFS(Table2[Indication],'By year'!$A143,Table2[Year],'By year'!H$135) -> 0 | I143: =SUM(B143:H143) -> 0
A144: =GVDs!K34 -> 0 | B144: =COUNTIFS(Table2[Indication],'By year'!$A144,Table2[Year],'By year'!B$135) -> 0 | C144: =COUNTIFS(Table2[Indication],'By year'!$A144,Table2[Year],'By year'!C$135) -> 0 | D144: =COUNTIFS(Table2[Indication],'By year'!$A144,Table2[Year],'By year'!D$135) -> 0 | E144: =COUNTIFS(Table2[Indication],'By year'!$A144,Table2[Year],'By year'!E$135) -> 0 | F144: =COUNTIFS(Table2[Indication],'By year'!$A144,Table2[Year],'By year'!F$135) -> 0 | G144: =COUNTIFS(Table2[Indication],'By year'!$A144,Table2[Year],'By year'!G$135) -> 0 | H144: =COUNTIFS(Table2[Indication],'By year'!$A144,Table2[Year],'By year'!H$135) -> 0 | I144: =SUM(B144:H144) -> 0
A145: =GVDs!K35 -> 0 | B145: =COUNTIFS(Table2[Indication],'By year'!$A145,Table2[Year],'By year'!B$135) -> 0 | C145: =COUNTIFS(Table2[Indication],'By year'!$A145,Table2[Year],'By year'!C$135) -> 0 | D145: =COUNTIFS(Table2[Indication],'By year'!$A145,Table2[Year],'By year'!D$135) -> 0 | E145: =COUNTIFS(Table2[Indication],'By year'!$A145,Table2[Year],'By year'!E$135) -> 0 | F145: =COUNTIFS(Table2[Indication],'By year'!$A145,Table2[Year],'By year'!F$135) -> 0 | G145: =COUNTIFS(Table2[Indication],'By year'!$A145,Table2[Year],'By year'!G$135) -> 0 | H145: =COUNTIFS(Table2[Indication],'By year'!$A145,Table2[Year],'By year'!H$135) -> 0 | I145: =SUM(B145:H145) -> 0
A146: =GVDs!K36 -> 0 | B146: =COUNTIFS(Table2[Indication],'By year'!$A146,Table2[Year],'By year'!B$135) -> 0 | C146: =COUNTIFS(Table2[Indication],'By year'!$A146,Table2[Year],'By year'!C$135) -> 0 | D146: =COUNTIFS(Table2[Indication],'By year'!$A146,Table2[Year],'By year'!D$135) -> 0 | E146: =COUNTIFS(Table2[Indication],'By year'!$A146,Table2[Year],'By year'!E$135) -> 0 | F146: =COUNTIFS(Table2[Indication],'By year'!$A146,Table2[Year],'By year'!F$135) -> 0 | G146: =COUNTIFS(Table2[Indication],'By year'!$A146,Table2[Year],'By year'!G$135) -> 0 | H146: =COUNTIFS(Table2[Indication],'By year'!$A146,Table2[Year],'By year'!H$135) -> 0 | I146: =SUM(B146:H146) -> 0
A147: =GVDs!K4 -> Acromegaly product | B147: =COUNTIFS(Table2[Indication],'By year'!$A147,Table2[Year],'By year'!B$135) -> 1 | C147: =COUNTIFS(Table2[Indication],'By year'!$A147,Table2[Year],'By year'!C$135) -> 0 | D147: =COUNTIFS(Table2[Indication],'By year'!$A147,Table2[Year],'By year'!D$135) -> 0 | E147: =COUNTIFS(Table2[Indication],'By year'!$A147,Table2[Year],'By year'!E$135) -> 0 | F147: =COUNTIFS(Table2[Indication],'By year'!$A147,Table2[Year],'By year'!F$135) -> 0 | G147: =COUNTIFS(Table2[Indication],'By year'!$A147,Table2[Year],'By year'!G$135) -> 0 | H147: =COUNTIFS(Table2[Indication],'By year'!$A147,Table2[Year],'By year'!H$135) -> 0 | I147: =SUM(B147:H147) -> 1
A148: =GVDs!K25 -> Advanced renal cell carcinoma | B148: =COUNTIFS(Table2[Indication],'By year'!$A148,Table2[Year],'By year'!B$135) -> 0 | C148: =COUNTIFS(Table2[Indication],'By year'!$A148,Table2[Year],'By year'!C$135) -> 0 | D148: =COUNTIFS(Table2[Indication],'By year'!$A148,Table2[Year],'By year'!D$135) -> 0 | E148: =COUNTIFS(Table2[Indication],'By year'!$A148,Table2[Year],'By year'!E$135) -> 0 | F148: =COUNTIFS(Table2[Indication],'By year'!$A148,Table2[Year],'By year'!F$135) -> 0 | G148: =COUNTIFS(Table2[Indication],'By year'!$A148,Table2[Year],'By year'!G$135) -> 0 | H148: =COUNTIFS(Table2[Indication],'By year'!$A148,Table2[Year],'By year'!H$135) -> 1 | I148: =SUM(B148:H148) -> 1
A149: =GVDs!K2 -> Anticoagulant product in venous thromboembolism | B149: =COUNTIFS(Table2[Indication],'By year'!$A149,Table2[Year],'By year'!B$135) -> 1 | C149: =COUNTIFS(Table2[Indication],'By year'!$A149,Table2[Year],'By year'!C$135) -> 0 | D149: =COUNTIFS(Table2[Indication],'By year'!$A149,Table2[Year],'By year'!D$135) -> 0 | E149: =COUNTIFS(Table2[Indication],'By year'!$A149,Table2[Year],'By year'!E$135) -> 0 | F149: =COUNTIFS(Table2[Indication],'By year'!$A149,Table2[Year],'By year'!F$135) -> 0 | G149: =COUNTIFS(Table2[Indication],'By year'!$A149,Table2[Year],'By year'!G$135) -> 0 | H149: =COUNTIFS(Table2[Indication],'By year'!$A149,Table2[Year],'By year'!H$135) -> 0 | I149: =SUM(B149:H149) -> 1
A150: =GVDs!K9 -> Asthma product | B150: =COUNTIFS(Table2[Indication],'By year'!$A150,Table2[Year],'By year'!B$135) -> 0 | C150: =COUNTIFS(Table2[Indication],'By year'!$A150,Table2[Year],'By year'!C$135) -> 0 | D150: =COUNTIFS(Table2[Indication],'By year'!$A150,Table2[Year],'By year'!D$135) -> 1 | E150: =COUNTIFS(Table2[Indication],'By year'!$A150,Table2[Year],'By year'!E$135) -> 0 | F150: =COUNTIFS(Table2[Indication],'By year'!$A150,Table2[Year],'By year'!F$135) -> 0 | G150: =COUNTIFS(Table2[Indication],'By year'!$A150,Table2[Year],'By year'!G$135) -> 0 | H150: =COUNTIFS(Table2[Indication],'By year'!$A150,Table2[Year],'By year'!H$135) -> 0 | I150: =SUM(B150:H150) -> 1
A151: =GVDs!K10 -> Chronic Obstructive Pulmonary Disease product | B151: =COUNTIFS(Table2[Indication],'By year'!$A151,Table2[Year],'By year'!B$135) -> 0 | C151: =COUNTIFS(Table2[Indication],'By year'!$A151,Table2[Year],'By year'!C$135) -> 0 | D151: =COUNTIFS(Table2[Indication],'By year'!$A151,Table2[Year],'By year'!D$135) -> 1 | E151: =COUNTIFS(Table2[Indication],'By year'!$A151,Table2[Year],'By year'!E$135) -> 0 | F151: =COUNTIFS(Table2[Indication],'By year'!$A151,Table2[Year],'By year'!F$135) -> 0 | G151: =COUNTIFS(Table2[Indication],'By year'!$A151,Table2[Year],'By year'!G$135) -> 0 | H151: =COUNTIFS(Table2[Indication],'By year'!$A151,Table2[Year],'By year'!H$135) -> 0 | I151: =SUM(B151:H151) -> 1
A152: =GVDs!K24 -> COVID-19 infection | B152: =COUNTIFS(Table2[Indication],'By year'!$A152,Table2[Year],'By year'!B$135) -> 0 | C152: =COUNTIFS(Table2[Indication],'By year'!$A152,Table2[Year],'By year'!C$135) -> 0 | D152: =COUNTIFS(Table2[Indication],'By year'!$A152,Table2[Year],'By year'!D$135) -> 0 | E152: =COUNTIFS(Table2[Indication],'By year'!$A152,Table2[Year],'By year'!E$135) -> 0 | F152: =COUNTIFS(Table2[Indication],'By year'!$A152,Table2[Year],'By year'!F$135) -> 0 | G152: =COUNTIFS(Table2[Indication],'By year'!$A152,Table2[Year],'By year'!G$135) -> 0 | H152: =COUNTIFS(Table2[Indication],'By year'!$A152,Table2[Year],'By year'!H$135) -> 1 | I152: =SUM(B152:H152) -> 1
A153: =GVDs!K15 -> Cutaneous melanoma product | B153: =COUNTIFS(Table2[Indication],'By year'!$A153,Table2[Year],'By year'!B$135) -> 0 | C153: =COUNTIFS(Table2[Indication],'By year'!$A153,Table2[Year],'By year'!C$135) -> 0 | D153: =COUNTIFS(Table2[Indication],'By year'!$A153,Table2[Year],'By year'!D$135) -> 0 | E153: =COUNTIFS(Table2[Indication],'By year'!$A153,Table2[Year],'By year'!E$135) -> 1 | F153: =COUNTIFS(Table2[Indication],'By year'!$A153,Table2[Year],'By year'!F$135) -> 0 | G153: =COUNTIFS(Table2[Indication],'By year'!$A153,Table2[Year],'By year'!G$135) -> 0 | H153: =COUNTIFS(Table2[Indication],'By year'!$A153,Table2[Year],'By year'!H$135) -> 0 | I153: =SUM(B153:H153) -> 1
A154: =GVDs!K11 -> Diabetic peripheral neuropathy/post-herpetic neuralgia product | B154: =COUNTIFS(Table2[Indication],'By year'!$A154,Table2[Year],'By year'!B$135) -> 0 | C154: =COUNTIFS(Table2[Indication],'By year'!$A154,Table2[Year],'By year'!C$135) -> 0 | D154: =COUNTIFS(Table2[Indication],'By year'!$A154,Table2[Year],'By year'!D$135) -> 0 | E154: =COUNTIFS(Table2[Indication],'By year'!$A154,Table2[Year],'By year'!E$135) -> 1 | F154: =COUNTIFS(Table2[Indication],'By year'!$A154,Table2[Year],'By year'!F$135) -> 0 | G154: =COUNTIFS(Table2[Indication],'By year'!$A154,Table2[Year],'By year'!G$135) -> 0 | H154: =COUNTIFS(Table2[Indication],'By year'!$A154,Table2[Year],'By year'!H$135) -> 0 | I154: =SUM(B154:H154) -> 1
A155: =GVDs!K13 -> Digital treatment program for depression | B155: =COUNTIFS(Table2[Indication],'By year'!$A155,Table2[Year],'By year'!B$135) -> 0 | C155: =COUNTIFS(Table2[Indication],'By year'!$A155,Table2[Year],'By year'!C$135) -> 0 | D155: =COUNTIFS(Table2[Indication],'By year'!$A155,Table2[Year],'By year'!D$135) -> 0 | E155: =COUNTIFS(Table2[Indication],'By year'!$A155,Table2[Year],'By year'!E$135) -> 1 | F155: =COUNTIFS(Table2[Indication],'By year'!$A155,Table2[Year],'By year'!F$135) -> 0 | G155: =COUNTIFS(Table2[Indication],'By year'!$A155,Table2[Year],'By year'!G$135) -> 0 | H155: =COUNTIFS(Table2[Indication],'By year'!$A155,Table2[Year],'By year'!H$135) -> 0 | I155: =SUM(B155:H155) -> 1
A156: =GVDs!K6 -> DPP-4 / SGLT-2 combination product in T2DM (update) | B156: =COUNTIFS(Table2[Indication],'By year'!$A156,Table2[Year],'By year'!B$135) -> 0 | C156: =COUNTIFS(Table2[Indication],'By year'!$A156,Table2[Year],'By year'!C$135) -> 1 | D156: =COUNTIFS(Table2[Indication],'By year'!$A156,Table2[Year],'By year'!D$135) -> 0 | E156: =COUNTIFS(Table2[Indication],'By year'!$A156,Table2[Year],'By year'!E$135) -> 0 | F156: =COUNTIFS(Table2[Indication],'By year'!$A156,Table2[Year],'By year'!F$135) -> 0 | G156: =COUNTIFS(Table2[Indication],'By year'!$A156,Table2[Year],'By year'!G$135) -> 0 | H156: =COUNTIFS(Table2[Indication],'By year'!$A156,Table2[Year],'By year'!H$135) -> 0 | I156: =SUM(B156:H156) -> 1
A157: =GVDs!K17 -> Epilepsy product (update) | B157: =COUNTIFS(Table2[Indication],'By year'!$A157,Table2[Year],'By year'!B$135) -> 0 | C157: =COUNTIFS(Table2[Indication],'By year'!$A157,Table2[Year],'By year'!C$135) -> 0 | D157: =COUNTIFS(Table2[Indication],'By year'!$A157,Table2[Year],'By year'!D$135) -> 0 | E157: =COUNTIFS(Table2[Indication],'By year'!$A157,Table2[Year],'By year'!E$135) -> 0 | F157: =COUNTIFS(Table2[Indication],'By year'!$A157,Table2[Year],'By year'!F$135) -> 1 | G157: =COUNTIFS(Table2[Indication],'By year'!$A157,Table2[Year],'By year'!G$135) -> 0 | H157: =COUNTIFS(Table2[Indication],'By year'!$A157,Table2[Year],'By year'!H$135) -> 0 | I157: =SUM(B157:H157) -> 1
A158: =GVDs!K14 -> GLP-1 agonist product in T2DM | B158: =COUNTIFS(Table2[Indication],'By year'!$A158,Table2[Year],'By year'!B$135) -> 0 | C158: =COUNTIFS(Table2[Indication],'By year'!$A158,Table2[Year],'By year'!C$135) -> 0 | D158: =COUNTIFS(Table2[Indication],'By year'!$A158,Table2[Year],'By year'!D$135) -> 0 | E158: =COUNTIFS(Table2[Indication],'By year'!$A158,Table2[Year],'By year'!E$135) -> 1 | F158: =COUNTIFS(Table2[Indication],'By year'!$A158,Table2[Year],'By year'!F$135) -> 0 | G158: =COUNTIFS(Table2[Indication],'By year'!$A158,Table2[Year],'By year'!G$135) -> 0 | H158: =COUNTIFS(Table2[Indication],'By year'!$A158,Table2[Year],'By year'!H$135) -> 0 | I158: =SUM(B158:H158) -> 1
A159: =GVDs!K19 -> Hepatocellular cell carcinoma/renal cell carcinoma product | B159: =COUNTIFS(Table2[Indication],'By year'!$A159,Table2[Year],'By year'!B$135) -> 0 | C159: =COUNTIFS(Table2[Indication],'By year'!$A159,Table2[Year],'By year'!C$135) -> 0 | D159: =COUNTIFS(Table2[Indication],'By year'!$A159,Table2[Year],'By year'!D$135) -> 0 | E159: =COUNTIFS(Table2[Indication],'By year'!$A159,Table2[Year],'By year'!E$135) -> 0 | F159: =COUNTIFS(Table2[Indication],'By year'!$A159,Table2[Year],'By year'!F$135) -> 1 | G159: =COUNTIFS(Table2[Indication],'By year'!$A159,Table2[Year],'By year'!G$135) -> 0 | H159: =COUNTIFS(Table2[Indication],'By year'!$A159,Table2[Year],'By year'!H$135) -> 0 | I159: =SUM(B159:H159) -> 1
A160: =GVDs!K18 -> HIV product | B160: =COUNTIFS(Table2[Indication],'By year'!$A160,Table2[Year],'By year'!B$135) -> 0 | C160: =COUNTIFS(Table2[Indication],'By year'!$A160,Table2[Year],'By year'!C$135) -> 0 | D160: =COUNTIFS(Table2[Indication],'By year'!$A160,Table2[Year],'By year'!D$135) -> 0 | E160: =COUNTIFS(Table2[Indication],'By year'!$A160,Table2[Year],'By year'!E$135) -> 0 | F160: =COUNTIFS(Table2[Indication],'By year'!$A160,Table2[Year],'By year'!F$135) -> 1 | G160: =COUNTIFS(Table2[Indication],'By year'!$A160,Table2[Year],'By year'!G$135) -> 0 | H160: =COUNTIFS(Table2[Indication],'By year'!$A160,Table2[Year],'By year'!H$135) -> 0 | I160: =SUM(B160:H160) -> 1
A161: =GVDs!K5 -> Hyperkalemia product | B161: =COUNTIFS(Table2[Indication],'By year'!$A161,Table2[Year],'By year'!B$135) -> 0 | C161: =COUNTIFS(Table2[Indication],'By year'!$A161,Table2[Year],'By year'!C$135) -> 1 | D161: =COUNTIFS(Table2[Indication],'By year'!$A161,Table2[Year],'By year'!D$135) -> 0 | E161: =COUNTIFS(Table2[Indication],'By year'!$A161,Table2[Year],'By year'!E$135) -> 0 | F161: =COUNTIFS(Table2[Indication],'By year'!$A161,Table2[Year],'By year'!F$135) -> 0 | G161: =COUNTIFS(Table2[Indication],'By year'!$A161,Table2[Year],'By year'!G$135) -> 0 | H161: =COUNTIFS(Table2[Indication],'By year'!$A161,Table2[Year],'By year'!H$135) -> 0 | I161: =SUM(B161:H161) -> 1
A162: =GVDs!K3 -> Mantle Cell Lymphoma product | B162: =COUNTIFS(Table2[Indication],'By year'!$A162,Table2[Year],'By year'!B$135) -> 1 | C162: =COUNTIFS(Table2[Indication],'By year'!$A162,Table2[Year],'By year'!C$135) -> 0 | D162: =COUNTIFS(Table2[Indication],'By year'!$A162,Table2[Year],'By year'!D$135) -> 0 | E162: =COUNTIFS(Table2[Indication],'By year'!$A162,Table2[Year],'By year'!E$135) -> 0 | F162: =COUNTIFS(Table2[Indication],'By year'!$A162,Table2[Year],'By year'!F$135) -> 0 | G162: =COUNTIFS(Table2[Indication],'By year'!$A162,Table2[Year],'By year'!G$135) -> 0 | H162: =COUNTIFS(Table2[Indication],'By year'!$A162,Table2[Year],'By year'!H$135) -> 0 | I162: =SUM(B162:H162) -> 1
A163: =GVDs!K7 -> Melanoma | B163: =COUNTIFS(Table2[Indication],'By year'!$A163,Table2[Year],'By year'!B$135) -> 0 | C163: =COUNTIFS(Table2[Indication],'By year'!$A163,Table2[Year],'By year'!C$135) -> 0 | D163: =COUNTIFS(Table2[Indication],'By year'!$A163,Table2[Year],'By year'!D$135) -> 1 | E163: =COUNTIFS(Table2[Indication],'By year'!$A163,Table2[Year],'By year'!E$135) -> 0 | F163: =COUNTIFS(Table2[Indication],'By year'!$A163,Table2[Year],'By year'!F$135) -> 0 | G163: =COUNTIFS(Table2[Indication],'By year'!$A163,Table2[Year],'By year'!G$135) -> 0 | H163: =COUNTIFS(Table2[Indication],'By year'!$A163,Table2[Year],'By year'!H$135) -> 0 | I163: =SUM(B163:H163) -> 1
A164: =GVDs!K8 -> Metastatic colorectal cancer product | B164: =COUNTIFS(Table2[Indication],'By year'!$A164,Table2[Year],'By year'!B$135) -> 0 | C164: =COUNTIFS(Table2[Indication],'By year'!$A164,Table2[Year],'By year'!C$135) -> 0 | D164: =COUNTIFS(Table2[Indication],'By year'!$A164,Table2[Year],'By year'!D$135) -> 1 | E164: =COUNTIFS(Table2[Indication],'By year'!$A164,Table2[Year],'By year'!E$135) -> 0 | F164: =COUNTIFS(Table2[Indication],'By year'!$A164,Table2[Year],'By year'!F$135) -> 0 | G164: =COUNTIFS(Table2[Indication],'By year'!$A164,Table2[Year],'By year'!G$135) -> 0 | H164: =COUNTIFS(Table2[Indication],'By year'!$A164,Table2[Year],'By year'!H$135) -> 0 | I164: =SUM(B164:H164) -> 1
A165: =GVDs!K20 -> Non Hodgkin Lymphoma | B165: =COUNTIFS(Table2[Indication],'By year'!$A165,Table2[Year],'By year'!B$135) -> 0 | C165: =COUNTIFS(Table2[Indication],'By year'!$A165,Table2[Year],'By year'!C$135) -> 0 | D165: =COUNTIFS(Table2[Indication],'By year'!$A165,Table2[Year],'By year'!D$135) -> 0 | E165: =COUNTIFS(Table2[Indication],'By year'!$A165,Table2[Year],'By year'!E$135) -> 0 | F165: =COUNTIFS(Table2[Indication],'By year'!$A165,Table2[Year],'By year'!F$135) -> 0 | G165: =COUNTIFS(Table2[Indication],'By year'!$A165,Table2[Year],'By year'!G$135) -> 1 | H165: =COUNTIFS(Table2[Indication],'By year'!$A165,Table2[Year],'By year'!H$135) -> 0 | I165: =SUM(B165:H165) -> 1
A166: =GVDs!K16 -> Non-small cell lung cancer IO product | B166: =COUNTIFS(Table2[Indication],'By year'!$A166,Table2[Year],'By year'!B$135) -> 0 | C166: =COUNTIFS(Table2[Indication],'By year'!$A166,Table2[Year],'By year'!C$135) -> 0 | D166: =COUNTIFS(Table2[Indication],'By year'!$A166,Table2[Year],'By year'!D$135) -> 0 | E166: =COUNTIFS(Table2[Indication],'By year'!$A166,Table2[Year],'By year'!E$135) -> 1 | F166: =COUNTIFS(Table2[Indication],'By year'!$A166,Table2[Year],'By year'!F$135) -> 0 | G166: =COUNTIFS(Table2[Indication],'By year'!$A166,Table2[Year],'By year'!G$135) -> 0 | H166: =COUNTIFS(Table2[Indication],'By year'!$A166,Table2[Year],'By year'!H$135) -> 0 | I166: =SUM(B166:H166) -> 1
A167: =GVDs!K12 -> Pseudomonas aeruginosa anti-infective product | B167: =COUNTIFS(Table2[Indication],'By year'!$A167,Table2[Year],'By year'!B$135) -> 0 | C167: =COUNTIFS(Table2[Indication],'By year'!$A167,Table2[Year],'By year'!C$135) -> 0 | D167: =COUNTIFS(Table2[Indication],'By year'!$A167,Table2[Year],'By year'!D$135) -> 0 | E167: =COUNTIFS(Table2[Indication],'By year'!$A167,Table2[Year],'By year'!E$135) -> 1 | F167: =COUNTIFS(Table2[Indication],'By year'!$A167,Table2[Year],'By year'!F$135) -> 0 | G167: =COUNTIFS(Table2[Indication],'By year'!$A167,Table2[Year],'By year'!G$135) -> 0 | H167: =COUNTIFS(Table2[Indication],'By year'!$A167,Table2[Year],'By year'!H$135) -> 0 | I167: =SUM(B167:H167) -> 1
A168: =GVDs!K21 -> Relapsed/refractory AML product | B168: =COUNTIFS(Table2[Indication],'By year'!$A168,Table2[Year],'By year'!B$135) -> 0 | C168: =COUNTIFS(Table2[Indication],'By year'!$A168,Table2[Year],'By year'!C$135) -> 0 | D168: =COUNTIFS(Table2[Indication],'By year'!$A168,Table2[Year],'By year'!D$135) -> 0 | E168: =COUNTIFS(Table2[Indication],'By year'!$A168,Table2[Year],'By year'!E$135) -> 0 | F168: =COUNTIFS(Table2[Indication],'By year'!$A168,Table2[Year],'By year'!F$135) -> 0 | G168: =COUNTIFS(Table2[Indication],'By year'!$A168,Table2[Year],'By year'!G$135) -> 1 | H168: =COUNTIFS(Table2[Indication],'By year'!$A168,Table2[Year],'By year'!H$135) -> 0 | I168: =SUM(B168:H168) -> 1
A169: =GVDs!K22 -> Unresectable malignant pleural mesothelioma | B169: =COUNTIFS(Table2[Indication],'By year'!$A169,Table2[Year],'By year'!B$135) -> 0 | C169: =COUNTIFS(Table2[Indication],'By year'!$A169,Table2[Year],'By year'!C$135) -> 0 | D169: =COUNTIFS(Table2[Indication],'By year'!$A169,Table2[Year],'By year'!D$135) -> 0 | E169: =COUNTIFS(Table2[Indication],'By year'!$A169,Table2[Year],'By year'!E$135) -> 0 | F169: =COUNTIFS(Table2[Indication],'By year'!$A169,Table2[Year],'By year'!F$135) -> 0 | G169: =COUNTIFS(Table2[Indication],'By year'!$A169,Table2[Year],'By year'!G$135) -> 1 | H169: =COUNTIFS(Table2[Indication],'By year'!$A169,Table2[Year],'By year'!H$135) -> 0 | I169: =SUM(B169:H169) -> 1
A170: =GVDs!K23 -> von Willebrand disease (an inherited bleeding disorder) | B170: =COUNTIFS(Table2[Indication],'By year'!$A170,Table2[Year],'By year'!B$135) -> 0 | C170: =COUNTIFS(Table2[Indication],'By year'!$A170,Table2[Year],'By year'!C$135) -> 0 | D170: =COUNTIFS(Table2[Indication],'By year'!$A170,Table2[Year],'By year'!D$135) -> 0 | E170: =COUNTIFS(Table2[Indication],'By year'!$A170,Table2[Year],'By year'!E$135) -> 0 | F170: =COUNTIFS(Table2[Indication],'By year'!$A170,Table2[Year],'By year'!F$135) -> 0 | G170: =COUNTIFS(Table2[Indication],'By year'!$A170,Table2[Year],'By year'!G$135) -> 0 | H170: =COUNTIFS(Table2[Indication],'By year'!$A170,Table2[Year],'By year'!H$135) -> 1 | I170: =SUM(B170:H170) -> 1
A171: Total | B171: =SUBTOTAL(109,B136:B170) -> 3 | C171: =SUBTOTAL(109,C136:C170) -> 2 | D171: =SUBTOTAL(109,D136:D170) -> 4 | E171: =SUBTOTAL(109,E136:E170) -> 6 | F171: =SUBTOTAL(109,F136:F170) -> 3 | G171: =SUBTOTAL(109,G136:G170) -> 3 | H171: =SUBTOTAL(109,H136:H170) -> 3 | I171: =SUBTOTAL(109,Table7[Total]) -> 24

Sheet By therapy area
A1: Local HTA submissions
A3: HTA submissions by Therapy area & HTA body
A4: Therapy area | B4: NICE | C4: SMC | D4: AWMSG | E4: NCPE | F4: G-BA | G4: N/A | H4: AIFA | I4: CEESP | J4: CT | K4: INFARMED | L4: Greek HTA Committee | M4: Zorginstituut Nederland | N4: Zorgverzekeraars Nederland | O4: SUKL | P4: ŠUKL | Q4: Total | R4: Percentage
A5: ='Local HTA submissions'!AD2 -> Oncology | B5: =COUNTIFS('Local HTA submissions'!$E:$E,'By therapy area'!$A5,'Local HTA submissions'!$C:$C,'By therapy area'!B$4) -> 20 | C5: =COUNTIFS('Local HTA submissions'!$E:$E,'By therapy area'!$A5,'Local HTA submissions'!$C:$C,'By therapy area'!C$4) -> 10 | D5: =COUNTIFS('Local HTA submissions'!$E:$E,'By therapy area'!$A5,'Local HTA submissions'!$C:$C,'By therapy area'!D$4) -> 1 | E5: =COUNTIFS('Local HTA submissions'!$E:$E,'By therapy area'!$A5,'Local HTA submissions'!$C:$C,'By therapy area'!E$4) -> 6 | F5: =COUNTIFS('Local HTA submissions'!$E:$E,'By therapy area'!$A5,'Local HTA submissions'!$C:$C,'By therapy area'!F$4) -> 39 | G5: =COUNTIFS('Local HTA submissions'!$E:$E,'By therapy area'!$A5,'Local HTA submissions'!$C:$C,'By therapy area'!G$4) -> 7 | H5: =COUNTIFS('Local HTA submissions'!$E:$E,'By therapy area'!$A5,'Local HTA submissions'!$C:$C,'By therapy area'!H$4) -> 21 | I5: =COUNTIFS('Local HTA submissions'!$E:$E,'By therapy area'!$A5,'Local HTA submissions'!$C:$C,'By therapy area'!I$4) -> 26 | ... P5: =COUNTIFS('Local HTA submissions'!$E:$E,'By therapy area'!$A5,'Local HTA submissions'!$C:$C,'By therapy area'!P$4) -> 1 | Q5: =SUM(B5:P5) -> 174 | R5: =Q5/$Q$38 -> 0.31693989
A6: ='Local HTA submissions'!AD3 -> Blood and immune system | B6: =COUNTIFS('Local HTA submissions'!$E:$E,'By therapy area'!$A6,'Local HTA submissions'!$C:$C,'By therapy area'!B$4) -> 1 | C6: =COUNTIFS('Local HTA submissions'!$E:$E,'By therapy area'!$A6,'Local HTA submissions'!$C:$C,'By therapy area'!C$4) -> 1 | D6: =COUNTIFS('Local HTA submissions'!$E:$E,'By therapy area'!$A6,'Local HTA submissions'!$C:$C,'By therapy area'!D$4) -> 0 | E6: =COUNTIFS('Local HTA submissions'!$E:$E,'By therapy area'!$A6,'Local HTA submissions'!$C:$C,'By therapy area'!E$4) -> 1 | F6: =COUNTIFS('Local HTA submissions'!$E:$E,'By therapy area'!$A6,'Local HTA submissions'!$C:$C,'By therapy area'!F$4) -> 3 | G6: =COUNTIFS('Local HTA submissions'!$E:$E,'By therapy area'!$A6,'Local HTA submissions'!$C:$C,'By therapy area'!G$4) -> 0 | H6: =COUNTIFS('Local HTA submissions'!$E:$E,'By therapy area'!$A6,'Local HTA submissions'!$C:$C,'By therapy area'!H$4) -> 5 | I6: =COUNTIFS('Local HTA submissions'!$E:$E,'By therapy area'!$A6,'Local HTA submissions'!$C:$C,'By therapy area'!I$4) -> 1 | ... P6: =COUNTIFS('Local HTA submissions'!$E:$E,'By therapy area'!$A6,'Local HTA submissions'!$C:$C,'By therapy area'!P$4) -> 0 | Q6: =SUM(B6:P6) -> 16 | R6: =Q6/$Q$38 -> 0.029143898
A7: ='Local HTA submissions'!AD4 -> Gastroenterology | B7: =COUNTIFS('Local HTA submissions'!$E:$E,'By therapy area'!$A7,'Local HTA submissions'!$C:$C,'By therapy area'!B$4) -> 1 | C7: =COUNTIFS('Local HTA submissions'!$E:$E,'By therapy area'!$A7,'Local HTA submissions'!$C:$C,'By therapy area'!C$4) -> 1 | D7: =COUNTIFS('Local HTA submissions'!$E:$E,'By therapy area'!$A7,'Local HTA submissions'!$C:$C,'By therapy area'!D$4) -> 0 | E7: =COUNTIFS('Local HTA submissions'!$E:$E,'By therapy area'!$A7,'Local HTA submissions'!$C:$C,'By therapy area'!E$4) -> 0 | F7: =COUNTIFS('Local HTA submissions'!$E:$E,'By therapy area'!$A7,'Local HTA submissions'!$C:$C,'By therapy area'!F$4) -> 0 | G7: =COUNTIFS('Local HTA submissions'!$E:$E,'By therapy area'!$A7,'Local HTA submissions'!$C:$C,'By therapy area'!G$4) -> 0 | H7: =COUNTIFS('Local HTA submissions'!$E:$E,'By therapy area'!$A7,'Local HTA submissions'!$C:$C,'By therapy area'!H$4) -> 0 | I7: =COUNTIFS('Local HTA submissions'!$E:$E,'By therapy area'!$A7,'Local HTA submissions'!$C:$C,'By therapy area'!I$4) -> 0 | ... P7: =COUNTIFS('Local HTA submissions'!$E:$E,'By therapy area'!$A7,'Local HTA submissions'!$C:$C,'By therapy area'!P$4) -> 0 | Q7: =SUM(B7:P7) -> 2 | R7: =Q7/$Q$38 -> 0.0036429872
A8: ='Local HTA submissions'!AD5 -> Cardiovascular diseases | B8: =COUNTIFS('Local HTA submissions'!$E:$E,'By therapy area'!$A8,'Local HTA submissions'!$C:$C,'By therapy area'!B$4) -> 6 | C8: =COUNTIFS('Local HTA submissions'!$E:$E,'By therapy area'!$A8,'Local HTA submissions'!$C:$C,'By therapy area'!C$4) -> 0 | D8: =COUNTIFS('Local HTA submissions'!$E:$E,'By therapy area'!$A8,'Local HTA submissions'!$C:$C,'By therapy area'!D$4) -> 1 | E8: =COUNTIFS('Local HTA submissions'!$E:$E,'By therapy area'!$A8,'Local HTA submissions'!$C:$C,'By therapy area'!E$4) -> 1 | F8: =COUNTIFS('Local HTA submissions'!$E:$E,'By therapy area'!$A8,'Local HTA submissions'!$C:$C,'By therapy area'!F$4) -> 2 | G8: =COUNTIFS('Local HTA submissions'!$E:$E,'By therapy area'!$A8,'Local HTA submissions'!$C:$C,'By therapy area'!G$4) -> 4 | H8: =COUNTIFS('Local HTA submissions'!$E:$E,'By therapy area'!$A8,'Local HTA submissions'!$C:$C,'By therapy area'!H$4) -> 1 | I8: =COUNTIFS('Local HTA submissions'!$E:$E,'By therapy area'!$A8,'Local HTA submissions'!$C:$C,'By therapy area'!I$4) -> 6 | ... P8: =COUNTIFS('Local HTA submissions'!$E:$E,'By therapy area'!$A8,'Local HTA submissions'!$C:$C,'By therapy area'!P$4) -> 0 | Q8: =SUM(B8:P8) -> 39 | R8: =Q8/$Q$38 -> 0.071038251
A9: ='Local HTA submissions'!AD6 -> Respiratory | B9: =COUNTIFS('Local HTA submissions'!$E:$E,'By therapy area'!$A9,'Local HTA submissions'!$C:$C,'By therapy area'!B$4) -> 1 | C9: =COUNTIFS('Local HTA submissions'!$E:$E,'By therapy area'!$A9,'Local HTA submissions'!$C:$C,'By therapy area'!C$4) -> 1 | D9: =COUNTIFS('Local HTA submissions'!$E:$E,'By therapy area'!$A9,'Local HTA submissions'!$C:$C,'By therapy area'!D$4) -> 0 | E9: =COUNTIFS('Local HTA submissions'!$E:$E,'By therapy area'!$A9,'Local HTA submissions'!$C:$C,'By therapy area'!E$4) -> 0 | F9: =COUNTIFS('Local HTA submissions'!$E:$E,'By therapy area'!$A9,'Local HTA submissions'!$C:$C,'By therapy area'!F$4) -> 0 | G9: =COUNTIFS('Local HTA submissions'!$E:$E,'By therapy area'!$A9,'Local HTA submissions'!$C:$C,'By therapy area'!G$4) -> 4 | H9: =COUNTIFS('Local HTA submissions'!$E:$E,'By therapy area'!$A9,'Local HTA submissions'!$C:$C,'By therapy area'!H$4) -> 3 | I9: =COUNTIFS('Local HTA submissions'!$E:$E,'By therapy area'!$A9,'Local HTA submissions'!$C:$C,'By therapy area'!I$4) -> 1 | ... P9: =COUNTIFS('Local HTA submissions'!$E:$E,'By therapy area'!$A9,'Local HTA submissions'!$C:$C,'By therapy area'!P$4) -> 0 | Q9: =SUM(B9:P9) -> 24 | R9: =Q9/$Q$38 -> 0.043715847
A10: ='Local HTA submissions'!AD7 -> Muscoloskeletal | B10: =COUNTIFS('Local HTA submissions'!$E:$E,'By therapy area'!$A10,'Local HTA submissions'!$C:$C,'By therapy area'!B$4) -> 5 | C10: =COUNTIFS('Local HTA submissions'!$E:$E,'By therapy area'!$A10,'Local HTA submissions'!$C:$C,'By therapy area'!C$4) -> 2 | D10: =COUNTIFS('Local HTA submissions'!$E:$E,'By therapy area'!$A10,'Local HTA submissions'!$C:$C,'By therapy area'!D$4) -> 0 | E10: =COUNTIFS('Local HTA submissions'!$E:$E,'By therapy area'!$A10,'Local HTA submissions'!$C:$C,'By therapy area'!E$4) -> 2 | F10: =COUNTIFS('Local HTA submissions'!$E:$E,'By therapy area'!$A10,'Local HTA submissions'!$C:$C,'By therapy area'!F$4) -> 3 | G10: =COUNTIFS('Local HTA submissions'!$E:$E,'By therapy area'!$A10,'Local HTA submissions'!$C:$C,'By therapy area'!G$4) -> 2 | H10: =COUNTIFS('Local HTA submissions'!$E:$E,'By therapy area'!$A10,'Local HTA submissions'!$C:$C,'By therapy area'!H$4) -> 1 | I10: =COUNTIFS('Local HTA submissions'!$E:$E,'By therapy area'!$A10,'Local HTA submissions'!$C:$C,'By therapy area'!I$4) -> 1 | ... P10: =COUNTIFS('Local HTA submissions'!$E:$E,'By therapy area'!$A10,'Local HTA submissions'!$C:$C,'By therapy area'!P$4) -> 0 | Q10: =SUM(B10:P10) -> 18 | R10: =Q10/$Q$38 -> 0.032786885
A11: ='Local HTA submissions'!AD8 -> Other/None | B11: =COUNTIFS('Local HTA submissions'!$E:$E,'By therapy area'!$A11,'Local HTA submissions'!$C:$C,'By therapy area'!B$4) -> 1 | C11: =COUNTIFS('Local HTA submissions'!$E:$E,'By therapy area'!$A11,'Local HTA submissions'!$C:$C,'By therapy area'!C$4) -> 0 | D11: =COUNTIFS('Local HTA submissions'!$E:$E,'By therapy area'!$A11,'Local HTA submissions'!$C:$C,'By therapy area'!D$4) -> 0 | E11: =COUNTIFS('Local HTA submissions'!$E:$E,'By therapy area'!$A11,'Local HTA submissions'!$C:$C,'By therapy area'!E$4) -> 0 | F11: =COUNTIFS('Local HTA submissions'!$E:$E,'By therapy area'!$A11,'Local HTA submissions'!$C:$C,'By therapy area'!F$4) -> 3 | G11: =COUNTIFS('Local HTA submissions'!$E:$E,'By therapy area'!$A11,'Local HTA submissions'!$C:$C,'By therapy area'!G$4) -> 1 | H11: =COUNTIFS('Local HTA submissions'!$E:$E,'By therapy area'!$A11,'Local HTA submissions'!$C:$C,'By therapy area'!H$4) -> 0 | I11: =COUNTIFS('Local HTA submissions'!$E:$E,'By therapy area'!$A11,'Local HTA submissions'!$C:$C,'By therapy area'!I$4) -> 13 | ... P11: =COUNTIFS('Local HTA submissions'!$E:$E,'By therapy area'!$A11,'Local HTA submissions'!$C:$C,'By therapy area'!P$4) -> 0 | Q11: =SUM(B11:P11) -> 26 | R11: =Q11/$Q$38 -> 0.047358834
A12: ='Local HTA submissions'!AD9 -> Metabolic/Endocrine Disorders | B12: =COUNTIFS('Local HTA submissions'!$E:$E,'By therapy area'!$A12,'Local HTA submissions'!$C:$C,'By therapy area'!B$4) -> 7 | C12: =COUNTIFS('Local HTA submissions'!$E:$E,'By therapy area'!$A12,'Local HTA submissions'!$C:$C,'By therapy area'!C$4) -> 5 | D12: =COUNTIFS('Local HTA submissions'!$E:$E,'By therapy area'!$A12,'Local HTA submissions'!$C:$C,'By therapy area'!D$4) -> 2 | E12: =COUNTIFS('Local HTA submissions'!$E:$E,'By therapy area'!$A12,'Local HTA submissions'!$C:$C,'By therapy area'!E$4) -> 2 | F12: =COUNTIFS('Local HTA submissions'!$E:$E,'By therapy area'!$A12,'Local HTA submissions'!$C:$C,'By therapy area'!F$4) -> 12 | G12: =COUNTIFS('Local HTA submissions'!$E:$E,'By therapy area'!$A12,'Local HTA submissions'!$C:$C,'By therapy area'!G$4) -> 9 | H12: =COUNTIFS('Local HTA submissions'!$E:$E,'By therapy area'!$A12,'Local HTA submissions'!$C:$C,'By therapy area'!H$4) -> 4 | I12: =COUNTIFS('Local HTA submissions'!$E:$E,'By therapy area'!$A12,'Local HTA submissions'!$C:$C,'By therapy area'!I$4) -> 2 | ... P12: =COUNTIFS('Local HTA submissions'!$E:$E,'By therapy area'!$A12,'Local HTA submissions'!$C:$C,'By therapy area'!P$4) -> 0 | Q12: =SUM(B12:P12) -> 55 | R12: =Q12/$Q$38 -> 0.10018215
A13: ='Local HTA submissions'!AD10 -> Dermatology | B13: =COUNTIFS('Local HTA submissions'!$E:$E,'By therapy area'!$A13,'Local HTA submissions'!$C:$C,'By therapy area'!B$4) -> 2 | C13: =COUNTIFS('Local HTA submissions'!$E:$E,'By therapy area'!$A13,'Local HTA submissions'!$C:$C,'By therapy area'!C$4) -> 1 | D13: =COUNTIFS('Local HTA submissions'!$E:$E,'By therapy area'!$A13,'Local HTA submissions'!$C:$C,'By therapy area'!D$4) -> 0 | E13: =COUNTIFS('Local HTA submissions'!$E:$E,'By therapy area'!$A13,'Local HTA submissions'!$C:$C,'By therapy area'!E$4) -> 2 | F13: =COUNTIFS('Local HTA submissions'!$E:$E,'By therapy area'!$A13,'Local HTA submissions'!$C:$C,'By therapy area'!F$4) -> 4 | G13: =COUNTIFS('Local HTA submissions'!$E:$E,'By therapy area'!$A13,'Local HTA submissions'!$C:$C,'By therapy area'!G$4) -> 5 | H13: =COUNTIFS('Local HTA submissions'!$E:$E,'By therapy area'!$A13,'Local HTA submissions'!$C:$C,'By therapy area'!H$4) -> 0 | I13: =COUNTIFS('Local HTA submissions'!$E:$E,'By therapy area'!$A13,'Local HTA submissions'!$C:$C,'By therapy area'!I$4) -> 0 | ... P13: =COUNTIFS('Local HTA submissions'!$E:$E,'By therapy area'!$A13,'Local HTA submissions'!$C:$C,'By therapy area'!P$4) -> 0 | Q13: =SUM(B13:P13) -> 22 | R13: =Q13/$Q$38 -> 0.04007286
A14: ='Local HTA submissions'!AD11 -> Infectious diseases | B14: =COUNTIFS('Local HTA submissions'!$E:$E,'By therapy area'!$A14,'Local HTA submissions'!$C:$C,'By therapy area'!B$4) -> 1 | C14: =COUNTIFS('Local HTA submissions'!$E:$E,'By therapy area'!$A14,'Local HTA submissions'!$C:$C,'By therapy area'!C$4) -> 3 | D14: =COUNTIFS('Local HTA submissions'!$E:$E,'By therapy area'!$A14,'Local HTA submissions'!$C:$C,'By therapy area'!D$4) -> 1 | E14: =COUNTIFS('Local HTA submissions'!$E:$E,'By therapy area'!$A14,'Local HTA submissions'!$C:$C,'By therapy area'!E$4) -> 3 | F14: =COUNTIFS('Local HTA submissions'!$E:$E,'By therapy area'!$A14,'Local HTA submissions'!$C:$C,'By therapy area'!F$4) -> 6 | G14: =COUNTIFS('Local HTA submissions'!$E:$E,'By therapy area'!$A14,'Local HTA submissions'!$C:$C,'By therapy area'!G$4) -> 1 | H14: =COUNTIFS('Local HTA submissions'!$E:$E,'By therapy area'!$A14,'Local HTA submissions'!$C:$C,'By therapy area'!H$4) -> 6 | I14: =COUNTIFS('Local HTA submissions'!$E:$E,'By therapy area'!$A14,'Local HTA submissions'!$C:$C,'By therapy area'!I$4) -> 0 | ... P14: =COUNTIFS('Local HTA submissions'!$E:$E,'By therapy area'!$A14,'Local HTA submissions'!$C:$C,'By therapy area'!P$4) -> 0 | Q14: =SUM(B14:P14) -> 30 | R14: =Q14/$Q$38 -> 0.054644809
A15: ='Local HTA submissions'!AD12 -> Ophthalmology | B15: =COUNTIFS('Local HTA submissions'!$E:$E,'By therapy area'!$A15,'Local HTA submissions'!$C:$C,'By therapy area'!B$4) -> 5 | C15: =COUNTIFS('Local HTA submissions'!$E:$E,'By therapy area'!$A15,'Local HTA submissions'!$C:$C,'By therapy area'!C$4) -> 1 | D15: =COUNTIFS('Local HTA submissions'!$E:$E,'By therapy area'!$A15,'Local HTA submissions'!$C:$C,'By therapy area'!D$4) -> 0 | E15: =COUNTIFS('Local HTA submissions'!$E:$E,'By therapy area'!$A15,'Local HTA submissions'!$C:$C,'By therapy area'!E$4) -> 3 | F15: =COUNTIFS('Local HTA submissions'!$E:$E,'By therapy area'!$A15,'Local HTA submissions'!$C:$C,'By therapy area'!F$4) -> 2 | G15: =COUNTIFS('Local HTA submissions'!$E:$E,'By therapy area'!$A15,'Local HTA submissions'!$C:$C,'By therapy area'!G$4) -> 1 | H15: =COUNTIFS('Local HTA submissions'!$E:$E,'By therapy area'!$A15,'Local HTA submissions'!$C:$C,'By therapy area'!H$4) -> 0 | I15: =COUNTIFS('Local HTA submissions'!$E:$E,'By therapy area'!$A15,'Local HTA submissions'!$C:$C,'By therapy area'!I$4) -> 1 | ... P15: =COUNTIFS('Local HTA submissions'!$E:$E,'By therapy area'!$A15,'Local HTA submissions'!$C:$C,'By therapy area'!P$4) -> 0 | Q15: =SUM(B15:P15) -> 16 | R15: =Q15/$Q$38 -> 0.029143898
A16: ='Local HTA submissions'!AD13 -> Gynacology | B16: =COUNTIFS('Local HTA submissions'!$E:$E,'By therapy area'!$A16,'Local HTA submissions'!$C:$C,'By therapy area'!B$4) -> 0 | C16: =COUNTIFS('Local HTA submissions'!$E:$E,'By therapy area'!$A16,'Local HTA submissions'!$C:$C,'By therapy area'!C$4) -> 2 | D16: =COUNTIFS('Local HTA submissions'!$E:$E,'By therapy area'!$A16,'Local HTA submissions'!$C:$C,'By therapy area'!D$4) -> 1 | E16: =COUNTIFS('Local HTA submissions'!$E:$E,'By therapy area'!$A16,'Local HTA submissions'!$C:$C,'By therapy area'!E$4) -> 0 | F16: =COUNTIFS('Local HTA submissions'!$E:$E,'By therapy area'!$A16,'Local HTA submissions'!$C:$C,'By therapy area'!F$4) -> 0 | G16: =COUNTIFS('Local HTA submissions'!$E:$E,'By therapy area'!$A16,'Local HTA submissions'!$C:$C,'By therapy area'!G$4) -> 0 | H16: =COUNTIFS('Local HTA submissions'!$E:$E,'By therapy area'!$A16,'Local HTA submissions'!$C:$C,'By therapy area'!H$4) -> 0 | I16: =COUNTIFS('Local HTA submissions'!$E:$E,'By therapy area'!$A16,'Local HTA submissions'!$C:$C,'By therapy area'!I$4) -> 4 | ... P16: =COUNTIFS('Local HTA submissions'!$E:$E,'By therapy area'!$A16,'Local HTA submissions'!$C:$C,'By therapy area'!P$4) -> 0 | Q16: =SUM(B16:P16) -> 15 | R16: =Q16/$Q$38 -> 0.027322404
... A37: ='Local HTA submissions'!AD34 -> 0 | B37: =COUNTIFS('Local HTA submissions'!$E:$E,'By therapy area'!$A37,'Local HTA submissions'!$C:$C,'By therapy area'!B$4) -> 0 | C37: =COUNTIFS('Local HTA submissions'!$E:$E,'By therapy area'!$A37,'Local HTA submissions'!$C:$C,'By therapy area'!C$4) -> 0 | D37: =COUNTIFS('Local HTA submissions'!$E:$E,'By therapy area'!$A37,'Local HTA submissions'!$C:$C,'By therapy area'!D$4) -> 0 | E37: =COUNTIFS('Local HTA submissions'!$E:$E,'By therapy area'!$A37,'Local HTA submissions'!$C:$C,'By therapy area'!E$4) -> 0 | F37: =COUNTIFS('Local HTA submissions'!$E:$E,'By therapy area'!$A37,'Local HTA submissions'!$C:$C,'By therapy area'!F$4) -> 0 | G37: =COUNTIFS('Local HTA submissions'!$E:$E,'By therapy area'!$A37,'Local HTA submissions'!$C:$C,'By therapy area'!G$4) -> 0 | H37: =COUNTIFS('Local HTA submissions'!$E:$E,'By therapy area'!$A37,'Local HTA submissions'!$C:$C,'By therapy area'!H$4) -> 0 | I37: =COUNTIFS('Local HTA submissions'!$E:$E,'By therapy area'!$A37,'Local HTA submissions'!$C:$C,'By therapy area'!I$4) -> 0 | ... P37: =COUNTIFS('Local HTA submissions'!$E:$E,'By therapy area'!$A37,'Local HTA submissions'!$C:$C,'By therapy area'!P$4) -> 0 | Q37: =SUM(B37:P37) -> 0 | R37: =Q37/$Q$38 -> 0
A38: Total | B38: =SUM(B5:B37) -> 50 | C38: =SUM(C5:C37) -> 27 | D38: =SUM(D5:D37) -> 6 | E38: =SUM(E5:E37) -> 22 | F38: =SUM(F5:F37) -> 85 | G38: =SUM(G5:G37) -> 40 | H38: =SUM(H5:H37) -> 46 | I38: =SUM(I5:I37) -> 69 | ... Q38: =SUM(Q5:Q37) -> 549 | R38: =Q38/$Q$38 -> 1
A72: HTA submissions by therapy area & Year
A73: Therapy area | B73: 2012 | C73: 2013 | D73: 2014 | E73: 2015 | F73: 2016 | G73: 2017 | H73: 2018 | I73: 2019 | J73: 2020 | K73: 2021 | L73: Total | M73: Percentage
A74: ='Local HTA submissions'!AD2 -> Oncology | B74: =COUNTIFS('Local HTA submissions'!$E:$E,'By therapy area'!$A5,'Local HTA submissions'!$H:$H,'By therapy area'!B$73) -> 0 | C74: =COUNTIFS('Local HTA submissions'!$E:$E,'By therapy area'!$A5,'Local HTA submissions'!$H:$H,'By therapy area'!C$73) -> 3 | D74: =COUNTIFS('Local HTA submissions'!$E:$E,'By therapy area'!$A5,'Local HTA submissions'!$H:$H,'By therapy area'!D$73) -> 3 | E74: =COUNTIFS('Local HTA submissions'!$E:$E,'By therapy area'!$A5,'Local HTA submissions'!$H:$H,'By therapy area'!E$73) -> 8 | F74: =COUNTIFS('Local HTA submissions'!$E:$E,'By therapy area'!$A5,'Local HTA submissions'!$H:$H,'By therapy area'!F$73) -> 6 | G74: =COUNTIFS('Local HTA submissions'!$E:$E,'By therapy area'!$A5,'Local HTA submissions'!$H:$H,'By therapy area'!G$73) -> 5 | H74: =COUNTIFS('Local HTA submissions'!$E:$E,'By therapy area'!$A5,'Local HTA submissions'!$H:$H,'By therapy area'!H$73) -> 17 | I74: =COUNTIFS('Local HTA submissions'!$E:$E,'By therapy area'!$A5,'Local HTA submissions'!$H:$H,'By therapy area'!I$73) -> 22 | ... K74: =COUNTIFS('Local HTA submissions'!$E:$E,'By therapy area'!$A5,'Local HTA submissions'!$H:$H,'By therapy area'!K$73) -> 28 | L74: =SUM(B74:K74) -> 118 | M74: =L74/$L$107 -> 0.37579618
A75: ='Local HTA submissions'!AD3 -> Blood and immune system | B75: =COUNTIFS('Local HTA submissions'!$E:$E,'By therapy area'!$A6,'Local HTA submissions'!$H:$H,'By therapy area'!B$73) -> 0 | C75: =COUNTIFS('Local HTA submissions'!$E:$E,'By therapy area'!$A6,'Local HTA submissions'!$H:$H,'By therapy area'!C$73) -> 0 | D75: =COUNTIFS('Local HTA submissions'!$E:$E,'By therapy area'!$A6,'Local HTA submissions'!$H:$H,'By therapy area'!D$73) -> 0 | E75: =COUNTIFS('Local HTA submissions'!$E:$E,'By therapy area'!$A6,'Local HTA submissions'!$H:$H,'By therapy area'!E$73) -> 0 | F75: =COUNTIFS('Local HTA submissions'!$E:$E,'By therapy area'!$A6,'Local HTA submissions'!$H:$H,'By therapy area'!F$73) -> 0 | G75: =COUNTIFS('Local HTA submissions'!$E:$E,'By therapy area'!$A6,'Local HTA submissions'!$H:$H,'By therapy area'!G$73) -> 1 | H75: =COUNTIFS('Local HTA submissions'!$E:$E,'By therapy area'!$A6,'Local HTA submissions'!$H:$H,'By therapy area'!H$73) -> 3 | I75: =COUNTIFS('Local HTA submissions'!$E:$E,'By therapy area'!$A6,'Local HTA submissions'!$H:$H,'By therapy area'!I$73) -> 0 | ... K75: =COUNTIFS('Local HTA submissions'!$E:$E,'By therapy area'!$A6,'Local HTA submissions'!$H:$H,'By therapy area'!K$73) -> 6 | L75: =SUM(B75:K75) -> 12 | M75: =L75/$L$107 -> 0.038216561
A76: ='Local HTA submissions'!AD4 -> Gastroenterology | B76: =COUNTIFS('Local HTA submissions'!$E:$E,'By therapy area'!$A7,'Local HTA submissions'!$H:$H,'By therapy area'!B$73) -> 0 | C76: =COUNTIFS('Local HTA submissions'!$E:$E,'By therapy area'!$A7,'Local HTA submissions'!$H:$H,'By therapy area'!C$73) -> 0 | D76: =COUNTIFS('Local HTA submissions'!$E:$E,'By therapy area'!$A7,'Local HTA submissions'!$H:$H,'By therapy area'!D$73) -> 0 | E76: =COUNTIFS('Local HTA submissions'!$E:$E,'By therapy area'!$A7,'Local HTA submissions'!$H:$H,'By therapy area'!E$73) -> 0 | F76: =COUNTIFS('Local HTA submissions'!$E:$E,'By therapy area'!$A7,'Local HTA submissions'!$H:$H,'By therapy area'!F$73) -> 0 | G76: =COUNTIFS('Local HTA submissions'!$E:$E,'By therapy area'!$A7,'Local HTA submissions'!$H:$H,'By therapy area'!G$73) -> 0 | H76: =COUNTIFS('Local HTA submissions'!$E:$E,'By therapy area'!$A7,'Local HTA submissions'!$H:$H,'By therapy area'!H$73) -> 0 | I76: =COUNTIFS('Local HTA submissions'!$E:$E,'By therapy area'!$A7,'Local HTA submissions'!$H:$H,'By therapy area'!I$73) -> 0 | ... K76: =COUNTIFS('Local HTA submissions'!$E:$E,'By therapy area'!$A7,'Local HTA submissions'!$H:$H,'By therapy area'!K$73) -> 2 | L76: =SUM(B76:K76) -> 2 | M76: =L76/$L$107 -> 0.0063694268
A77: ='Local HTA submissions'!AD5 -> Cardiovascular diseases | B77: =COUNTIFS('Local HTA submissions'!$E:$E,'By therapy area'!$A8,'Local HTA submissions'!$H:$H,'By therapy area'!B$73) -> 2 | C77: =COUNTIFS('Local HTA submissions'!$E:$E,'By therapy area'!$A8,'Local HTA submissions'!$H:$H,'By therapy area'!C$73) -> 3 | D77: =COUNTIFS('Local HTA submissions'!$E:$E,'By therapy area'!$A8,'Local HTA submissions'!$H:$H,'By therapy area'!D$73) -> 0 | E77: =COUNTIFS('Local HTA submissions'!$E:$E,'By therapy area'!$A8,'Local HTA submissions'!$H:$H,'By therapy area'!E$73) -> 1 | F77: =COUNTIFS('Local HTA submissions'!$E:$E,'By therapy area'!$A8,'Local HTA submissions'!$H:$H,'By therapy area'!F$73) -> 0 | G77: =COUNTIFS('Local HTA submissions'!$E:$E,'By therapy area'!$A8,'Local HTA submissions'!$H:$H,'By therapy area'!G$73) -> 0 | H77: =COUNTIFS('Local HTA submissions'!$E:$E,'By therapy area'!$A8,'Local HTA submissions'!$H:$H,'By therapy area'!H$73) -> 0 | I77: =COUNTIFS('Local HTA submissions'!$E:$E,'By therapy area'!$A8,'Local HTA submissions'!$H:$H,'By therapy area'!I$73) -> 4 | ... K77: =COUNTIFS('Local HTA submissions'!$E:$E,'By therapy area'!$A8,'Local HTA submissions'!$H:$H,'By therapy area'!K$73) -> 1 | L77: =SUM(B77:K77) -> 15 | M77: =L77/$L$107 -> 0.047770701
A78: ='Local HTA submissions'!AD6 -> Respiratory | B78: =COUNTIFS('Local HTA submissions'!$E:$E,'By therapy area'!$A9,'Local HTA submissions'!$H:$H,'By therapy area'!B$73) -> 0 | C78: =COUNTIFS('Local HTA submissions'!$E:$E,'By therapy area'!$A9,'Local HTA submissions'!$H:$H,'By therapy area'!C$73) -> 0 | D78: =COUNTIFS('Local HTA submissions'!$E:$E,'By therapy area'!$A9,'Local HTA submissions'!$H:$H,'By therapy area'!D$73) -> 0 | E78: =COUNTIFS('Local HTA submissions'!$E:$E,'By therapy area'!$A9,'Local HTA submissions'!$H:$H,'By therapy area'!E$73) -> 0 | F78: =COUNTIFS('Local HTA submissions'!$E:$E,'By therapy area'!$A9,'Local HTA submissions'!$H:$H,'By therapy area'!F$73) -> 0 | G78: =COUNTIFS('Local HTA submissions'!$E:$E,'By therapy area'!$A9,'Local HTA submissions'!$H:$H,'By therapy area'!G$73) -> 1 | H78: =COUNTIFS('Local HTA submissions'!$E:$E,'By therapy area'!$A9,'Local HTA submissions'!$H:$H,'By therapy area'!H$73) -> 1 | I78: =COUNTIFS('Local HTA submissions'!$E:$E,'By therapy area'!$A9,'Local HTA submissions'!$H:$H,'By therapy area'!I$73) -> 2 | ... K78: =COUNTIFS('Local HTA submissions'!$E:$E,'By therapy area'!$A9,'Local HTA submissions'!$H:$H,'By therapy area'!K$73) -> 1 | L78: =SUM(B78:K78) -> 10 | M78: =L78/$L$107 -> 0.031847134
A79: ='Local HTA submissions'!AD7 -> Muscoloskeletal | B79: =COUNTIFS('Local HTA submissions'!$E:$E,'By therapy area'!$A10,'Local HTA submissions'!$H:$H,'By therapy area'!B$73) -> 0 | C79: =COUNTIFS('Local HTA submissions'!$E:$E,'By therapy area'!$A10,'Local HTA submissions'!$H:$H,'By therapy area'!C$73) -> 0 | D79: =COUNTIFS('Local HTA submissions'!$E:$E,'By therapy area'!$A10,'Local HTA submissions'!$H:$H,'By therapy area'!D$73) -> 0 | E79: =COUNTIFS('Local HTA submissions'!$E:$E,'By therapy area'!$A10,'Local HTA submissions'!$H:$H,'By therapy area'!E$73) -> 1 | F79: =COUNTIFS('Local HTA submissions'!$E:$E,'By therapy area'!$A10,'Local HTA submissions'!$H:$H,'By therapy area'!F$73) -> 1 | G79: =COUNTIFS('Local HTA submissions'!$E:$E,'By therapy area'!$A10,'Local HTA submissions'!$H:$H,'By therapy area'!G$73) -> 3 | H79: =COUNTIFS('Local HTA submissions'!$E:$E,'By therapy area'!$A10,'Local HTA submissions'!$H:$H,'By therapy area'!H$73) -> 1 | I79: =COUNTIFS('Local HTA submissions'!$E:$E,'By therapy area'!$A10,'Local HTA submissions'!$H:$H,'By therapy area'!I$73) -> 3 | ... K79: =COUNTIFS('Local HTA submissions'!$E:$E,'By therapy area'!$A10,'Local HTA submissions'!$H:$H,'By therapy area'!K$73) -> 2 | L79: =SUM(B79:K79) -> 15 | M79: =L79/$L$107 -> 0.047770701
A80: ='Local HTA submissions'!AD8 -> Other/None | B80: =COUNTIFS('Local HTA submissions'!$E:$E,'By therapy area'!$A11,'Local HTA submissions'!$H:$H,'By therapy area'!B$73) -> 0 | C80: =COUNTIFS('Local HTA submissions'!$E:$E,'By therapy area'!$A11,'Local HTA submissions'!$H:$H,'By therapy area'!C$73) -> 0 | D80: =COUNTIFS('Local HTA submissions'!$E:$E,'By therapy area'!$A11,'Local HTA submissions'!$H:$H,'By therapy area'!D$73) -> 0 | E80: =COUNTIFS('Local HTA submissions'!$E:$E,'By therapy area'!$A11,'Local HTA submissions'!$H:$H,'By therapy area'!E$73) -> 0 | F80: =COUNTIFS('Local HTA submissions'!$E:$E,'By therapy area'!$A11,'Local HTA submissions'!$H:$H,'By therapy area'!F$73) -> 0 | G80: =COUNTIFS('Local HTA submissions'!$E:$E,'By therapy area'!$A11,'Local HTA submissions'!$H:$H,'By therapy area'!G$73) -> 1 | H80: =COUNTIFS('Local HTA submissions'!$E:$E,'By therapy area'!$A11,'Local HTA submissions'!$H:$H,'By therapy area'!H$73) -> 1 | I80: =COUNTIFS('Local HTA submissions'!$E:$E,'By therapy area'!$A11,'Local HTA submissions'!$H:$H,'By therapy area'!I$73) -> 0 | ... K80: =COUNTIFS('Local HTA submissions'!$E:$E,'By therapy area'!$A11,'Local HTA submissions'!$H:$H,'By therapy area'!K$73) -> 0 | L80: =SUM(B80:K80) -> 5 | M80: =L80/$L$107 -> 0.015923567
A81: ='Local HTA submissions'!AD9 -> Metabolic/Endocrine Disorders | B81: =COUNTIFS('Local HTA submissions'!$E:$E,'By therapy area'!$A12,'Local HTA submissions'!$H:$H,'By therapy area'!B$73) -> 3 | C81: =COUNTIFS('Local HTA submissions'!$E:$E,'By therapy area'!$A12,'Local HTA submissions'!$H:$H,'By therapy area'!C$73) -> 1 | D81: =COUNTIFS('Local HTA submissions'!$E:$E,'By therapy area'!$A12,'Local HTA submissions'!$H:$H,'By therapy area'!D$73) -> 0 | E81: =COUNTIFS('Local HTA submissions'!$E:$E,'By therapy area'!$A12,'Local HTA submissions'!$H:$H,'By therapy area'!E$73) -> 8 | F81: =COUNTIFS('Local HTA submissions'!$E:$E,'By therapy area'!$A12,'Local HTA submissions'!$H:$H,'By therapy area'!F$73) -> 9 | G81: =COUNTIFS('Local HTA submissions'!$E:$E,'By therapy area'!$A12,'Local HTA submissions'!$H:$H,'By therapy area'!G$73) -> 6 | H81: =COUNTIFS('Local HTA submissions'!$E:$E,'By therapy area'!$A12,'Local HTA submissions'!$H:$H,'By therapy area'!H$73) -> 4 | I81: =COUNTIFS('Local HTA submissions'!$E:$E,'By therapy area'!$A12,'Local HTA submissions'!$H:$H,'By therapy area'!I$73) -> 7 | ... K81: =COUNTIFS('Local HTA submissions'!$E:$E,'By therapy area'!$A12,'Local HTA submissions'!$H:$H,'By therapy area'!K$73) -> 1 | L81: =SUM(B81:K81) -> 42 | M81: =L81/$L$107 -> 0.13375796
A82: ='Local HTA submissions'!AD10 -> Dermatology | B82: =COUNTIFS('Local HTA submissions'!$E:$E,'By therapy area'!$A13,'Local HTA submissions'!$H:$H,'By therapy area'!B$73) -> 0 | C82: =COUNTIFS('Local HTA submissions'!$E:$E,'By therapy area'!$A13,'Local HTA submissions'!$H:$H,'By therapy area'!C$73) -> 0 | D82: =COUNTIFS('Local HTA submissions'!$E:$E,'By therapy area'!$A13,'Local HTA submissions'!$H:$H,'By therapy area'!D$73) -> 0 | E82: =COUNTIFS('Local HTA submissions'!$E:$E,'By therapy area'!$A13,'Local HTA submissions'!$H:$H,'By therapy area'!E$73) -> 3 | F82: =COUNTIFS('Local HTA submissions'!$E:$E,'By therapy area'!$A13,'Local HTA submissions'!$H:$H,'By therapy area'!F$73) -> 2 | G82: =COUNTIFS('Local HTA submissions'!$E:$E,'By therapy area'!$A13,'Local HTA submissions'!$H:$H,'By therapy area'!G$73) -> 2 | H82: =COUNTIFS('Local HTA submissions'!$E:$E,'By therapy area'!$A13,'Local HTA submissions'!$H:$H,'By therapy area'!H$73) -> 3 | I82: =COUNTIFS('Local HTA submissions'!$E:$E,'By therapy area'!$A13,'Local HTA submissions'!$H:$H,'By therapy area'!I$73) -> 2 | ... K82: =COUNTIFS('Local HTA submissions'!$E:$E,'By therapy area'!$A13,'Local HTA submissions'!$H:$H,'By therapy area'!K$73) -> 0 | L82: =SUM(B82:K82) -> 14 | M82: =L82/$L$107 -> 0.044585987
A83: ='Local HTA submissions'!AD11 -> Infectious diseases | B83: =COUNTIFS('Local HTA submissions'!$E:$E,'By therapy area'!$A14,'Local HTA submissions'!$H:$H,'By therapy area'!B$73) -> 1 | C83: =COUNTIFS('Local HTA submissions'!$E:$E,'By therapy area'!$A14,'Local HTA submissions'!$H:$H,'By therapy area'!C$73) -> 0 | D83: =COUNTIFS('Local HTA submissions'!$E:$E,'By therapy area'!$A14,'Local HTA submissions'!$H:$H,'By therapy area'!D$73) -> 0 | E83: =COUNTIFS('Local HTA submissions'!$E:$E,'By therapy area'!$A14,'Local HTA submissions'!$H:$H,'By therapy area'!E$73) -> 4 | F83: =COUNTIFS('Local HTA submissions'!$E:$E,'By therapy area'!$A14,'Local HTA submissions'!$H:$H,'By therapy area'!F$73) -> 0 | G83: =COUNTIFS('Local HTA submissions'!$E:$E,'By therapy area'!$A14,'Local HTA submissions'!$H:$H,'By therapy area'!G$73) -> 3 | H83: =COUNTIFS('Local HTA submissions'!$E:$E,'By therapy area'!$A14,'Local HTA submissions'!$H:$H,'By therapy area'!H$73) -> 2 | I83: =COUNTIFS('Local HTA submissions'!$E:$E,'By therapy area'!$A14,'Local HTA submissions'!$H:$H,'By therapy area'!I$73) -> 3 | ... K83: =COUNTIFS('Local HTA submissions'!$E:$E,'By therapy area'!$A14,'Local HTA submissions'!$H:$H,'By therapy area'!K$73) -> 4 | L83: =SUM(B83:K83) -> 21 | M83: =L83/$L$107 -> 0.066878981
A84: ='Local HTA submissions'!AD12 -> Ophthalmology | B84: =COUNTIFS('Local HTA submissions'!$E:$E,'By therapy area'!$A15,'Local HTA submissions'!$H:$H,'By therapy area'!B$73) -> 0 | C84: =COUNTIFS('Local HTA submissions'!$E:$E,'By therapy area'!$A15,'Local HTA submissions'!$H:$H,'By therapy area'!C$73) -> 3 | D84: =COUNTIFS('Local HTA submissions'!$E:$E,'By therapy area'!$A15,'Local HTA submissions'!$H:$H,'By therapy area'!D$73) -> 2 | E84: =COUNTIFS('Local HTA submissions'!$E:$E,'By therapy area'!$A15,'Local HTA submissions'!$H:$H,'By therapy area'!E$73) -> 2 | F84: =COUNTIFS('Local HTA submissions'!$E:$E,'By therapy area'!$A15,'Local HTA submissions'!$H:$H,'By therapy area'!F$73) -> 3 | G84: =COUNTIFS('Local HTA submissions'!$E:$E,'By therapy area'!$A15,'Local HTA submissions'!$H:$H,'By therapy area'!G$73) -> 0 | H84: =COUNTIFS('Local HTA submissions'!$E:$E,'By therapy area'!$A15,'Local HTA submissions'!$H:$H,'By therapy area'!H$73) -> 0 | I84: =COUNTIFS('Local HTA submissions'!$E:$E,'By therapy area'!$A15,'Local HTA submissions'!$H:$H,'By therapy area'!I$73) -> 0 | ... K84: =COUNTIFS('Local HTA submissions'!$E:$E,'By therapy area'!$A15,'Local HTA submissions'!$H:$H,'By therapy area'!K$73) -> 0 | L84: =SUM(B84:K84) -> 14 | M84: =L84/$L$107 -> 0.044585987
A85: ='Local HTA submissions'!AD13 -> Gynacology | B85: =COUNTIFS('Local HTA submissions'!$E:$E,'By therapy area'!$A16,'Local HTA submissions'!$H:$H,'By therapy area'!B$73) -> 0 | C85: =COUNTIFS('Local HTA submissions'!$E:$E,'By therapy area'!$A16,'Local HTA submissions'!$H:$H,'By therapy area'!C$73) -> 0 | D85: =COUNTIFS('Local HTA submissions'!$E:$E,'By therapy area'!$A16,'Local HTA submissions'!$H:$H,'By therapy area'!D$73) -> 0 | E85: =COUNTIFS('Local HTA submissions'!$E:$E,'By therapy area'!$A16,'Local HTA submissions'!$H:$H,'By therapy area'!E$73) -> 1 | F85: =COUNTIFS('Local HTA submissions'!$E:$E,'By therapy area'!$A16,'Local HTA submissions'!$H:$H,'By therapy area'!F$73) -> 0 | G85: =COUNTIFS('Local HTA submissions'!$E:$E,'By therapy area'!$A16,'Local HTA submissions'!$H:$H,'By therapy area'!G$73) -> 1 | H85: =COUNTIFS('Local HTA submissions'!$E:$E,'By therapy area'!$A16,'Local HTA submissions'!$H:$H,'By therapy area'!H$73) -> 1 | I85: =COUNTIFS('Local HTA submissions'!$E:$E,'By therapy area'!$A16,'Local HTA submissions'!$H:$H,'By therapy area'!I$73) -> 0 | ... K85: =COUNTIFS('Local HTA submissions'!$E:$E,'By therapy area'!$A16,'Local HTA submissions'!$H:$H,'By therapy area'!K$73) -> 0 | L85: =SUM(B85:K85) -> 3 | M85: =L85/$L$107 -> 0.0095541401
... A106: ='Local HTA submissions'!AD34 -> 0 | B106: =COUNTIFS('Local HTA submissions'!$E:$E,'By therapy area'!$A37,'Local HTA submissions'!$H:$H,'By therapy area'!B$73) -> 0 | C106: =COUNTIFS('Local HTA submissions'!$E:$E,'By therapy area'!$A37,'Local HTA submissions'!$H:$H,'By therapy area'!C$73) -> 0 | D106: =COUNTIFS('Local HTA submissions'!$E:$E,'By therapy area'!$A37,'Local HTA submissions'!$H:$H,'By therapy area'!D$73) -> 0 | E106: =COUNTIFS('Local HTA submissions'!$E:$E,'By therapy area'!$A37,'Local HTA submissions'!$H:$H,'By therapy area'!E$73) -> 0 | F106: =COUNTIFS('Local HTA submissions'!$E:$E,'By therapy area'!$A37,'Local HTA submissions'!$H:$H,'By therapy area'!F$73) -> 0 | G106: =COUNTIFS('Local HTA submissions'!$E:$E,'By therapy area'!$A37,'Local HTA submissions'!$H:$H,'By therapy area'!G$73) -> 0 | H106: =COUNTIFS('Local HTA submissions'!$E:$E,'By therapy area'!$A37,'Local HTA submissions'!$H:$H,'By therapy area'!H$73) -> 0 | I106: =COUNTIFS('Local HTA submissions'!$E:$E,'By therapy area'!$A37,'Local HTA submissions'!$H:$H,'By therapy area'!I$73) -> 0 | ... K106: =COUNTIFS('Local HTA submissions'!$E:$E,'By therapy area'!$A37,'Local HTA submissions'!$H:$H,'By therapy area'!K$73) -> 0 | L106: =SUM(B106:K106) -> 0 | M106: =L106/$L$107 -> 0
A107: Total | B107: =SUBTOTAL(109,Table11[2012]) -> 6 | C107: =SUBTOTAL(109,Table11[2013]) -> 10 | D107: =SUBTOTAL(109,Table11[2014]) -> 5 | E107: =SUBTOTAL(109,Table11[2015]) -> 29 | F107: =SUBTOTAL(109,Table11[2016]) -> 24 | G107: =SUBTOTAL(109,Table11[2017]) -> 25 | H107: =SUBTOTAL(109,Table11[2018]) -> 38 | I107: =SUBTOTAL(109,Table11[2019]) -> 49 | J107: =SUBTOTAL(109,Table11[2020]) -> 73 | K107: =SUBTOTAL(109,Table11[2021]) -> 55 | L107: =SUM(B107:K107) -> 314 | M107: =L107/549 -> 0.571949
A142: HTA scientific advice
A143: HTA scientific advice by therapy area & Year
A144: Therapy area | B144: 2016 | C144: 2017 | D144: 2018 | E144: 2019 | F144: 2020 | G144: 2021 | H144: Total | I144: Percentage
A145: ='HTA scientific advice'!L2 -> Dermatology | B145: =COUNTIFS(Table1[Therapy area],'By therapy area'!$A145,Table1[Year],'By therapy area'!B$144) -> 0 | C145: =COUNTIFS(Table1[Therapy area],'By therapy area'!$A145,Table1[Year],'By therapy area'!C$144) -> 0 | D145: =COUNTIFS(Table1[Therapy area],'By therapy area'!$A145,Table1[Year],'By therapy area'!D$144) -> 4 | E145: =COUNTIFS(Table1[Therapy area],'By therapy area'!$A145,Table1[Year],'By therapy area'!E$144) -> 0 | F145: =COUNTIFS(Table1[Therapy area],'By therapy area'!$A145,Table1[Year],'By therapy area'!F$144) -> 0 | G145: =COUNTIFS(Table1[Therapy area],'By therapy area'!$A145,Table1[Year],'By therapy area'!G$144) -> 0 | H145: =SUM(B145:G145) -> 4 | I145: =H145/$H$154 -> 0.28571429
A146: ='HTA scientific advice'!L3 -> Haemato-oncology | B146: =COUNTIFS(Table1[Therapy area],'By therapy area'!$A146,Table1[Year],'By therapy area'!B$144) -> 0 | C146: =COUNTIFS(Table1[Therapy area],'By therapy area'!$A146,Table1[Year],'By therapy area'!C$144) -> 0 | D146: =COUNTIFS(Table1[Therapy area],'By therapy area'!$A146,Table1[Year],'By therapy area'!D$144) -> 0 | E146: =COUNTIFS(Table1[Therapy area],'By therapy area'!$A146,Table1[Year],'By therapy area'!E$144) -> 0 | F146: =COUNTIFS(Table1[Therapy area],'By therapy area'!$A146,Table1[Year],'By therapy area'!F$144) -> 1 | G146: =COUNTIFS(Table1[Therapy area],'By therapy area'!$A146,Table1[Year],'By therapy area'!G$144) -> 3 | H146: =SUM(B146:G146) -> 4 | I146: =H146/$H$154 -> 0.28571429
A147: ='HTA scientific advice'!L4 -> Nephrology | B147: =COUNTIFS(Table1[Therapy area],'By therapy area'!$A147,Table1[Year],'By therapy area'!B$144) -> 0 | C147: =COUNTIFS(Table1[Therapy area],'By therapy area'!$A147,Table1[Year],'By therapy area'!C$144) -> 0 | D147: =COUNTIFS(Table1[Therapy area],'By therapy area'!$A147,Table1[Year],'By therapy area'!D$144) -> 0 | E147: =COUNTIFS(Table1[Therapy area],'By therapy area'!$A147,Table1[Year],'By therapy area'!E$144) -> 0 | F147: =COUNTIFS(Table1[Therapy area],'By therapy area'!$A147,Table1[Year],'By therapy area'!F$144) -> 0 | G147: =COUNTIFS(Table1[Therapy area],'By therapy area'!$A147,Table1[Year],'By therapy area'!G$144) -> 1 | H147: =SUM(B147:G147) -> 1 | I147: =H147/$H$154 -> 0.071428571
A148: ='HTA scientific advice'!L5 -> Oncology | B148: =COUNTIFS(Table1[Therapy area],'By therapy area'!$A148,Table1[Year],'By therapy area'!B$144) -> 0 | C148: =COUNTIFS(Table1[Therapy area],'By therapy area'!$A148,Table1[Year],'By therapy area'!C$144) -> 1 | D148: =COUNTIFS(Table1[Therapy area],'By therapy area'!$A148,Table1[Year],'By therapy area'!D$144) -> 0 | E148: =COUNTIFS(Table1[Therapy area],'By therapy area'!$A148,Table1[Year],'By therapy area'!E$144) -> 1 | F148: =COUNTIFS(Table1[Therapy area],'By therapy area'!$A148,Table1[Year],'By therapy area'!F$144) -> 0 | G148: =COUNTIFS(Table1[Therapy area],'By therapy area'!$A148,Table1[Year],'By therapy area'!G$144) -> 2 | H148: =SUM(B148:G148) -> 4 | I148: =H148/$H$154 -> 0.28571429
A149: ='HTA scientific advice'!L6 -> Various | B149: =COUNTIFS(Table1[Therapy area],'By therapy area'!$A149,Table1[Year],'By therapy area'!B$144) -> 1 | C149: =COUNTIFS(Table1[Therapy area],'By therapy area'!$A149,Table1[Year],'By therapy area'!C$144) -> 0 | D149: =COUNTIFS(Table1[Therapy area],'By therapy area'!$A149,Table1[Year],'By therapy area'!D$144) -> 0 | E149: =COUNTIFS(Table1[Therapy area],'By therapy area'!$A149,Table1[Year],'By therapy area'!E$144) -> 0 | F149: =COUNTIFS(Table1[Therapy area],'By therapy area'!$A149,Table1[Year],'By therapy area'!F$144) -> 0 | G149: =COUNTIFS(Table1[Therapy area],'By therapy area'!$A149,Table1[Year],'By therapy area'!G$144) -> 0 | H149: =SUM(B149:G149) -> 1 | I149: =H149/$H$154 -> 0.071428571
A150: ='HTA scientific advice'!L7 -> 0 | B150: =COUNTIFS(Table1[Therapy area],'By therapy area'!$A150,Table1[Year],'By therapy area'!B$144) -> 0 | C150: =COUNTIFS(Table1[Therapy area],'By therapy area'!$A150,Table1[Year],'By therapy area'!C$144) -> 0 | D150: =COUNTIFS(Table1[Therapy area],'By therapy area'!$A150,Table1[Year],'By therapy area'!D$144) -> 0 | E150: =COUNTIFS(Table1[Therapy area],'By therapy area'!$A150,Table1[Year],'By therapy area'!E$144) -> 0 | F150: =COUNTIFS(Table1[Therapy area],'By therapy area'!$A150,Table1[Year],'By therapy area'!F$144) -> 0 | G150: =COUNTIFS(Table1[Therapy area],'By therapy area'!$A150,Table1[Year],'By therapy area'!G$144) -> 0 | H150: =SUM(B150:G150) -> 0
A151: ='HTA scientific advice'!L8 -> 0 | B151: =COUNTIFS(Table1[Therapy area],'By therapy area'!$A151,Table1[Year],'By therapy area'!B$144) -> 0 | C151: =COUNTIFS(Table1[Therapy area],'By therapy area'!$A151,Table1[Year],'By therapy area'!C$144) -> 0 | D151: =COUNTIFS(Table1[Therapy area],'By therapy area'!$A151,Table1[Year],'By therapy area'!D$144) -> 0 | E151: =COUNTIFS(Table1[Therapy area],'By therapy area'!$A151,Table1[Year],'By therapy area'!E$144) -> 0 | F151: =COUNTIFS(Table1[Therapy area],'By therapy area'!$A151,Table1[Year],'By therapy area'!F$144) -> 0 | G151: =COUNTIFS(Table1[Therapy area],'By therapy area'!$A151,Table1[Year],'By therapy area'!G$144) -> 0 | H151: =SUM(B151:G151) -> 0
A152: ='HTA scientific advice'!L9 -> 0 | B152: =COUNTIFS(Table1[Therapy area],'By therapy area'!$A152,Table1[Year],'By therapy area'!B$144) -> 0 | C152: =COUNTIFS(Table1[Therapy area],'By therapy area'!$A152,Table1[Year],'By therapy area'!C$144) -> 0 | D152: =COUNTIFS(Table1[Therapy area],'By therapy area'!$A152,Table1[Year],'By therapy area'!D$144) -> 0 | E152: =COUNTIFS(Table1[Therapy area],'By therapy area'!$A152,Table1[Year],'By therapy area'!E$144) -> 0 | F152: =COUNTIFS(Table1[Therapy area],'By therapy area'!$A152,Table1[Year],'By therapy area'!F$144) -> 0 | G152: =COUNTIFS(Table1[Therapy area],'By therapy area'!$A152,Table1[Year],'By therapy area'!G$144) -> 0 | H152: =SUM(B152:G152) -> 0
A153: ='HTA scientific advice'!L10 -> 0 | B153: =COUNTIFS(Table1[Therapy area],'By therapy area'!$A153,Table1[Year],'By therapy area'!B$144) -> 0 | C153: =COUNTIFS(Table1[Therapy area],'By therapy area'!$A153,Table1[Year],'By therapy area'!C$144) -> 0 | D153: =COUNTIFS(Table1[Therapy area],'By therapy area'!$A153,Table1[Year],'By therapy area'!D$144) -> 0 | E153: =COUNTIFS(Table1[Therapy area],'By therapy area'!$A153,Table1[Year],'By therapy area'!E$144) -> 0 | F153: =COUNTIFS(Table1[Therapy area],'By therapy area'!$A153,Table1[Year],'By therapy area'!F$144) -> 0 | G153: =COUNTIFS(Table1[Therapy area],'By therapy area'!$A153,Table1[Year],'By therapy area'!G$144) -> 0 | H153: =SUM(B153:G153) -> 0
A154: Total | B154: =SUBTOTAL(109,B145:B153) -> 1 | C154: =SUBTOTAL(109,C145:C153) -> 1 | D154: =SUBTOTAL(109,D145:D153) -> 4 | E154: =SUBTOTAL(109,E145:E153) -> 1 | F154: =SUBTOTAL(109,F145:F153) -> 1 | G154: =SUBTOTAL(109,G145:G153) -> 6 | H154: =SUBTOTAL(109,H145:H153) -> 14 | I154: =H154/$H$154 -> 1
A189: GVDs
A190: GVDs by therapy area & Year
A191: Therapy area | B191: 2015 | C191: 2016 | D191: 2017 | E191: 2018 | F191: 2019 | G191: 2020 | H191: 2021 | I191: Total | J191: Percentage
A192: =GVDs!J2 -> Haematology | B192: =COUNTIFS(Table2[Therapy area],'By therapy area'!$A192,Table2[Year],'By therapy area'!B$191) -> 1 | C192: =COUNTIFS(Table2[Therapy area],'By therapy area'!$A192,Table2[Year],'By therapy area'!C$191) -> 0 | D192: =COUNTIFS(Table2[Therapy area],'By therapy area'!$A192,Table2[Year],'By therapy area'!D$191) -> 0 | E192: =COUNTIFS(Table2[Therapy area],'By therapy area'!$A192,Table2[Year],'By therapy area'!E$191) -> 0 | F192: =COUNTIFS(Table2[Therapy area],'By therapy area'!$A192,Table2[Year],'By therapy area'!F$191) -> 0 | G192: =COUNTIFS(Table2[Therapy area],'By therapy area'!$A192,Table2[Year],'By therapy area'!G$191) -> 0 | H192: =COUNTIFS(Table2[Therapy area],'By therapy area'!$A192,Table2[Year],'By therapy area'!H$191) -> 1 | I192: =SUM(B192:H192) -> 2 | J192: =I192/$I$209 -> 0.083333333
A193: =GVDs!J3 -> Haemato-oncology | B193: =COUNTIFS(Table2[Therapy area],'By therapy area'!$A193,Table2[Year],'By therapy area'!B$191) -> 1 | C193: =COUNTIFS(Table2[Therapy area],'By therapy area'!$A193,Table2[Year],'By therapy area'!C$191) -> 0 | D193: =COUNTIFS(Table2[Therapy area],'By therapy area'!$A193,Table2[Year],'By therapy area'!D$191) -> 0 | E193: =COUNTIFS(Table2[Therapy area],'By therapy area'!$A193,Table2[Year],'By therapy area'!E$191) -> 0 | F193: =COUNTIFS(Table2[Therapy area],'By therapy area'!$A193,Table2[Year],'By therapy area'!F$191) -> 0 | G193: =COUNTIFS(Table2[Therapy area],'By therapy area'!$A193,Table2[Year],'By therapy area'!G$191) -> 2 | H193: =COUNTIFS(Table2[Therapy area],'By therapy area'!$A193,Table2[Year],'By therapy area'!H$191) -> 0 | I193: =SUM(B193:H193) -> 3 | J193: =I193/$I$209 -> 0.125
A194: =GVDs!J4 -> Metabolic/Endocrine Disorders | B194: =COUNTIFS(Table2[Therapy area],'By therapy area'!$A194,Table2[Year],'By therapy area'!B$191) -> 1 | C194: =COUNTIFS(Table2[Therapy area],'By therapy area'!$A194,Table2[Year],'By therapy area'!C$191) -> 1 | D194: =COUNTIFS(Table2[Therapy area],'By therapy area'!$A194,Table2[Year],'By therapy area'!D$191) -> 0 | E194: =COUNTIFS(Table2[Therapy area],'By therapy area'!$A194,Table2[Year],'By therapy area'!E$191) -> 1 | F194: =COUNTIFS(Table2[Therapy area],'By therapy area'!$A194,Table2[Year],'By therapy area'!F$191) -> 0 | G194: =COUNTIFS(Table2[Therapy area],'By therapy area'!$A194,Table2[Year],'By therapy area'!G$191) -> 0 | H194: =COUNTIFS(Table2[Therapy area],'By therapy area'!$A194,Table2[Year],'By therapy area'!H$191) -> 0 | I194: =SUM(B194:H194) -> 3 | J194: =I194/$I$209 -> 0.125
A195: =GVDs!J5 -> Cardiorenal/Metabolic | B195: =COUNTIFS(Table2[Therapy area],'By therapy area'!$A195,Table2[Year],'By therapy area'!B$191) -> 0 | C195: =COUNTIFS(Table2[Therapy area],'By therapy area'!$A195,Table2[Year],'By therapy area'!C$191) -> 1 | D195: =COUNTIFS(Table2[Therapy area],'By therapy area'!$A195,Table2[Year],'By therapy area'!D$191) -> 0 | E195: =COUNTIFS(Table2[Therapy area],'By therapy area'!$A195,Table2[Year],'By therapy area'!E$191) -> 0 | F195: =COUNTIFS(Table2[Therapy area],'By therapy area'!$A195,Table2[Year],'By therapy area'!F$191) -> 0 | G195: =COUNTIFS(Table2[Therapy area],'By therapy area'!$A195,Table2[Year],'By therapy area'!G$191) -> 0 | H195: =COUNTIFS(Table2[Therapy area],'By therapy area'!$A195,Table2[Year],'By therapy area'!H$191) -> 0 | I195: =SUM(B195:H195) -> 1 | J195: =I195/$I$209 -> 0.041666667
A196: =GVDs!J6 -> Oncology | B196: =COUNTIFS(Table2[Therapy area],'By therapy area'!$A196,Table2[Year],'By therapy area'!B$191) -> 0 | C196: =COUNTIFS(Table2[Therapy area],'By therapy area'!$A196,Table2[Year],'By therapy area'!C$191) -> 0 | D196: =COUNTIFS(Table2[Therapy area],'By therapy area'!$A196,Table2[Year],'By therapy area'!D$191) -> 2 | E196: =COUNTIFS(Table2[Therapy area],'By therapy area'!$A196,Table2[Year],'By therapy area'!E$191) -> 2 | F196: =COUNTIFS(Table2[Therapy area],'By therapy area'!$A196,Table2[Year],'By therapy area'!F$191) -> 1 | G196: =COUNTIFS(Table2[Therapy area],'By therapy area'!$A196,Table2[Year],'By therapy area'!G$191) -> 1 | H196: =COUNTIFS(Table2[Therapy area],'By therapy area'!$A196,Table2[Year],'By therapy area'!H$191) -> 1 | I196: =SUM(B196:H196) -> 7 | J196: =I196/$I$209 -> 0.29166667
A197: =GVDs!J7 -> Respiratory | B197: =COUNTIFS(Table2[Therapy area],'By therapy area'!$A197,Table2[Year],'By therapy area'!B$191) -> 0 | C197: =COUNTIFS(Table2[Therapy area],'By therapy area'!$A197,Table2[Year],'By therapy area'!C$191) -> 0 | D197: =COUNTIFS(Table2[Therapy area],'By therapy area'!$A197,Table2[Year],'By therapy area'!D$191) -> 2 | E197: =COUNTIFS(Table2[Therapy area],'By therapy area'!$A197,Table2[Year],'By therapy area'!E$191) -> 0 | F197: =COUNTIFS(Table2[Therapy area],'By therapy area'!$A197,Table2[Year],'By therapy area'!F$191) -> 0 | G197: =COUNTIFS(Table2[Therapy area],'By therapy area'!$A197,Table2[Year],'By therapy area'!G$191) -> 0 | H197: =COUNTIFS(Table2[Therapy area],'By therapy area'!$A197,Table2[Year],'By therapy area'!H$191) -> 0 | I197: =SUM(B197:H197) -> 2 | J197: =I197/$I$209 -> 0.083333333
A198: =GVDs!J8 -> Central nervous system | B198: =COUNTIFS(Table2[Therapy area],'By therapy area'!$A198,Table2[Year],'By therapy area'!B$191) -> 0 | C198: =COUNTIFS(Table2[Therapy area],'By therapy area'!$A198,Table2[Year],'By therapy area'!C$191) -> 0 | D198: =COUNTIFS(Table2[Therapy area],'By therapy area'!$A198,Table2[Year],'By therapy area'!D$191) -> 0 | E198: =COUNTIFS(Table2[Therapy area],'By therapy area'!$A198,Table2[Year],'By therapy area'!E$191) -> 1 | F198: =COUNTIFS(Table2[Therapy area],'By therapy area'!$A198,Table2[Year],'By therapy area'!F$191) -> 1 | G198: =COUNTIFS(Table2[Therapy area],'By therapy area'!$A198,Table2[Year],'By therapy area'!G$191) -> 0 | H198: =COUNTIFS(Table2[Therapy area],'By therapy area'!$A198,Table2[Year],'By therapy area'!H$191) -> 0 | I198: =SUM(B198:H198) -> 2 | J198: =I198/$I$209 -> 0.083333333
A199: =GVDs!J9 -> Infectious diseases | B199: =COUNTIFS(Table2[Therapy area],'By therapy area'!$A199,Table2[Year],'By therapy area'!B$191) -> 0 | C199: =COUNTIFS(Table2[Therapy area],'By therapy area'!$A199,Table2[Year],'By therapy area'!C$191) -> 0 | D199: =COUNTIFS(Table2[Therapy area],'By therapy area'!$A199,Table2[Year],'By therapy area'!D$191) -> 0 | E199: =COUNTIFS(Table2[Therapy area],'By therapy area'!$A199,Table2[Year],'By therapy area'!E$191) -> 1 | F199: =COUNTIFS(Table2[Therapy area],'By therapy area'!$A199,Table2[Year],'By therapy area'!F$191) -> 1 | G199: =COUNTIFS(Table2[Therapy area],'By therapy area'!$A199,Table2[Year],'By therapy area'!G$191) -> 0 | H199: =COUNTIFS(Table2[Therapy area],'By therapy area'!$A199,Table2[Year],'By therapy area'!H$191) -> 1 | I199: =SUM(B199:H199) -> 3 | J199: =I199/$I$209 -> 0.125
A200: =GVDs!J10 -> Mental illness | B200: =COUNTIFS(Table2[Therapy area],'By therapy area'!$A200,Table2[Year],'By therapy area'!B$191) -> 0 | C200: =COUNTIFS(Table2[Therapy area],'By therapy area'!$A200,Table2[Year],'By therapy area'!C$191) -> 0 | D200: =COUNTIFS(Table2[Therapy area],'By therapy area'!$A200,Table2[Year],'By therapy area'!D$191) -> 0 | E200: =COUNTIFS(Table2[Therapy area],'By therapy area'!$A200,Table2[Year],'By therapy area'!E$191) -> 1 | F200: =COUNTIFS(Table2[Therapy area],'By therapy area'!$A200,Table2[Year],'By therapy area'!F$191) -> 0 | G200: =COUNTIFS(Table2[Therapy area],'By therapy area'!$A200,Table2[Year],'By therapy area'!G$191) -> 0 | H200: =COUNTIFS(Table2[Therapy area],'By therapy area'!$A200,Table2[Year],'By therapy area'!H$191) -> 0 | I200: =SUM(B200:H200) -> 1 | J200: =I200/$I$209 -> 0.041666667
A201: =GVDs!J11 -> 0 | B201: =COUNTIFS(Table2[Therapy area],'By therapy area'!$A201,Table2[Year],'By therapy area'!B$191) -> 0 | C201: =COUNTIFS(Table2[Therapy area],'By therapy area'!$A201,Table2[Year],'By therapy area'!C$191) -> 0 | D201: =COUNTIFS(Table2[Therapy area],'By therapy area'!$A201,Table2[Year],'By therapy area'!D$191) -> 0 | E201: =COUNTIFS(Table2[Therapy area],'By therapy area'!$A201,Table2[Year],'By therapy area'!E$191) -> 0 | F201: =COUNTIFS(Table2[Therapy area],'By therapy area'!$A201,Table2[Year],'By therapy area'!F$191) -> 0 | G201: =COUNTIFS(Table2[Therapy area],'By therapy area'!$A201,Table2[Year],'By therapy area'!G$191) -> 0 | H201: =COUNTIFS(Table2[Therapy area],'By therapy area'!$A201,Table2[Year],'By therapy area'!H$191) -> 0 | I201: =SUM(B201:H201) -> 0
A202: =GVDs!J12 -> 0 | B202: =COUNTIFS(Table2[Therapy area],'By therapy area'!$A202,Table2[Year],'By therapy area'!B$191) -> 0 | C202: =COUNTIFS(Table2[Therapy area],'By therapy area'!$A202,Table2[Year],'By therapy area'!C$191) -> 0 | D202: =COUNTIFS(Table2[Therapy area],'By therapy area'!$A202,Table2[Year],'By therapy area'!D$191) -> 0 | E202: =COUNTIFS(Table2[Therapy area],'By therapy area'!$A202,Table2[Year],'By therapy area'!E$191) -> 0 | F202: =COUNTIFS(Table2[Therapy area],'By therapy area'!$A202,Table2[Year],'By therapy area'!F$191) -> 0 | G202: =COUNTIFS(Table2[Therapy area],'By therapy area'!$A202,Table2[Year],'By therapy area'!G$191) -> 0 | H202: =COUNTIFS(Table2[Therapy area],'By therapy area'!$A202,Table2[Year],'By therapy area'!H$191) -> 0 | I202: =SUM(B202:H202) -> 0
A203: =GVDs!J13 -> 0 | B203: =COUNTIFS(Table2[Therapy area],'By therapy area'!$A203,Table2[Year],'By therapy area'!B$191) -> 0 | C203: =COUNTIFS(Table2[Therapy area],'By therapy area'!$A203,Table2[Year],'By therapy area'!C$191) -> 0 | D203: =COUNTIFS(Table2[Therapy area],'By therapy area'!$A203,Table2[Year],'By therapy area'!D$191) -> 0 | E203: =COUNTIFS(Table2[Therapy area],'By therapy area'!$A203,Table2[Year],'By therapy area'!E$191) -> 0 | F203: =COUNTIFS(Table2[Therapy area],'By therapy area'!$A203,Table2[Year],'By therapy area'!F$191) -> 0 | G203: =COUNTIFS(Table2[Therapy area],'By therapy area'!$A203,Table2[Year],'By therapy area'!G$191) -> 0 | H203: =COUNTIFS(Table2[Therapy area],'By therapy area'!$A203,Table2[Year],'By therapy area'!H$191) -> 0 | I203: =SUM(B203:H203) -> 0
A204: =GVDs!J14 -> 0 | B204: =COUNTIFS(Table2[Therapy area],'By therapy area'!$A204,Table2[Year],'By therapy area'!B$191) -> 0 | C204: =COUNTIFS(Table2[Therapy area],'By therapy area'!$A204,Table2[Year],'By therapy area'!C$191) -> 0 | D204: =COUNTIFS(Table2[Therapy area],'By therapy area'!$A204,Table2[Year],'By therapy area'!D$191) -> 0 | E204: =COUNTIFS(Table2[Therapy area],'By therapy area'!$A204,Table2[Year],'By therapy area'!E$191) -> 0 | F204: =COUNTIFS(Table2[Therapy area],'By therapy area'!$A204,Table2[Year],'By therapy area'!F$191) -> 0 | G204: =COUNTIFS(Table2[Therapy area],'By therapy area'!$A204,Table2[Year],'By therapy area'!G$191) -> 0 | H204: =COUNTIFS(Table2[Therapy area],'By therapy area'!$A204,Table2[Year],'By therapy area'!H$191) -> 0 | I204: =SUM(B204:H204) -> 0
A205: =GVDs!J15 -> 0 | B205: =COUNTIFS(Table2[Therapy area],'By therapy area'!$A205,Table2[Year],'By therapy area'!B$191) -> 0 | C205: =COUNTIFS(Table2[Therapy area],'By therapy area'!$A205,Table2[Year],'By therapy area'!C$191) -> 0 | D205: =COUNTIFS(Table2[Therapy area],'By therapy area'!$A205,Table2[Year],'By therapy area'!D$191) -> 0 | E205: =COUNTIFS(Table2[Therapy area],'By therapy area'!$A205,Table2[Year],'By therapy area'!E$191) -> 0 | F205: =COUNTIFS(Table2[Therapy area],'By therapy area'!$A205,Table2[Year],'By therapy area'!F$191) -> 0 | G205: =COUNTIFS(Table2[Therapy area],'By therapy area'!$A205,Table2[Year],'By therapy area'!G$191) -> 0 | H205: =COUNTIFS(Table2[Therapy area],'By therapy area'!$A205,Table2[Year],'By therapy area'!H$191) -> 0 | I205: =SUM(B205:H205) -> 0
A206: =GVDs!J16 -> 0 | B206: =COUNTIFS(Table2[Therapy area],'By therapy area'!$A206,Table2[Year],'By therapy area'!B$191) -> 0 | C206: =COUNTIFS(Table2[Therapy area],'By therapy area'!$A206,Table2[Year],'By therapy area'!C$191) -> 0 | D206: =COUNTIFS(Table2[Therapy area],'By therapy area'!$A206,Table2[Year],'By therapy area'!D$191) -> 0 | E206: =COUNTIFS(Table2[Therapy area],'By therapy area'!$A206,Table2[Year],'By therapy area'!E$191) -> 0 | F206: =COUNTIFS(Table2[Therapy area],'By therapy area'!$A206,Table2[Year],'By therapy area'!F$191) -> 0 | G206: =COUNTIFS(Table2[Therapy area],'By therapy area'!$A206,Table2[Year],'By therapy area'!G$191) -> 0 | H206: =COUNTIFS(Table2[Therapy area],'By therapy area'!$A206,Table2[Year],'By therapy area'!H$191) -> 0 | I206: =SUM(B206:H206) -> 0
A207: =GVDs!J17 -> 0 | B207: =COUNTIFS(Table2[Therapy area],'By therapy area'!$A207,Table2[Year],'By therapy area'!B$191) -> 0 | C207: =COUNTIFS(Table2[Therapy area],'By therapy area'!$A207,Table2[Year],'By therapy area'!C$191) -> 0 | D207: =COUNTIFS(Table2[Therapy area],'By therapy area'!$A207,Table2[Year],'By therapy area'!D$191) -> 0 | E207: =COUNTIFS(Table2[Therapy area],'By therapy area'!$A207,Table2[Year],'By therapy area'!E$191) -> 0 | F207: =COUNTIFS(Table2[Therapy area],'By therapy area'!$A207,Table2[Year],'By therapy area'!F$191) -> 0 | G207: =COUNTIFS(Table2[Therapy area],'By therapy area'!$A207,Table2[Year],'By therapy area'!G$191) -> 0 | H207: =COUNTIFS(Table2[Therapy area],'By therapy area'!$A207,Table2[Year],'By therapy area'!H$191) -> 0 | I207: =SUM(B207:H207) -> 0
A208: =GVDs!J18 -> 0 | B208: =COUNTIFS(Table2[Therapy area],'By therapy area'!$A208,Table2[Year],'By therapy area'!B$191) -> 0 | C208: =COUNTIFS(Table2[Therapy area],'By therapy area'!$A208,Table2[Year],'By therapy area'!C$191) -> 0 | D208: =COUNTIFS(Table2[Therapy area],'By therapy area'!$A208,Table2[Year],'By therapy area'!D$191) -> 0 | E208: =COUNTIFS(Table2[Therapy area],'By therapy area'!$A208,Table2[Year],'By therapy area'!E$191) -> 0 | F208: =COUNTIFS(Table2[Therapy area],'By therapy area'!$A208,Table2[Year],'By therapy area'!F$191) -> 0 | G208: =COUNTIFS(Table2[Therapy area],'By therapy area'!$A208,Table2[Year],'By therapy area'!G$191) -> 0 | H208: =COUNTIFS(Table2[Therapy area],'By therapy area'!$A208,Table2[Year],'By therapy area'!H$191) -> 0 | I208: =SUM(B208:H208) -> 0 | J208: =I208/$I$209 -> 0
A209: Total | B209: =SUM(B192:B208) -> 3 | C209: =SUM(C192:C208) -> 2 | D209: =SUM(D192:D208) -> 4 | E209: =SUM(E192:E208) -> 6 | F209: =SUM(F192:F208) -> 3 | G209: =SUM(G192:G208) -> 3 | H209: =SUM(H192:H208) -> 3 | I209: =SUM(B209:H209) -> 24 | J209: =I209/$I$209 -> 1
